Workbook

Sheet Легенда
A1: № плц | B1: выработанные рецепты в указанную дату
A2: наимен рецепта
A3: дата
A5: № плц | B5: поставленные на выработку рецепты
A6: наимен рецепта
A7: дата
A9: № плц | B9: планируемые на выработку рецепты
A10: наимен рецепта
A11: дата
A13: число | B13: планировать закупку
A14: число | B14: перевезти с Липковской или закупить
A15: отр. число | B15: СРОЧНО ЗАКУПАТЬ!!!!

Sheet 1_квартал
GQ1: число | GR1: планировать закупку, держать на контроле | GU1: п. - партия
A2: число | B2: остатки, которые надо закрыть | GQ2: число | GR2: перевезти с Липковской или закупить
A3: число | B3: на пересчет рецепта | GQ3: отр. число | GR3: СРОЧНО ЗАКУПАТЬ!!!!
J4: ФАКТ | FW4: ПЛАН | GI4: КАЗАХСТАН
A5: № п/п | B5: сырье | C5: Полоцк КХП | G5: СРЕДНЕМЕСЯЧНЫЙ РАСХОД за текущий квартал | J5: январь | K5: 2 | L5: 3 | M5: 7 | N5: 9 | O5: 10 | P5: 11 | Q5: 12 | R5: 14 | S5: 13 | T5: 16 | U5: 17 | V5: 14 | W5: 21 | X5: 15 | Y5: 28 | Z5: 15 | AA5: 25 | AB5: 24 | AC5: 26 | AD5: 40 | AE5: 44 | AF5: 45 | AG5: 46 | AH5: 37 | AI5: 30 | AJ5: 50 | AK5: 12 | AL5: 43 | AM5: 15 | AN5: 38 | AO5: 11 | AP5: 29 | AQ5: 42 | AR5: 60 | AS5: 61 | AT5: 62 | AU5: 33 | AV5: 53 | AW5: 3 | AX5: 48 | AY5: 35 | AZ5: 36 | BA5: 34 | BB5: 32 | BC5: 51 А | BD5: 52 | BE5: 10 | BF5: 27 | BG5: 71 | BH5: 16 | BI5: 25 | BJ5: Расход за мес. (оперативный) | BK5: февраль | BL5: 74 | BM5: 13 | BN5: 68 | BO5: 70 | BP5: 73 | BQ5: 67 | BR5: 85 | BS5: 24 | BT5: 89 | BU5: 93 | BV5: 94 | BW5: 95 | BX5: 24 | BY5: 92 | BZ5: 97 | CA5: 91 | CB5: 75 | CC5: 101 | CD5: 91 | CE5: 103 | CF5: 90 | CG5: 106 | CH5: 107 | CI5: 108 | CJ5: 113 | CK5: 42 | CL5: 115 | CM5: 117 | CN5: 76 | CO5: 123 | CP5: 68 | CQ5: 124 | CR5: 116 | CS5: 41 | CT5: 112 | CU5: 110 | CV5: 111 | CW5: 49 | CX5: 126 | CY5: 98 | CZ5: 42 | DA5: 130 | DB5: 50 | DC5: 129 | DD5: 128 | DE5: 127 | DF5: 114 | DG5: 135 | DH5: 136 | DI5: 134 | DJ5: 139 | DK5: 46 | DL5: 142 | DM5: 141 | DN5: 135 | DO5: 136 | DP5: 134 | DQ5: 55 | DR5: 137 | DS5: Расход за текущий мес. (оперативный) | DT5: март | DU5: 144 | DV5: 150 | DW5: 151 | DX5: 42 | DY5: 145 | DZ5: 156 | EA5: 162 | EB5: 161 | EC5: 163 | ED5: 164 | EE5: 165 | EF5: 166 | EG5: 168 | EH5: 169 | EI5: 135 | EJ5: 136 | EK5: 158 | EL5: 171 | EM5: 20 | EN5: 134 | EO5: 135 | EP5: 136 | EQ5: 167 | ER5: 23 | ES5: 136 | ET5: 172 | EU5: 173 | EV5: 179 | EW5: 50 | EX5: 129 | EY5: 130 | EZ5: 182 | FA5: 68 | FB5: 185 | FC5: 183 | FD5: 178 | FE5: 42 | FF5: 191 | FG5: 184 | FH5: 198 | FI5: 191 | FJ5: 161 | FK5: 199 | FL5: 135 | FM5: 160 | FN5: 190 | FO5: 204 | FP5: 193 | FQ5: 193 | FR5: 194 | FS5: 208 | FT5: 168 | FU5: Расход за текущий мес. (оперативный) | GP5: ИТОГО | GQ5: Остаток на Полоцке после произв-ва | GR5: Запас на ОТЧЕТНУЮ дату | GS5: =G5 -> СРЕДНЕМЕСЯЧНЫЙ РАСХОД за текущий квартал | GT5: РАСХОД ЗА предыдущий месяц | GV5: годность | GW5: запас в месяцах
C6: декабрь | D6: январь | E6: февраль | F6: март | H6: Остаток на начало месяца | I6: Остаток ЗА ОТЧЕТНУЮ дату | K6: ДП60-3, дойное, Бакуново | L6: ДП60-3, дойное, АгроСолы | M6: ДП60-3 дойное, Савушкина пуща | N6: ДП60-3 дойное Мумуша, Агро-Детковичи, БИРЖА | O6: ДП60-3 1й сух, Свитязянка | P6: ДП60-3 2й сух, Свитязянка | Q6: ДП60-3 НОВОТЕЛ, Свитязянка | R6: ДП60-3 2й сух, Савушкина пуща, Савушкино | S6: ДП60-3 дойное Мумуша (ДейриБаланс), Макарово-агро, БИРЖА | T6: ДП60-3 1й сух, Савушкино | U6: ДП60-3 НОВОТЕЛ, Городилово | V6: ДП60-3 2й сух, Савушкино | W6: ДП60-3 дойное, Киселёвцы | X6: ДП60-3 НОВОТЕЛ, Савушкино | Y6: ДП60-3, дойное, Осовецкий | Z6: ДП60-3 НОВОТЕЛ, Савушкина пуща | AA6: ДП60-3 2й сух, Савушкина пуща | AB6: ДП60-3 НОВОТЕЛ, Савушкина пуща | AC6: ДП60-3 дойное, Савушкина пуща | AD6: ДП60-3 мастит, Видомлянское | AE6: ДП60-3 1й сух, Зеленевичи | AF6: ДП60-3 2й сух, Зеленевичи | AG6: ДП60-3 НОВОТЕЛ, Зеленевичи | AH6: ДП60-3 НОВОТЕЛ, Восх.заря | AI6: ДП60-3 дойное, Восх.заря | AJ6: ДП60-3 дойное Мумуша, Зеленевичи | AK6: ДПКР-2, Калф, Восх.заря | AL6: ДП60-3 НОВОТЕЛ, ФХ Юлиан | AM6: ДПКР-2 Хайфер, ФХ Юлиан | AN6: ДП60-3 2й сух, Восх.заря | AO6: ДПКР-2 Хайфер, Восх.заря | AP6: ДП60-3 1й сух, Восх. Заря | AQ6: ДП60-3 2й сух, ФХ Юлиан | AR6: ДП60-3 2й сух, Осовецкий | AS6: ДП60-3 НОВОТЕЛ, Осовецкий | AT6: ДП60-3 1й сух, Осовецкий | AU6: ДП60-3 2й сух, Бакуново | AV6: ДП60-3 1й сух, Шапчицы | AW6: ДП60-3, дойное, АгроСолы | AX6: ДП60-3 дойное Мумуша, с-з Минский | AY6: ДП60-3 1й сух, АгроМилк, БИРЖА | AZ6: ДП60-3 2й сух, АгроМилк, БИРЖА | BA6: ДП60-3 НОВОТЕЛ, АгроМилк, БИРЖА | BB6: ДП60-3 НОВОТЕЛ, Бакуново | BC6: ДП60-3 дойное 1 Мая | BD6: ДП60-3 1й сух 1 Мая | BE6: ДПКР-1 Мумуша в к/к Восх.заря, ФХ Юлиан | BF6: ДПКР-2, в к/к | BG6: ДП60-3 дойное, Савушкина пуща | BH6: ДП60-3 1й сух, Утес | BI6: ДП60-3 2й сух, Утес | BL6: ДП60-3 дойное, Полесская нива | BM6: ДП60-3 дойное Мумуша (ДейриБаланс), Макарово-агро, БИРЖА | BN6: ДП60-3 1й сух, ФХ Юлиан | BO6: ДП60-3 дойное, ФХ Юлиан | BP6: ДП60-3 1й сух, Полесская нива | BQ6: ДП60-3 дойное Мумуша, Лебедева Ветка | BR6: ДП60-3 2й сух, Журавлиное, БИРЖА | BS6: ДП60-3 НОВОТЕЛ, Савушкино | BT6: ДП60-3 дойное, Агросолы | BU6: ДП60-3 дойное, Киселевцы | BV6: ДП60-3 2й сух, Киселевцы | BW6: ДП60-3 2й сух Мумуша, Припять-2009, БИРЖА | BX6: ДП60-3 НОВОТЕЛ, Савушкино | BY6: ДП60-3 НОВОТЕЛ, Городилово | BZ6: ДП60-3 1й сух, Савушкино | CA6: ДП60-3 2й сух, Савушкино | CB6: ДП60-3 дойное, Бакуново | CC6: ДП60-3 дойное Мумуша, Минский | CD6: ДП60-3 2й сух, Савушкина пуща | CE6: ДП60-3 1й сух, Шапчицы | CF6: ДП60-3 НОВОТЕЛ, Савушкина пуща | CG6: ДП60-3 1й сух, Свитязянка | CH6: ДП60-3 2й сух, Свитязянка | CI6: ДП60-3 НОВОТЕЛ, Свитязянка | CJ6: ДП60-3 дойное, Осовецкий | CK6: ДПКР-2 Хайфер, ФХ Юлиан | CL6: ДП60-3 2й сух, ФХ Юлиан | CM6: ДП60-3 НОВОТЕЛ, ФХ Юлиан | CN6: ДП60-3 дойное Мумуша, Агро-Детковичи, БИРЖА | CO6: ДП60-3 НОВОТЕЛ, Городилово | CP6: ДП60-3 1й сух, ФХ Юлиан | CQ6: ДП60-3 дойное, Агросолы | CR6: ДП60-3 1й сух, Минский | CS6: ДПКР-2, КАЗАХСТАН | CT6: ДП60-3 дойное, КАЗАХСТАН | CU6: ДП60-3 1й сух, КАЗАХСТАН | CV6: ДП60-3 2й сух, КАЗАХСТАН | CW6: ПКР-2, Газовик-Сипаково, БИРЖА | CX6: ДП60-3 дойное, Савушкина пуща | CY6: ДП60-3 ЭНЕРГЕТИК | CZ6: ДПКР-2 Хайфер, Восх.заря | DA6: ДП60-3 1й сух, Восх. Заря | DB6: ДПКР-2, Калф, Восх.заря | DC6: ДП60-3 дойное, Восх.заря | DD6: ДП60-3 НОВОТЕЛ, Восх.заря | DE6: ДП60-3 2й сух, Восх.заря | DF6: ДП60-3 2й сух, Бакуново | DG6: ДП60-3 1й сух, С-з Минский | DH6: ДП60-3 2й сух, С-з Минский | DI6: ДП60-3 НОВОТЕЛ, С-з Минский | DJ6: ДП60-3 Мумуша, дойное (ДейриБаланс) Макарово, БИРЖА | DK6: ДПКР-2, в к/к ФХ Юлиан | DL6: ДП60-3 дойное, с-з Минский | DM6: ДП60-3 дойное, Бакуново | DN6: ДП60-3 1й сух, Савушкино | DO6: ДП60-3 2й сух, Савушкино | DP6: ДП60-3 НОВОТЕЛ, Савушкино | DQ6: ДПКР-2, Орешковичи | DR6: ДП60-3 транзит, в к/к Сестричество | DU6: ДП60-3 дойное, ФХ Юлиан | DV6: ДП60-3 дойное, Киселевцы | DW6: ДП60-3 2й сух, Киселевцы | DX6: ДПКР-2 Хайфер, ФХ Юлиан | DY6: ДП60-3 1й сух, ФХ Юлиан | DZ6: ДП60-3 Анионные соли, Киселевцы | EA6: ДП60-3 2й сух, Видомлянское | EB6: ДП60-3 дойное, Савушкина пуща | EC6: ДП60-3 1й сух, Осовецкий | ED6: ДП60-3 2й сух, Осовецкий | EE6: ДП60-3 НОВОТЕЛ, Осовецкий | EF6: ДП60-3 НОВОТЕЛ, Орешковичи | EG6: ДП60-3 2й сух, Припять-2009, БИРЖА | EH6: ДП60-3 дойное Мумуша, Агро-Детковичи, БИРЖА | EI6: ДП60-3 1й сух, Утес | EJ6: ДП60-3 2й сух, Утес | EK6: ДП60-3 2й сух, Бакуново | EL6: ДП60-3 2й сух, Лебедева Ветка | EM6: ДПКР-1, Мумуша в к/к Восх.заря | EN6: ДП60-3 НОВОТЕЛ, Савушкина пуща | EO6: ДП60-3 1й сух, Савушкина пуща | EP6: ДП60-3 2й сух, Савушкина пуща | EQ6: ДП60-3 дойное, Агро-Солы | ER6: ДПКР-1 Мумуша в к/к КАЗАХСТАН | ES6: ДП60-3 2й сух, Савушкина пуща | ET6: ДП60-3 НОВОТЕЛ, ФХ Юлиан | EU6: ДП60-3 2й сух, ФХ Юлиан | EV6: ДП60-3 2й сух, Восх.заря | EW6: ДПКР-2, Калф, Восх.заря | EX6: ДП60-3 дойное, Восх.заря | EY6: ДП60-3 1й сух, Восх. Заря | EZ6: ДП60-3 НОВОТЕЛ, КАЗАХСТАН | FA6: ДПКР-2, КАЗАХСТАН | FB6: ДП60-3 2й сух, Свитязянка | FC6: ДП60-3 дойное, Осовецкий | FD6: ДП60-3 НОВОТЕЛ, Восх.заря | FE6: ДПКР-2 Хайфер, ФХ Юлиан | FF6: ДП60-3 дойное, Киселевцы | FG6: ДП60-3 дойное МУМУША, Видомлянское | FH6: ДП60-3 Биохром, ФХ Юлиан | FI6: ДП60-3 дойное, Киселевцы | FJ6: ДП60-3 дойное, Савушкина пуща (склад) | FK6: ДП60-3 дойное, Бакуново | FL6: ДП60-3 1й сух, Неверовичи | FM6: ДП60-3 1й сух, Шапчицы | FN6: ДП60-3 АС, 1 Мая | FO6: ДП60-3 НОВОТЕЛ, Неверовичи | FP6: ДП60-3 дойное Мумуша, Лебедева Ветка, БИРЖА | FQ6: ДП60-3 дойное Мумуша, Лебедева Ветка, БИРЖА | FR6: ДП60-3 1й сух, Лебедева Ветка, БИРЖА | FS6: ДП60-3 2й сух, Лебедева Ветка, БИРЖА | FT6: ДП60-3 2й сух, Припять-2009, БИРЖА | GO6: Отгрузка
B7: дата выработки/планирования | C7: 2025 | D7: 2026 | H7: 46082 | I7: 46112 | K7: 46027 | L7: 46028 | M7: 46030 | N7: 46031 | O7: 46031 | P7: 46031 | Q7: 46031 | R7: 46034 | S7: 46035 | T7: 46035 | U7: 46035 | V7: 46036 | W7: 46036 | X7: 46037 | Y7: 46038 | Z7: 46041 | AA7: 46041 | AB7: 46042 | AC7: 46043 | AD7: 46044 | AE7: 46044 | AF7: 46044 | AG7: 46044 | AH7: 46045 | AI7: 46048 | AJ7: 46048 | AK7: 46048 | AL7: 46048 | AM7: 46049 | AN7: 46049 | AO7: 46049 | AP7: 46049 | AQ7: 46049 | AR7: 46050 | AS7: 46050 | AT7: 46050 | AU7: 46050 | AV7: 46050 | AW7: 46050 | AX7: 46050 | AY7: 46051 | AZ7: 46051 | BA7: 46051 | BB7: 46051 | BC7: 46051 | BD7: 46051 | BE7: 46051 | BF7: 46051 | BG7: 46052 | BH7: 46052 | BI7: 46052 | BJ7: январь | BL7: 46055 | BM7: 46055 | BN7: 46056 | BO7: 46056 | BP7: 46056 | BQ7: 46056 | BR7: 46057 | BS7: 46058 | BT7: 46058 | BU7: 46059 | BV7: 46059 | BW7: 46059 | BX7: 46059 | BY7: 46059 | BZ7: 46059 | CA7: 46059 | CB7: 46062 | CC7: 46062 | CD7: 46062 | CE7: 46063 | CF7: 46063 | CG7: 46064 | CH7: 46064 | CI7: 46064 | CJ7: 46065 | CK7: 46066 | CL7: 46066 | CM7: 46066 | CN7: 46066 | CO7: 46069 | CP7: 46069 | CQ7: 46069 | CR7: 46069 | CS7: 46069 | CT7: 46070 | CU7: 46071 | CV7: 46071 | CW7: 46071 | CX7: 46072 | CY7: 46072 | CZ7: 46073 | DA7: 46073 | DB7: 46073 | DC7: 46073 | DD7: 46076 | DE7: 46076 | DF7: 46076 | DG7: 46076 | DH7: 46076 | DI7: 46076 | DJ7: 46077 | DK7: 46077 | DL7: 46077 | DM7: 46078 | DN7: 46079 | DO7: 46079 | DP7: 46079 | DQ7: 46079 | DR7: 46079 | DS7: февраль | DU7: 46083 | DV7: 46084 | DW7: 46084 | DX7: 46085 | DY7: 46085 | DZ7: 46086 | EA7: 46086 | EB7: 46087 | EC7: 46092 | ED7: 46092 | EE7: 46092 | EF7: 46092 | EG7: 46092 | EH7: 46092 | EI7: 46092 | EJ7: 46092 | EK7: 46093 | EL7: 46093 | EM7: 46093 | EN7: 46094 | EO7: 46097 | EP7: 46098 | EQ7: 46098 | ER7: 46098 | ES7: 46099 | ET7: 46099 | EU7: 46099 | EV7: 46099 | EW7: 46099 | EX7: 46100 | EY7: 46100 | EZ7: 46101 | FA7: 46104 | FB7: 46104 | FC7: 46104 | FD7: 46104 | FE7: 46105 | FF7: 46105 | FG7: 46106 | FH7: 46106 | FI7: 46106 | FJ7: 46107 | FK7: 46108 | FL7: 46108 | FM7: 46108 | FN7: 46108 | FO7: 46111 | FP7: 46111 | FQ7: 46112 | FR7: 46112 | FS7: 46112 | FT7: 46112 | FU7: март | GR7: =I7 -> 46112
B8: Выработка, т | C8: 154.95 | D8: =BJ8 -> 113.2 | E8: =DS8 -> 148.8 | F8: =FU8 -> 108.2 | K8: =1*3 -> 3 | L8: 3 | M8: =1*8 -> 8 | N8: 3.5 | O8: 0.8 | P8: =1 -> 1 | Q8: 1.5 | R8: =1*3 -> 3 | S8: =1*1.6 -> 1.6 | T8: 1 | U8: =1*1.5 -> 1.5 | V8: =1*4 -> 4 | W8: =1*1.5 -> 1.5 | X8: =1*7 -> 7 | Y8: =1*3 -> 3 | Z8: =1*2 -> 2 | AA8: =1*4 -> 4 | AB8: =1*8 -> 8 | AC8: =1*6 -> 6 | AD8: 0.6 | AE8: 1.2 | AF8: 0.8 | AG8: 0.8 | AH8: 3 | AI8: =1*4 -> 4 | AJ8: 2.3 | AK8: 1 | AL8: 0.6 | AM8: 0.8 | AN8: 1 | AO8: =1*2 -> 2 | AP8: =1*1.3 -> 1.3 | AQ8: 0.9 | AR8: 0.4 | AS8: 0.6 | AT8: 1 | AU8: 1 | AV8: =1 -> 1 | AW8: 3 | AX8: =1*1.2 -> 1.2 | AY8: 1.5 | AZ8: 2 | BA8: 2 | BB8: 1 | BC8: =0.3 -> 0.3 | BD8: =0.3/0.3 -> 1 | BE8: 1.5 | BF8: 0.3 | BG8: =10 -> 10 | BH8: =1*0.6 -> 0.6 | BI8: =1*1.1 -> 1.1 | BJ8: =SUM(K8:BI8) -> 113.2 | BL8: 5 | BM8: =1*2.5 -> 2.5 | BN8: =1*1.5 -> 1.5 | BO8: =1*2.4 -> 2.4 | BP8: 1 | BQ8: =1*3 -> 3 | BR8: 5 | BS8: =1*5.4 -> 5.4 | BT8: 3 | BU8: =1*1.9 -> 1.9 | BV8: 0.5 | BW8: 0.3 | BX8: =1*2.1 -> 2.1 | BY8: =1*2 -> 2 | BZ8: 1 | CA8: =1*4 -> 4 | CB8: =1*3 -> 3 | CC8: =1.2/1.2*3 -> 3 | CD8: =1*4 -> 4 | CE8: 1 | CF8: =8/8*6 -> 6 | CG8: 0.3 | CH8: =1*0.6 -> 0.6 | CI8: 1.5 | CJ8: 3 | CK8: =0.8/0.8*0.9 -> 0.9 | CL8: =0.6/0.6*0.9 -> 0.9 | CM8: 0.6 | CN8: 3.5 | CO8: =1*2 -> 2 | CP8: =1*0.3 -> 0.3 | CQ8: 3 | CR8: 1 | CS8: 2 | CT8: 9 | CU8: 4 | CV8: 5 | CW8: 3 | CX8: =10 -> 10 | CY8: 0.1 | CZ8: =0.8/0.8*3 -> 3 | DA8: =1.3/1.3*1.5 -> 1.5 | DB8: =1*2 -> 2 | DC8: =4/4*4.5 -> 4.5 | DD8: 3 | DE8: 1 | DF8: =1*0.6 -> 0.6 | DG8: 1 | DH8: =1 -> 1 | DI8: =8/8 -> 1 | DJ8: =1.6/1.6*1.5 -> 1.5 | DK8: 0.3 | DL8: =1*3 -> 3 | DM8: =1*3 -> 3 | DN8: 1 | DO8: =1*4 -> 4 | DP8: =8/8*7.5 -> 7.5 | DQ8: =1*1.5 -> 1.5 | DR8: 0.1 | DS8: =SUM(BL8:DR8) -> 148.8 | DU8: 2.4 | DV8: 1.5 | DW8: 0.3 | DX8: =0.8/0.8*0.9 -> 0.9 | DY8: =1*1.3 -> 1.3 | DZ8: 0.3 | EA8: 3.6 | EB8: =1*10 -> 10 | EC8: 1 | ED8: 0.6 | EE8: 0.4 | EF8: 1 | EG8: =0.3/0.3*0.6 -> 0.6 | EH8: 0.3 | EI8: =1*0.8 -> 0.8 | EJ8: =1*1.5 -> 1.5 | EK8: 1 | EL8: 1 | EM8: 3 | EN8: =8/8*5 -> 5 | EO8: =1*5 -> 5 | EP8: =1*2 -> 2 | EQ8: 3 | ER8: =1*0.3 -> 0.3 | ES8: =1*3 -> 3 | ET8: 0.6 | EU8: 0.9 | EV8: 0.5 | EW8: =1*2 -> 2 | EX8: =4/4*5 -> 5 | EY8: =1.3/1.3*2 -> 2 | EZ8: 5 | FA8: 2 | FB8: =0.6/0.6*1.2 -> 1.2 | FC8: 3 | FD8: 3 | FE8: =0.8/0.8*2.5 -> 2.5 | FF8: =1.5/1.5*1.1 -> 1.1 | FG8: 4 | FH8: =0.3/0.3*0.1 -> 0.1 | FI8: =1.5/1.5*0.6 -> 0.6 | FJ8: =1*10 -> 10 | FK8: 3 | FL8: =1*0.7 -> 0.7 | FM8: 1 | FN8: =0.5/0.5*0.6 -> 0.6 | FO8: =1*1.2 -> 1.2 | FP8: =3 -> 3 | FQ8: =3 -> 3 | FR8: 0.8 | FS8: =1 -> 1 | FT8: =0.3/0.3*0.6 -> 0.6 | FU8: =SUM(DU8:FT8) -> 108.2 | GP8: =SUM(FW8:GO8) -> 0
A9: 1 | B9: вит А 1000 | C9: 90.47 | D9: =29.41+30.6 -> 60.01 | E9: 87.74 | F9: =63.591 -> 63.591 | G9: =ROUND(AVERAGE(D9:F9),3) -> 70.447 | H9: 81.66 | I9: =18.069+75+125 -> 218.069 | K9: =0.675*3 -> 2.025 | L9: 2.026 | M9: =0.842*8 -> 6.736 | N9: 0.882 | O9: 0.528 | P9: =0.202 -> 0.202 | R9: =0.181*3 -> 0.543 | T9: =0.66 -> 0.66 | U9: =0.181*1.5 -> 0.2715 | V9: =0.181*4 -> 0.724 | W9: =0.675*1.5 -> 1.0125 | X9: =0.181*7 -> 1.267 | Z9: =0.181*2 -> 0.362 | AA9: =0.181*4 -> 0.724 | AB9: =0.181*8 -> 1.448 | AC9: =0.842*6 -> 5.052 | AE9: 1.572 | AF9: 0.14 | AG9: 0.14 | AH9: 0.544 | AI9: =1.008*4 -> 4.032 | AJ9: 6.028 | AK9: 0.302 | AL9: 0.109 | AM9: 0.427 | AN9: 0.706 | AO9: =0.534*2 -> 1.068 | AP9: =0.66*1.3 -> 0.858 | AQ9: 0.163 | AR9: 0.07 | AS9: 0.105 | AT9: 2.621 | AU9: 0.181 | AV9: =0.66 -> 0.66 | AW9: 2.026 | AX9: =0.675*1.2 -> 0.81 | AY9: 1.966 | AZ9: 0.308 | BA9: 0.31 | BB9: 0.181 | BD9: =0.198/0.3 -> 0.66 | BE9: 0.378 | BF9: 0.151 | BG9: =8.417 -> 8.417 | BH9: =0.66*0.6 -> 0.396 | BI9: =0.181*1.1 -> 0.1991 | BJ9: =SUM(K9:BI9) -> 59.9911 | BL9: 2.52 | BN9: =0.66*1.5 -> 0.99 | BO9: =0.675*2.4 -> 1.62 | BP9: 0.66 | BQ9: =0.675*3 -> 2.025 | BS9: =0.181*5.4 -> 0.9774 | BT9: 2.026 | BU9: =0.675*1.9 -> 1.2825 | BV9: 0.33 | BW9: 0.172 | BX9: =0.181*2.1 -> 0.3801 | BY9: =0.181*2 -> 0.362 | BZ9: =0.66 -> 0.66 | CA9: =0.181*4 -> 0.724 | CB9: =0.675*3 -> 2.025 | CC9: =0.81/1.2*3 -> 2.025 | CD9: =0.181*4 -> 0.724 | CE9: 0.66 | CF9: =1.452/8*6 -> 1.089 | CG9: 0.198 | CH9: =0.202*0.6 -> 0.1212 | CK9: =0.427/0.8*0.9 -> 0.480375 | CL9: =0.109/0.6*0.9 -> 0.1635 | CM9: 0.109 | CN9: 0.882 | CO9: =0.181*2 -> 0.362 | CP9: =0.66*0.3 -> 0.198 | CQ9: 2.026 | CR9: 0.66 | CS9: 3.024 | CT9: 23.587 | CU9: 2.867 | CV9: 1.008 | CW9: 4.536 | CX9: =8.417 -> 8.417 | CY9: 0.111 | CZ9: =0.427/0.8*3 -> 1.60125 | DA9: =0.858/1.3*1.5 -> 0.99 | DB9: =0.302*2 -> 0.604 | DC9: =4.032/4*4.5 -> 4.536 | DD9: 0.544 | DE9: 0.706 | DF9: =0.181*0.6 -> 0.1086 | DG9: =0.66 -> 0.66 | DH9: =0.181 -> 0.181 | DI9: =1.452/8 -> 0.1815 | DK9: 0.151 | DL9: =0.675*3 -> 2.025 | DM9: =0.675*3 -> 2.025 | DN9: =0.66 -> 0.66 | DO9: =0.181*4 -> 0.724 | DP9: =1.452/8*7.5 -> 1.36125 | DQ9: =0.383*1.5 -> 0.5745 | DR9: 0.06 | DS9: =SUM(BL9:DR9) -> 87.695175 | DU9: 1.621 | DV9: 1.013 | DW9: 0.198 | DX9: =0.427/0.8*0.9 -> 0.480375 | DY9: =0.66*1.3 -> 0.858 | EA9: =0.726 -> 0.726 | EB9: =0.842*10 -> 8.42 | EC9: 2.621 | ED9: 0.105 | EE9: 0.07 | EF9: 0.181 | EG9: =0.172/0.3*0.6 -> 0.344 | EH9: 0.203 | EI9: =0.66*0.8 -> 0.528 | EJ9: =0.181*1.5 -> 0.2715 | EK9: 0.181 | EL9: 0.181 | EM9: 0.756 | EN9: =1.452/8*5 -> 0.9075 | EO9: =0.66*5 -> 3.3 | EP9: =0.181*2 -> 0.362 | EQ9: 2.026 | ER9: =0.252*0.3 -> 0.0756 | ES9: =0.181*3 -> 0.543 | ET9: 0.109 | EU9: 0.163 | EV9: 0.353 | EW9: =0.302*2 -> 0.604 | EX9: =4.032/4*5 -> 5.04 | EY9: =0.858/1.3*2 -> 1.32 | EZ9: 1.008 | FA9: 3.024 | FB9: =0.121/0.6*1.2 -> 0.242 | FC9: 3.024 | FD9: 0.544 | FE9: =0.427/0.8*2.5 -> 1.334375 | FF9: =1.013/1.5*1.1 -> 0.74286667 | FG9: 2.701 | FH9: =0.003/0.3*0.1 -> 0.001 | FI9: =1.013/1.5*0.6 -> 0.4052 | FJ9: =0.842*10 -> 8.42 | FK9: =2.026 -> 2.026 | FL9: =0.66*0.7 -> 0.462 | FM9: 0.66 | FN9: =0.101/0.5*0.6 -> 0.1212 | FO9: =0.181*1.2 -> 0.2172 | FP9: =2.026 -> 2.026 | FQ9: =2.026 -> 2.026 | FR9: 0.528 | FS9: =0.181 -> 0.181 | FT9: =0.172/0.3*0.6 -> 0.344 | FU9: =SUM(DU9:FT9) -> 63.598817 | GP9: =SUM(FW9:GO9) -> 0 | GQ9: =I9-GP9 -> 218.069 | GR9: =I9 -> 218.069 | GS9: =G9 -> 70.447 | GT9: =E9 -> 87.74 | GU9: =B9 -> вит А 1000
A10: =A9+1 -> 2 | B10: вит Д3 500 | C10: =28.8+3.75+5.23 -> 37.78 | D10: =0.01+26.35 -> 26.36 | E10: 36.554 | F10: =31.021+4.2 -> 35.221 | G10: =ROUND(AVERAGE(D10:F10),3) -> 32.712 | H10: 31.866 | I10: =0.845+95.8 -> 96.645 | K10: =0.397*3 -> 1.191 | L10: 1.192 | M10: =0.407*8 -> 3.256 | N10: 0.38 | O10: 0.248 | P10: =0.097 -> 0.097 | Q10: 0.116 | R10: =0.097*3 -> 0.291 | T10: =0.31 -> 0.31 | U10: =0.097*1.5 -> 0.1455 | V10: =0.097*4 -> 0.388 | W10: =0.397*1.5 -> 0.5955 | X10: =0.097*7 -> 0.679 | Z10: =0.097*2 -> 0.194 | AA10: =0.097*4 -> 0.388 | AB10: =0.097*8 -> 0.776 | AC10: =0.407*6 -> 2.442 | AE10: 0.349 | AF10: 0.031 | AG10: 0.031 | AH10: 0.291 | AI10: =0.397*4 -> 1.588 | AJ10: 1.56 | AK10: 0.165 | AL10: 0.058 | AM10: 0.155 | AN10: =0.3+0.01 -> 0.31 | AO10: =0.194*2 -> 0.388 | AP10: =0.31*1.3 -> 0.403 | AQ10: 0.087 | AR10: 0.016 | AS10: 0.023 | AT10: 0.582 | AU10: 0.097 | AV10: =0.31 -> 0.31 | AW10: 1.192 | AX10: =0.397*1.2 -> 0.4764 | AY10: 0.436 | AZ10: 0.07 | BA10: 0.07 | BB10: 0.097 | BC10: =0.024 -> 0.024 | BD10: =0.093/0.3 -> 0.31 | BE10: 0.087 | BF10: 0.074 | BG10: =4.071 -> 4.071 | BH10: =0.31*0.6 -> 0.186 | BI10: =0.097*1.1 -> 0.1067 | BJ10: =SUM(K10:BI10) -> 26.3331 | BL10: 0.649 | BN10: =0.31*1.5 -> 0.465 | BO10: =0.397*2.4 -> 0.9528 | BP10: 0.31 | BQ10: =0.397*3 -> 1.191 | BS10: =0.097*5.4 -> 0.5238 | BT10: 1.192 | BU10: =0.397*1.9 -> 0.7543 | BV10: 0.155 | BW10: 0.081 | BX10: =0.097*2.1 -> 0.2037 | BY10: =0.097*2 -> 0.194 | BZ10: =0.31 -> 0.31 | CA10: =0.097*4 -> 0.388 | CB10: =0.397*3 -> 1.191 | CC10: =0.477/1.2*3 -> 1.1925 | CD10: =0.097*4 -> 0.388 | CE10: 0.31 | CF10: =0.775/8*6 -> 0.58125 | CG10: 0.093 | CH10: =0.097*0.6 -> 0.0582 | CI10: 0.116 | CK10: =0.155/0.8*0.9 -> 0.174375 | CL10: =0.058/0.6*0.9 -> 0.087 | CM10: 0.058 | CN10: 0.38 | CO10: =0.097*2 -> 0.194 | CP10: =0.31*0.3 -> 0.093 | CQ10: 1.192 | CR10: 0.31 | CS10: 1.473 | CT10: 5.234 | CU10: 1.093 | CV10: 0.262 | CW10: 2.21 | CX10: =4.071 -> 4.071 | CY10: 0.004 | CZ10: =0.155/0.8*3 -> 0.58125 | DA10: =0.403/1.3*1.5 -> 0.465 | DB10: =0.165*2 -> 0.33 | DC10: =1.59/4*4.5 -> 1.78875 | DD10: 0.291 | DE10: =0.3+0.01 -> 0.31 | DF10: =0.097*0.6 -> 0.0582 | DG10: =0.31 -> 0.31 | DH10: =0.097 -> 0.097 | DI10: =0.775/8 -> 0.096875 | DK10: 0.074 | DL10: =0.397*3 -> 1.191 | DM10: =0.397*3 -> 1.191 | DN10: =0.31 -> 0.31 | DO10: =0.097*4 -> 0.388 | DP10: =0.775/8*7.5 -> 0.7265625 | DQ10: =0.136*1.5 -> 0.204 | DR10: 0.019 | DS10: =SUM(BL10:DR10) -> 36.566563 | DU10: 0.954 | DV10: 0.596 | DW10: 0.093 | DX10: =0.155/0.8*0.9 -> 0.174375 | DY10: =0.31*1.3 -> 0.403 | EA10: =0.465 -> 0.465 | EB10: =0.407*10 -> 4.07 | EC10: 0.582 | ED10: 0.023 | EE10: 0.016 | EF10: 0.097 | EG10: =0.081/0.3*0.6 -> 0.162 | EH10: 0.119 | EI10: =0.31*0.8 -> 0.248 | EJ10: =0.097*1.5 -> 0.1455 | EK10: 0.097 | EL10: 0.097 | EM10: 0.174 | EN10: =0.775/8*5 -> 0.484375 | EO10: =0.31*5 -> 1.55 | EP10: =0.097*2 -> 0.194 | EQ10: 1.192 | ER10: =0.058*0.3 -> 0.0174 | ES10: =0.097*3 -> 0.291 | ET10: 0.058 | EU10: 0.087 | EV10: 0.155 | EW10: =0.165*2 -> 0.33 | EX10: =1.59/4*5 -> 1.9875 | EY10: =0.403/1.3*2 -> 0.62 | EZ10: 0.262 | FA10: 1.473 | FB10: =0.058/0.6*1.2 -> 0.116 | FC10: 5.815 | FD10: 0.291 | FE10: =0.155/0.8*2.5 -> 0.484375 | FF10: =0.596/1.5*1.1 -> 0.43706667 | FG10: 1.59 | FH10: =0.003/0.3*0.1 -> 0.001 | FI10: =0.596/1.5*0.6 -> 0.2384 | FJ10: =0.407*10 -> 4.07 | FK10: =1.24 -> 1.24 | FL10: =0.31*0.7 -> 0.217 | FM10: 0.31 | FN10: =0.048/0.5*0.6 -> 0.0576 | FO10: =0.101*1.2 -> 0.1212 | FP10: =1.24 -> 1.24 | FQ10: =1.24 -> 1.24 | FR10: 0.258 | FS10: =0.101 -> 0.101 | FT10: =0.081/0.3*0.6 -> 0.162 | FU10: =SUM(DU10:FT10) -> 35.206792 | GP10: =SUM(FW10:GO10) -> 0 | GQ10: =I10-GP10 -> 96.645 | GR10: =I10 -> 96.645 | GS10: =G10 -> 32.712 | GT10: =E10 -> 36.554 | GU10: =B10 -> вит Д3 500
A11: =A10+1 -> 3 | B11: вит Е 50% | C11: =31.74+876.66+187.87 -> 1096.27 | D11: =835.24 -> 835.24 | E11: =472.08+568.9 -> 1040.98 | F11: =4.81+973.35 -> 978.16 | G11: =ROUND(AVERAGE(D11:F11),3) -> 951.46 | H11: =4.81+1431.1 -> 1435.91 | I11: =457.75+2000 -> 2457.75 | K11: =8.971*3 -> 26.913 | L11: 26.914 | M11: =12.096*8 -> 96.768 | N11: 9.878 | O11: 8.064 | P11: =9.193 -> 9.193 | Q11: 4.234 | R11: =9.475*3 -> 28.425 | T11: =19.152 -> 19.152 | U11: =2.419*1.5 -> 3.6285 | V11: =9.475*4 -> 37.9 | W11: =8.971*1.5 -> 13.4565 | X11: =2.419*7 -> 16.933 | Y11: =2.016*3 -> 6.048 | Z11: =2.419*2 -> 4.838 | AA11: =9.475*4 -> 37.9 | AB11: =2.419*8 -> 19.352 | AC11: =12.096*6 -> 72.576 | AD11: 0.161 | AE11: 1.814 | AF11: 0.323 | AG11: 0.161 | AH11: 7.258 | AI11: =8.971*4 -> 35.884 | AJ11: 9.274 | AK11: 8.064 | AL11: 1.452 | AM11: 8.064 | AN11: 19.152 | AO11: =10.08*2 -> 20.16 | AP11: =19.152*1.3 -> 24.8976 | AQ11: 8.528 | AR11: 0.161 | AS11: 0.121 | AT11: 3.024 | AU11: 9.475 | AV11: =19.152 -> 19.152 | AW11: 26.914 | AX11: =8.971*1.2 -> 10.7652 | AY11: 2.268 | AZ11: 0.71 | BA11: 0.355 | BB11: 2.419 | BC11: =2.298 -> 2.298 | BD11: =5.746/0.3 -> 19.153333 | BE11: 8.017 | BF11: 0.202 | BG11: =120.96 -> 120.96 | BH11: =19.152*0.6 -> 11.4912 | BI11: =9.475*1.1 -> 10.4225 | BJ11: =SUM(K11:BI11) -> 835.27383 | BL11: 20.16 | BN11: =19.152*1.5 -> 28.728 | BO11: =8.971*2.4 -> 21.5304 | BP11: 19.152 | BQ11: =8.971*3 -> 26.913 | BR11: 15.12 | BS11: =2.419*5.4 -> 13.0626 | BT11: 26.914 | BU11: =8.971*1.9 -> 17.0449 | BV11: 9.576 | BW11: 3.145 | BX11: =2.419*2.1 -> 5.0799 | BY11: =2.419*2 -> 4.838 | BZ11: 23.99 | CA11: =9.475*4 -> 37.9 | CB11: =8.971*3 -> 26.913 | CC11: =10.765/1.2*3 -> 26.9125 | CD11: =9.475*4 -> 37.9 | CE11: 19.152 | CF11: =19.354/8*6 -> 14.5155 | CG11: 3.024 | CH11: =9.193*0.6 -> 5.5158 | CI11: 4.234 | CJ11: 6.048 | CK11: =7.906/0.8*0.9 -> 8.89425 | CL11: =5.574/0.6*0.9 -> 8.361 | CM11: 1.452 | CN11: 9.878 | CO11: =2.372*2 -> 4.744 | CP11: =19.152*0.3 -> 5.7456 | CQ11: 26.386 | CR11: 23.52 | CS11: 4.032 | CT11: 27.234 | CU11: 45.467 | CV11: 9.882 | CW11: 5.929 | CX11: 118.588 | CY11: 0.484 | CZ11: =7.906/0.8*3 -> 29.6475 | DA11: =24.409/1.3*1.5 -> 28.164231 | DB11: =7.906*2 -> 15.812 | DC11: =35.181/4*4.5 -> 39.578625 | DD11: 7.115 | DE11: 18.776 | DF11: =9.475*0.6 -> 5.685 | DG11: 23.52 | DH11: =9.289 -> 9.289 | DI11: =18.974/8 -> 2.37175 | DK11: 0.202 | DL11: =8.795*3 -> 26.385 | DM11: =8.795*3 -> 26.385 | DN11: 23.52 | DO11: =9.289*4 -> 37.156 | DP11: =18.974/8*7.5 -> 17.788125 | DQ11: =7.511*1.5 -> 11.2665 | DR11: 0.356 | DS11: =SUM(BL11:DR11) -> 1040.9832 | DU11: =16.393+4.81 -> 21.203 | DV11: 13.193 | DW11: 5.633 | DX11: =7.906/0.8*0.9 -> 8.89425 | DY11: =18.776*1.3 -> 24.4088 | DZ11: 0.889 | EA11: =5.218 -> 5.218 | EB11: =11.859*10 -> 118.59 | EC11: 2.965 | ED11: 0.237 | EE11: 0.079 | EF11: 2.372 | EG11: =3.083/0.3*0.6 -> 6.166 | EH11: 2.639 | EI11: =23.52*0.8 -> 18.816 | EJ11: =9.289*1.5 -> 13.9335 | EK11: 9.289 | EL11: 9.289 | EM11: 15.719 | EN11: =18.974/8*5 -> 11.85875 | EO11: =23.52*5 -> 117.6 | EP11: =9.289*2 -> 18.578 | EQ11: 26.386 | ER11: =5.24*0.3 -> 1.572 | ES11: =9.289*3 -> 27.867 | ET11: 1.423 | EU11: 8.36 | EV11: 9.388 | EW11: =7.906*2 -> 15.812 | EX11: =35.181/4*5 -> 43.97625 | EY11: =24.409/1.3*2 -> 37.552308 | EZ11: 9.882 | FA11: 3.953 | FB11: =5.408/0.6*1.2 -> 10.816 | FD11: 7.115 | FE11: =7.906/0.8*2.5 -> 24.70625 | FF11: =13.193/1.5*1.1 -> 9.6748667 | FG11: 35.181 | FH11: =0.059/0.3*0.1 -> 0.019666667 | FI11: =13.193/1.5*0.6 -> 5.2772 | FJ11: =11.859*10 -> 118.59 | FK11: =26.386 -> 26.386 | FL11: =23.52*0.7 -> 16.464 | FM11: 18.776 | FN11: =4.447/0.5*0.6 -> 5.3364 | FO11: =2.372*1.2 -> 2.8464 | FP11: =26.386 -> 26.386 | FQ11: =26.386 -> 26.386 | FR11: 15.021 | FS11: =9.289 -> 9.289 | FT11: =3.083/0.3*0.6 -> 6.166 | FU11: =SUM(DU11:FT11) -> 978.17864 | GP11: =SUM(FW11:GO11) -> 0 | GQ11: =I11-GP11 -> 2457.75 | GR11: =I11 -> 2457.75 | GS11: =G11 -> 951.46 | GT11: =E11 -> 1040.98 | GU11: =B11 -> вит Е 50%
A12: =A11+1 -> 4 | B12: вит В1 (тиамин) | C12: 0 | D12: 0 | E12: 0 | F12: 0 | G12: =ROUND(AVERAGE(D12:F12),3) -> 0 | H12: 0 | I12: 0 | BJ12: =SUM(K12:BI12) -> 0 | DS12: =SUM(BL12:DR12) -> 0 | FU12: =SUM(DU12:FT12) -> 0 | GP12: =SUM(FW12:GO12) -> 0 | GQ12: =I12-GP12 -> 0 | GR12: =I12 -> 0 | GS12: =G12 -> 0 | GT12: =E12 -> 0 | GU12: =B12 -> вит В1 (тиамин)
A13: =A12+1 -> 5 | B13: вит В2 | C13: 0.71 | D13: 0.52 | E13: 0.73 | F13: 0.04 | G13: =ROUND(AVERAGE(D13:F13),3) -> 0.43 | H13: 0.04 | I13: 0 | BE13: 0.019 | BG13: =0.504 -> 0.504 | BJ13: =SUM(K13:BI13) -> 0.523 | BN13: =0.05*1.5 -> 0.075 | BO13: =0.05*2.4 -> 0.12 | BQ13: =0.05*3 -> 0.15 | CP13: =0.05*0.3 -> 0.015 | CX13: 0.36 | DS13: =SUM(BL13:DR13) -> 0.72 | EM13: 0.04 | FU13: =SUM(DU13:FT13) -> 0.04 | GP13: =SUM(FW13:GO13) -> 0 | GQ13: =I13-GP13 -> 0 | GR13: =I13 -> 0 | GS13: =G13 -> 0.43 | GT13: =E13 -> 0.73 | GU13: =B13 -> вит В2 | GV13: 46133
A14: =A13+1 -> 6 | B14: вит В3, Нутравит В5 (кальпан) | C14: 0.25 | D14: 0.08 | E14: 0 | F14: 0.17 | G14: =ROUND(AVERAGE(D14:F14),3) -> 0.083 | H14: 14.29 | I14: 14.12 | BE14: 0.077 | BJ14: =SUM(K14:BI14) -> 0.077 | DS14: =SUM(BL14:DR14) -> 0 | EM14: 0.154 | ER14: =0.051*0.3 -> 0.0153 | FU14: =SUM(DU14:FT14) -> 0.1693 | GP14: =SUM(FW14:GO14) -> 0 | GQ14: =I14-GP14 -> 14.12 | GR14: =I14 -> 14.12 | GS14: =G14 -> 0.083 | GT14: =E14 -> 0 | GU14: =B14 -> вит В3, Нутравит В5 (кальпан) | GV14: 46455 | GW14: =GQ14/GT14 -> #DIV/0!
A15: =A14+1 -> 7 | B15: вит В5 (ниацин) | C15: 0.53 | D15: 0.23 | E15: 0 | F15: 0.51 | G15: =ROUND(AVERAGE(D15:F15),3) -> 0.247 | H15: 19.977 | I15: 19.467 | BE15: 0.229 | BJ15: =SUM(K15:BI15) -> 0.229 | DS15: =SUM(BL15:DR15) -> 0 | EM15: 0.458 | ER15: =0.153*0.3 -> 0.0459 | FU15: =SUM(DU15:FT15) -> 0.5039 | GP15: =SUM(FW15:GO15) -> 0 | GQ15: =I15-GP15 -> 19.467 | GR15: =I15 -> 19.467 | GS15: =G15 -> 0.247 | GT15: =E15 -> 0 | GU15: =B15 -> вит В5 (ниацин) | GV15: 46890 | GW15: =GQ15/GT15 -> #DIV/0!
A16: =A15+1 -> 8 | B16: вит В6 (пиридоксин) | C16: 0.03 | D16: 0.02 | E16: 0.51 | F16: 0.133 | G16: =ROUND(AVERAGE(D16:F16),3) -> 0.221 | H16: 14.1 | I16: 13.967 | BE16: 0.015 | BJ16: =SUM(K16:BI16) -> 0.015 | BL16: 0.509 | DS16: =SUM(BL16:DR16) -> 0.509 | EM16: 0.031 | ER16: =0.01*0.3 -> 0.003 | FS16: =0.102 -> 0.102 | FU16: =SUM(DU16:FT16) -> 0.136 | GP16: =SUM(FW16:GO16) -> 0 | GQ16: =I16-GP16 -> 13.967 | GR16: =I16 -> 13.967 | GS16: =G16 -> 0.221 | GT16: =E16 -> 0.51 | GU16: =B16 -> вит В6 (пиридоксин) | GV16: 46941 | GW16: =GQ16/GT16 -> 27.386275
A17: =A16+1 -> 9 | B17: вит Н (биотин) | C17: =143.25+16.72+111.24 -> 271.21 | D17: =7.13+88.76+139.14 -> 235.03 | E17: 252.97 | F17: 167.52 | G17: =ROUND(AVERAGE(D17:F17),3) -> 218.507 | H17: 307.89 | I17: 140.37 | M17: =5.796*8 -> 46.368 | N17: 7.056 | P17: =2.016 -> 2.016 | Q17: 3.024 | R17: =2.016*3 -> 6.048 | U17: =2.016*1.5 -> 3.024 | V17: =2.016*4 -> 8.064 | X17: =2.016*7 -> 14.112 | Z17: =2.016*2 -> 4.032 | AA17: =2.016*4 -> 8.064 | AB17: =2.016*8 -> 16.128 | AC17: =5.796*6 -> 34.776 | AF17: 0.536 | AG17: 0.536 | AH17: =2.09+3.961 -> 6.051 | AJ17: 3.709 | AL17: 1.21 | AQ17: 1.814 | AR17: 0.268 | AS17: 0.402 | AU17: 2.016 | AZ17: 1.179 | BA17: 1.179 | BB17: 2.016 | BC17: =1.21 -> 1.21 | BG17: =57.96 -> 57.96 | BI17: =2.016*1.1 -> 2.2176 | BJ17: =SUM(K17:BI17) -> 235.0156 | BS17: =2.016*5.4 -> 10.8864 | BX17: =2.016*2.1 -> 4.2336 | BY17: =2.016*2 -> 4.032 | CA17: =2.016*4 -> 8.064 | CD17: =2.016*4 -> 8.064 | CF17: =16.128/8*6 -> 12.096 | CH17: =2.016*0.6 -> 1.2096 | CI17: 3.024 | CL17: =1.21/0.6*0.9 -> 1.815 | CM17: 1.21 | CN17: 7.056 | CO17: =2.016*2 -> 4.032 | CT17: 90.72 | CV17: 3.78 | CX17: =57.96 -> 57.96 | DD17: =2.09+3.961 -> 6.051 | DF17: =2.016*0.6 -> 1.2096 | DH17: =2.016 -> 2.016 | DI17: =16.128/8 -> 2.016 | DO17: =2.016*4 -> 8.064 | DP17: =16.128/8*7.5 -> 15.12 | DR17: 0.318 | DS17: =SUM(BL17:DR17) -> 252.9772 | EA17: =2.413 -> 2.413 | EB17: =5.796*10 -> 57.96 | ED17: 0.402 | EE17: 0.268 | EF17: 2.016 | EJ17: =2.016*1.5 -> 3.024 | EK17: 2.016 | EL17: 2.016 | EN17: =16.128/8*5 -> 10.08 | EP17: =2.016*2 -> 4.032 | ES17: =2.016*3 -> 6.048 | ET17: 1.21 | EU17: 1.814 | EZ17: 3.352 | FB17: =1.21/0.6*1.2 -> 2.42 | FD17: 6.048 | FJ17: =5.796*10 -> 57.96 | FO17: =2.016*1.2 -> 2.4192 | FS17: =2.016 -> 2.016 | FU17: =SUM(DU17:FT17) -> 167.5142 | GP17: =SUM(FW17:GO17) -> 0 | GQ17: =I17-GP17 -> 140.37 | GR17: =I17 -> 140.37 | GS17: =G17 -> 218.507 | GT17: =E17 -> 252.97 | GU17: =B17 -> вит Н (биотин)
H18: =SUM(H9:H17) -> 1905.733 | I18: =SUM(I9:I17) -> 2960.388
A19: =A17+1 -> 10 | B19: окись магния, порошок магнезитовый | C19: =3914.16+10971.21 -> 14885.37 | D19: 10047.63 | E19: 15140.75 | F19: =3840.41+8549.98 -> 12390.39 | G19: =ROUND(AVERAGE(D19:F19),3) -> 12526.257 | H19: =3840.41+20000 -> 23840.41 | I19: 11450.02 | K19: =159.957*3 -> 479.871 | L19: 478.242 | M19: =70.56*8 -> 564.48 | N19: 10.263 | O19: 185.07 | P19: =69.051 -> 69.051 | Q19: 249.458 | R19: =93.283*3 -> 279.849 | T19: =208.128 -> 208.128 | V19: =93.283*4 -> 373.132 | W19: =159.957*1.5 -> 239.9355 | Y19: =18.327*3 -> 54.981 | AA19: =93.283*4 -> 373.132 | AC19: =70.56*6 -> 423.36 | AD19: 16.128 | AE19: 149.551 | AF19: 1.955 | AG19: 1.955 | AH19: 302.204 | AI19: =444.145*4 -> 1776.58 | AJ19: 84.305 | AK19: 91.636 | AL19: 60.441 | AM19: 87.971 | AN19: 208.135 | AO19: =109.964*2 -> 219.928 | AP19: =208.128*1.3 -> 270.5664 | AQ19: 92.344 | AR19: 0.977 | AS19: 1.466 | AT19: 249.251 | AU19: 93.283 | AV19: =208.128 -> 208.128 | AW19: 478.242 | AX19: =159.957*1.2 -> 191.9484 | AY19: 186.938 | AZ19: 4.312 | BA19: 4.312 | BB19: 93.413 | BD19: =62.438/0.3 -> 208.12667 | BE19: 41.236 | BF19: 0.275 | BG19: =705.6 -> 705.6 | BH19: =208.128*0.6 -> 124.8768 | BI19: =93.283*1.1 -> 102.6113 | BJ19: =SUM(K19:BI19) -> 10047.648 | BL19: 606.734 | BN19: =208.128*1.5 -> 312.192 | BO19: =159.414*2.4 -> 382.5936 | BP19: 208.128 | BQ19: =159.957*3 -> 479.871 | BT19: 478.242 | BU19: =159.957*1.9 -> 303.9183 | BV19: 104.064 | BW19: 45.076 | BZ19: =208.128 -> 208.128 | CA19: =93.283*4 -> 373.132 | CB19: =159.957*3 -> 479.871 | CC19: =191.948/1.2*3 -> 479.87 | CD19: =93.283*4 -> 373.132 | CE19: 208.128 | CG19: 69.401 | CH19: =69.051*0.6 -> 41.4306 | CI19: 249.458 | CJ19: 54.982 | CK19: =87.971/0.8*0.9 -> 98.967375 | CL19: =61.563/0.6*0.9 -> 92.3445 | CM19: 60.441 | CN19: 10.263 | CP19: =208.128*0.3 -> 62.4384 | CQ19: 478.242 | CR19: 208.128 | CS19: 5.498 | CT19: 1649.455 | CU19: 997.004 | CV19: 67.444 | CW19: 8.247 | CX19: =705.6 -> 705.6 | CZ19: =87.971/0.8*3 -> 329.89125 | DA19: =270.676/1.3*1.5 -> 312.31846 | DB19: =91.636*2 -> 183.272 | DC19: =1776.813/4*4.5 -> 1998.9146 | DD19: 302.204 | DE19: 208.135 | DF19: =93.283*0.6 -> 55.9698 | DG19: =208.212 -> 208.212 | DH19: =93.347 -> 93.347 | DK19: 0.275 | DL19: =160.014*3 -> 480.042 | DM19: =160.014*3 -> 480.042 | DN19: =208.212 -> 208.212 | DO19: =93.347*4 -> 373.388 | DQ19: =1.833*1.5 -> 2.7495 | DR19: 1.375 | DS19: =SUM(BL19:DR19) -> 15140.771 | DU19: 382.733 | DV19: 239.964 | DW19: 62.464 | DX19: =87.971/0.8*0.9 -> 98.967375 | DY19: =208.212*1.3 -> 270.6756 | EA19: 8.797 | EB19: =70.56*10 -> 705.6 | EC19: 249.251 | ED19: 1.466 | EE19: 0.977 | EF19: 93.433 | EG19: =45.09/0.3*0.6 -> 90.18 | EH19: 48.004 | EI19: =208.212*0.8 -> 166.5696 | EJ19: =93.347*1.5 -> 140.0205 | EK19: 93.347 | EL19: 93.348 | EM19: 82.473 | EO19: =208.212*5 -> 1041.06 | EP19: =93.347*2 -> 186.694 | EQ19: 478.417 | ER19: =27.491*0.3 -> 8.2473 | ES19: =93.347*3 -> 280.041 | ET19: 60.452 | EU19: 92.38 | EV19: 104.11 | EW19: =91.636*2 -> 183.272 | EX19: =1776.813/4*5 -> 2221.0163 | EY19: =270.676/1.3*2 -> 416.42462 | EZ19: 61.396 | FA19: 5.498 | FB19: =41.461/0.6*1.2 -> 82.922 | FD19: 302.262 | FE19: =87.971/0.8*2.5 -> 274.90938 | FF19: =240.021/1.5*1.1 -> 176.0154 | FG19: 640.057 | FI19: =240.021/1.5*0.6 -> 96.0084 | FJ19: =70.56*10 -> 705.6 | FK19: =480.853 -> 480.853 | FL19: =208.212*0.7 -> 145.7484 | FM19: 208.212 | FP19: =480.042 -> 480.042 | FQ19: =480.042 -> 480.042 | FR19: 166.57 | FS19: =93.652 -> 93.652 | FT19: =45.09/0.3*0.6 -> 90.18 | FU19: =SUM(DU19:FT19) -> 12390.352 | GP19: =SUM(FW19:GO19) -> 0 | GQ19: =I19-GP19 -> 11450.02 | GR19: =I19 -> 11450.02 | GS19: =G19 -> 12526.257 | GT19: =E19 -> 15140.75 | GU19: =B19 -> окись магния, порошок магнезитовый
A20: =A19+1 -> 11 | B20: сульфат магния б/водный, магний с/кисл. | C20: =7803.13+3000+1522.55 -> 12325.68 | D20: 7659.51 | E20: =7767.32+3207.89+655.2 -> 11630.41 | F20: =50.62+6061.38+1679.13 -> 7791.13 | G20: =ROUND(AVERAGE(D20:F20),3) -> 9027.017 | H20: =50.62+13792.11+2000+2344.8 -> 18187.53 | I20: =7730.73+2000+1000+665.67 -> 11396.4 | K20: =98.695*3 -> 296.085 | L20: 301.033 | M20: =65.52*8 -> 524.16 | O20: 43.544 | P20: =87.34 -> 87.34 | Q20: 43.673 | R20: =111.391*3 -> 334.173 | S20: =342.72*1.6 -> 548.352 | T20: =147.236 -> 147.236 | U20: =66.833*1.5 -> 100.2495 | V20: =111.391*4 -> 445.564 | W20: =98.695*1.5 -> 148.0425 | X20: =66.834*7 -> 467.838 | Z20: =66.834*2 -> 133.668 | AA20: =111.391*4 -> 445.564 | AB20: =66.834*8 -> 534.672 | AC20: =65.52*6 -> 393.12 | AH20: 100.251 | AI20: =100.252*4 -> 401.008 | AL20: 20.05 | AN20: 147.236 | AP20: =147.236*1.3 -> 191.4068 | AQ20: 61.138 | AU20: 111.391 | AV20: =147.236 -> 147.236 | AW20: 301.033 | AX20: =98.695*1.2 -> 118.434 | BB20: 33.417 | BC20: =19.312 -> 19.312 | BD20: =44.171/0.3 -> 147.23667 | BG20: =655.2 -> 655.2 | BH20: =147.236*0.6 -> 88.3416 | BI20: =111.391*1.1 -> 122.5301 | BJ20: =SUM(K20:BI20) -> 7659.5352 | BL20: 383.958 | BM20: =342.72*2.5 -> 856.8 | BN20: =147.236*1.5 -> 220.854 | BO20: =100.344*2.4 -> 240.8256 | BP20: 147.236 | BQ20: =98.695*3 -> 296.085 | BR20: 886.669 | BS20: =66.834*5.4 -> 360.9036 | BT20: 301.033 | BU20: =98.695*1.9 -> 187.5205 | BV20: 73.618 | BW20: 23.417 | BX20: =66.834*2.1 -> 140.3514 | BY20: =66.833*2 -> 133.666 | BZ20: =147.236 -> 147.236 | CA20: =111.391*4 -> 445.564 | CB20: =98.695*3 -> 296.085 | CC20: =118.433/1.2*3 -> 296.0825 | CD20: =111.391*4 -> 445.564 | CE20: 147.236 | CF20: =534.667/8*6 -> 401.00025 | CG20: 16.329 | CH20: =87.34*0.6 -> 52.404 | CI20: 43.673 | CL20: =40.759/0.6*0.9 -> 61.1385 | CM20: 20.05 | CO20: =66.833*2 -> 133.666 | CP20: =147.236*0.3 -> 44.1708 | CQ20: 301.033 | CR20: 147.236 | CV20: 201.6 | CX20: =655.2 -> 655.2 | DA20: =192.131/1.3*1.5 -> 221.68962 | DC20: =402.523/4*4.5 -> 452.83838 | DD20: 100.251 | DE20: 147.236 | DF20: =111.391*0.6 -> 66.8346 | DG20: =147.793 -> 147.793 | DH20: =111.812 -> 111.812 | DI20: =536.689/8 -> 67.086125 | DJ20: =548.352/1.6*1.5 -> 514.08 | DL20: =99.068*3 -> 297.204 | DM20: =99.068*3 -> 297.204 | DN20: =147.793 -> 147.793 | DO20: =111.812*4 -> 447.248 | DP20: =536.689/8*7.5 -> 503.14594 | DS20: =SUM(BL20:DR20) -> 11630.421 | DU20: 241.737 | DV20: =50.62+97.613 -> 148.233 | DW20: 44.338 | DY20: =147.793*1.3 -> 192.1309 | DZ20: 53.401 | EB20: =65.52*10 -> 655.2 | EF20: 33.544 | EG20: =23.506/0.3*0.6 -> 47.012 | EH20: 29.72 | EI20: =147.793*0.8 -> 118.2344 | EJ20: =111.812*1.5 -> 167.718 | EK20: 111.812 | EL20: 111.812 | EN20: =536.689/8*5 -> 335.43062 | EO20: =147.793*5 -> 738.965 | EP20: =111.812*2 -> 223.624 | EQ20: 302.171 | ES20: =111.812*3 -> 335.436 | ET20: 20.126 | EU20: 61.369 | EV20: 73.896 | EX20: =402.523/4*5 -> 503.15375 | EY20: =192.131/1.3*2 -> 295.58615 | FB20: =52.602/0.6*1.2 -> 105.204 | FD20: 100.631 | FF20: =148.602/1.5*1.1 -> 108.9748 | FG20: 396.271 | FI20: =148.602/1.5*0.6 -> 59.4408 | FJ20: =65.52*10 -> 655.2 | FK20: =267.933 -> 267.933 | FL20: =147.793*0.7 -> 103.4551 | FM20: 147.793 | FN20: =50.4/0.5*0.6 -> 60.48 | FO20: =67.086*1.2 -> 80.5032 | FP20: =297.203 -> 297.203 | FQ20: =297.203 -> 297.203 | FR20: 118.235 | FS20: =100.8 -> 100.8 | FT20: =23.506/0.3*0.6 -> 47.012 | FU20: =SUM(DU20:FT20) -> 7790.9887 | GP20: =SUM(FW20:GO20) -> 0 | GQ20: =I20-GP20 -> 11396.4 | GR20: =I20 -> 11396.4 | GS20: =G20 -> 9027.017 | GT20: =E20 -> 11630.41 | GU20: =B20 -> сульфат магния б/водный, магний с/кисл.
A21: =A20+1 -> 12 | B21: сульфат магния Кизерит | C21: 0 | D21: 0 | E21: 0 | F21: 0 | G21: =ROUND(AVERAGE(D21:F21),3) -> 0 | H21: 0 | I21: 0 | BJ21: =SUM(K21:BI21) -> 0 | DS21: =SUM(BL21:DR21) -> 0 | FU21: =SUM(DU21:FT21) -> 0 | GP21: =SUM(FW21:GO21) -> 0 | GQ21: =I21-GP21 -> 0 | GR21: =I21 -> 0 | GS21: =G21 -> 0 | GT21: =E21 -> 0 | GU21: =B21 -> сульфат магния Кизерит
A22: =A21+1 -> 13 | B22: сера | C22: =69.23+71.59 -> 140.82 | D22: 81.34 | E22: 154.64 | F22: 44.27 | G22: =ROUND(AVERAGE(D22:F22),3) -> 93.417 | H22: 211.43 | I22: 167.16 | N22: 14.112 | P22: =3.384 -> 3.384 | Q22: 23.825 | AD22: 0.591 | AE22: 7.942 | AT22: 13.135 | AY22: 9.851 | BC22: =4.435 -> 4.435 | BE22: 3.055 | BF22: 1.018 | BJ22: =SUM(K22:BI22) -> 81.348 | CH22: =3.384*0.6 -> 2.0304 | CI22: 23.825 | CN22: 14.112 | CS22: 20.364 | CU22: 52.538 | CV22: 5.111 | CW22: 30.545 | DK22: 1.018 | DQ22: =3.394*1.5 -> 5.091 | DS22: =SUM(BL22:DR22) -> 154.6344 | EC22: 13.135 | EM22: 6.109 | ER22: =2.036*0.3 -> 0.6108 | FA22: 20.364 | FB22: =2.031/0.6*1.2 -> 4.062 | FU22: =SUM(DU22:FT22) -> 44.2808 | GP22: =SUM(FW22:GO22) -> 0 | GQ22: =I22-GP22 -> 167.16 | GR22: =I22 -> 167.16 | GS22: =G22 -> 93.417 | GT22: =E22 -> 154.64 | GU22: =B22 -> сера
A23: =A22+1 -> 14 | B23: сульфат железа | C23: 99.05 | D23: 10.75 | E23: =48.84+32.37 -> 81.21 | F23: =0.32+23.39 -> 23.71 | G23: =ROUND(AVERAGE(D23:F23),3) -> 38.557 | H23: =0.32+167.63 -> 167.95 | I23: 144.24 | AF23: 0.173 | AG23: 0.173 | AJ23: 7.479 | AR23: 0.087 | AS23: 0.13 | AZ23: 0.383 | BA23: 0.383 | BE23: =0.29+0.685 -> 0.975 | BF23: 0.975 | BJ23: =SUM(K23:BI23) -> 10.758 | CS23: 19.51 | CT23: 29.265 | CV23: 1.12 | CW23: 30.24 | CY23: 0.062 | DK23: 1.008 | DS23: =SUM(BL23:DR23) -> 81.205 | ED23: 0.13 | EE23: 0.087 | EM23: =1.912+0.1 -> 2.012 | ER23: =0.672*0.3 -> 0.2016 | EZ23: 1.12 | FA23: 20.16 | FU23: =SUM(DU23:FT23) -> 23.7106 | GP23: =SUM(FW23:GO23) -> 0 | GQ23: =I23-GP23 -> 144.24 | GR23: =I23 -> 144.24 | GS23: =G23 -> 38.557 | GT23: =E23 -> 81.21 | GU23: =B23 -> сульфат железа
A24: =A23+1 -> 15 | B24: медный купорос | C24: =71.702+127.488 -> 199.19 | D24: 218.5 | E24: 200.94 | F24: 223.58 | G24: =ROUND(AVERAGE(D24:F24),3) -> 214.34 | H24: 453.072 | I24: 229.492 | K24: =4.435*3 -> 13.305 | M24: =6.048*8 -> 48.384 | N24: =5.08 -> 5.08 | O24: 5.484 | W24: =6.653*1.5 -> 9.9795 | X24: =0.968*7 -> 6.776 | Z24: =0.968*2 -> 1.936 | AB24: =0.968*8 -> 7.744 | AC24: =6.048*6 -> 36.288 | AF24: 0.151 | AG24: 0.151 | AJ24: 6.492 | AK24: 1.21 | AM24: 1.129 | AO24: =1.411*2 -> 2.822 | AR24: 0.075 | AS24: 0.113 | AU24: 1.21 | AX24: =4.435*1.2 -> 5.322 | AZ24: 0.332 | BA24: 0.332 | BB24: 0.968 | BD24: =0.765/0.3 -> 2.55 | BF24: 0.202 | BG24: =60.48 -> 60.48 | BJ24: =SUM(K24:BI24) -> 218.5155 | BL24: 10.08 | BQ24: =4.435*3 -> 13.305 | BS24: =0.968*5.4 -> 5.2272 | BU24: =6.653*1.9 -> 12.6407 | BV24: 1.275 | BX24: =0.968*2.1 -> 2.0328 | CB24: =4.435*3 -> 13.305 | CC24: =5.322/1.2*3 -> 13.305 | CF24: =7.741/8*6 -> 5.80575 | CG24: 2.056 | CK24: =1.129/0.8*0.9 -> 1.270125 | CN24: 5.08 | CS24: 4.032 | CW24: 6.048 | CX24: =60.48 -> 60.48 | CZ24: =1.129/0.8*3 -> 4.23375 | DB24: =1.21*2 -> 2.42 | DF24: =1.21*0.6 -> 0.726 | DI24: =7.741/8 -> 0.967625 | DK24: 0.202 | DL24: =4.435*3 -> 13.305 | DM24: =4.435*3 -> 13.305 | DP24: =7.741/8*7.5 -> 7.2571875 | DQ24: =1.452*1.5 -> 2.178 | DR24: 0.363 | DS24: =SUM(BL24:DR24) -> 200.90014 | DV24: 9.979 | DW24: 0.765 | DX24: =1.129/0.8*0.9 -> 1.270125 | EA24: =0.677 -> 0.677 | EB24: =6.048*10 -> 60.48 | ED24: 0.113 | EE24: 0.075 | EF24: 0.968 | EH24: 1.331 | EK24: 1.21 | EL24: 1.21 | EN24: =7.741/8*5 -> 4.838125 | EW24: =1.21*2 -> 2.42 | FA24: 4.032 | FE24: =1.129/0.8*2.5 -> 3.528125 | FF24: =9.979/1.5*1.1 -> 7.3179333 | FG24: 17.741 | FI24: =9.979/1.5*0.6 -> 3.9916 | FJ24: =6.048*10 -> 60.48 | FK24: =13.306 -> 13.306 | FP24: =13.306 -> 13.306 | FQ24: =13.306 -> 13.306 | FS24: =1.21 -> 1.21 | FU24: =SUM(DU24:FT24) -> 223.55491 | GP24: =SUM(FW24:GO24) -> 0 | GQ24: =I24-GP24 -> 229.492 | GR24: =I24 -> 229.492 | GS24: =G24 -> 214.34 | GT24: =E24 -> 200.94 | GU24: =B24 -> медный купорос
A25: =A24+1 -> 16 | B25: цинковый купорос+ сульфат цинка | C25: =5.47+849.07 -> 854.54 | D25: 868.88 | E25: =216.61+531.79 -> 748.4 | F25: 893.57 | G25: =ROUND(AVERAGE(D25:F25),3) -> 836.95 | H25: 1468.21 | I25: 574.64 | K25: =18.568*3 -> 55.704 | M25: =24.802*8 -> 198.416 | N25: 18.568 | O25: 20.16 | P25: =2.631 -> 2.631 | W25: =27.853*1.5 -> 41.7795 | X25: =2.918*7 -> 20.426 | Z25: =2.918*2 -> 5.836 | AB25: =2.918*8 -> 23.344 | AC25: =24.802*6 -> 148.812 | AF25: 0.849 | AG25: 0.849 | AJ25: 36.606 | AK25: 2.785 | AM25: 2.653 | AO25: =3.316*2 -> 6.632 | AR25: 0.424 | AS25: 0.637 | AU25: 1.273 | AX25: =18.568*1.2 -> 22.2816 | AZ25: 1.872 | BA25: 1.872 | BB25: 2.918 | BD25: =0.859/0.3 -> 2.8633333 | BF25: 0.663 | BG25: =248.021 -> 248.021 | BJ25: =SUM(K25:BI25) -> 868.87543 | BL25: 9.947 | BQ25: =18.568*3 -> 55.704 | BS25: =2.918*5.4 -> 15.7572 | BU25: =27.853*1.9 -> 52.9207 | BV25: 1.432 | BX25: =2.918*2.1 -> 6.1278 | CB25: =18.568*3 -> 55.704 | CC25: =22.282/1.2*3 -> 55.705 | CF25: =23.343/8*6 -> 17.50725 | CG25: 7.56 | CH25: =2.631*0.6 -> 1.5786 | CK25: =2.653/0.8*0.9 -> 2.984625 | CN25: 18.568 | CS25: 13.263 | CW25: 19.895 | CX25: =248.021 -> 248.021 | CY25: 0.119 | CZ25: =2.653/0.8*3 -> 9.94875 | DB25: =2.785*2 -> 5.57 | DF25: =1.273*0.6 -> 0.7638 | DI25: =23.343/8 -> 2.917875 | DK25: 0.663 | DL25: =18.568*3 -> 55.704 | DM25: =18.568*3 -> 55.704 | DP25: =23.343/8*7.5 -> 21.884062 | DQ25: =7.958*1.5 -> 11.937 | DR25: 0.477 | DS25: =SUM(BL25:DR25) -> 748.36366 | DV25: 41.779 | DW25: 0.859 | DX25: =2.653/0.8*0.9 -> 2.984625 | EA25: =3.82 -> 3.82 | EB25: =24.802*10 -> 248.02 | ED25: 0.637 | EE25: 0.424 | EF25: 2.918 | EH25: 5.571 | EK25: 1.273 | EL25: 1.273 | EN25: =23.343/8*5 -> 14.589375 | EW25: =2.785*2 -> 5.57 | FA25: 13.263 | FB25: =1.579/0.6*1.2 -> 3.158 | FE25: =2.653/0.8*2.5 -> 8.290625 | FF25: =41.779/1.5*1.1 -> 30.637933 | FG25: 74.274 | FI25: =41.779/1.5*0.6 -> 16.7116 | FJ25: =24.802*10 -> 248.02 | FK25: =55.705 -> 55.705 | FN25: =0.928/0.5*0.6 -> 1.1136 | FP25: =55.705 -> 55.705 | FQ25: =55.705 -> 55.705 | FS25: =1.273 -> 1.273 | FU25: =SUM(DU25:FT25) -> 893.57476 | GP25: =SUM(FW25:GO25) -> 0 | GQ25: =I25-GP25 -> 574.64 | GR25: =I25 -> 574.64 | GS25: =G25 -> 836.95 | GT25: =E25 -> 748.4 | GU25: =B25 -> цинковый купорос+ сульфат цинка
A26: =A25+1 -> 17 | B26: сульфат марганца | C26: =479.34+154.75 -> 634.09 | D26: 508.28 | E26: =336.97+182.76 -> 519.73 | F26: =417.24+152.16 -> 569.4 | G26: =ROUND(AVERAGE(D26:F26),3) -> 532.47 | H26: 417.24 | I26: 1297.84 | K26: =11.813*3 -> 35.439 | M26: =14.648*8 -> 117.184 | N26: 16.427 | O26: 5.04 | W26: =17.719*1.5 -> 26.5785 | X26: =1.89*7 -> 13.23 | Z26: =1.89*2 -> 3.78 | AB26: =1.89*8 -> 15.12 | AC26: =14.648*6 -> 87.888 | AF26: 0.083 | AG26: 0.083 | AJ26: 3.623 | AK26: 2.599 | AM26: 3.15 | AO26: =3.938*2 -> 7.876 | AR26: 0.006 | AS26: 0.062 | AU26: 1.796 | AX26: =11.813*1.2 -> 14.1756 | AZ26: 0.183 | BA26: 0.195 | BB26: 1.89 | BD26: =1.243/0.3 -> 4.1433333 | BF26: 1.26 | BG26: =146.475 -> 146.475 | BJ26: =SUM(K26:BI26) -> 508.28643 | BL26: 7.875 | BQ26: =11.813*3 -> 35.439 | BS26: =1.89*5.4 -> 10.206 | BU26: =17.719*1.9 -> 33.6661 | BV26: 2.071 | BX26: =1.89*2.1 -> 3.969 | CB26: =11.813*3 -> 35.439 | CC26: =14.175/1.2*3 -> 35.4375 | CF26: =15.12/8*6 -> 11.34 | CG26: 1.89 | CK26: =3.15/0.8*0.9 -> 3.54375 | CN26: 16.427 | CS26: 25.2 | CW26: 37.8 | CX26: =146.475 -> 146.475 | CY26: 0.054 | CZ26: =3.15/0.8*3 -> 11.8125 | DB26: =2.599*2 -> 5.198 | DF26: =1.796*0.6 -> 1.0776 | DI26: =15.12/8 -> 1.89 | DK26: 1.26 | DL26: =11.813*3 -> 35.439 | DM26: =11.813*3 -> 35.439 | DP26: =15.12/8*7.5 -> 14.175 | DQ26: =4.199*1.5 -> 6.2985 | DR26: 0.283 | DS26: =SUM(BL26:DR26) -> 519.70495 | DV26: 26.578 | DW26: 1.243 | DX26: =3.15/0.8*0.9 -> 3.54375 | EA26: =0.374 -> 0.374 | EB26: =14.648*10 -> 146.48 | ED26: 0.009 | EE26: 0.042 | EF26: 1.89 | EH26: 3.544 | EK26: 1.796 | EL26: 1.796 | EN26: =15.12/8*5 -> 9.45 | EW26: =2.599*2 -> 5.198 | FA26: 25.2 | FE26: =3.15/0.8*2.5 -> 9.84375 | FF26: =26.578/1.5*1.1 -> 19.490533 | FG26: 47.25 | FI26: =26.578/1.5*0.6 -> 10.6312 | FJ26: =14.648*10 -> 146.48 | FK26: =35.438 -> 35.438 | FN26: =0.394/0.5*0.6 -> 0.4728 | FP26: =35.438 -> 35.438 | FQ26: =35.438 -> 35.438 | FS26: =1.796 -> 1.796 | FU26: =SUM(DU26:FT26) -> 569.42203 | GP26: =SUM(FW26:GO26) -> 0 | GQ26: =I26-GP26 -> 1297.84 | GR26: =I26 -> 1297.84 | GS26: =G26 -> 532.47 | GT26: =E26 -> 519.73 | GU26: =B26 -> сульфат марганца
A27: =A26+1 -> 18 | B27: калий йод | C27: =17.59 -> 17.59 | D27: 13.002 | E27: =7.878+11.047 -> 18.925 | F27: 13.96 | G27: =ROUND(AVERAGE(D27:F27),3) -> 15.296 | H27: 38.953 | I27: 24.993 | K27: =0.219*3 -> 0.657 | L27: 0.657 | M27: =0.175*8 -> 1.4 | N27: 0.174 | O27: 0.164 | P27: =0.053 -> 0.053 | Q27: 0.077 | R27: =0.053*3 -> 0.159 | T27: =0.139 -> 0.139 | U27: =0.044*1.5 -> 0.066 | V27: =0.053*4 -> 0.212 | W27: =0.219*1.5 -> 0.3285 | X27: =0.044*7 -> 0.308 | Z27: =0.044*2 -> 0.088 | AA27: =0.053*4 -> 0.212 | AB27: =0.044*8 -> 0.352 | AC27: =0.175*6 -> 1.05 | AE27: 0.21 | AF27: 0.019 | AG27: 0.019 | AH27: 0.131 | AI27: =0.219*4 -> 0.876 | AJ27: 0.84 | AK27: 0.078 | AL27: 0.026 | AM27: 0.112 | AN27: 0.153 | AO27: =0.14*2 -> 0.28 | AP27: =0.139*1.3 -> 0.1807 | AQ27: 0.047 | AR27: 0.01 | AS27: 0.015 | AT27: 0.351 | AU27: 0.053 | AV27: =0.139 -> 0.139 | AW27: 0.657 | AX27: =0.219*1.2 -> 0.2628 | AY27: 0.263 | AZ27: 0.043 | BA27: 0.043 | BB27: 0.044 | BD27: =0.042/0.3 -> 0.14 | BE27: 0.044 | BF27: 0.002 | BG27: =1.753 -> 1.753 | BH27: =0.139*0.6 -> 0.0834 | BI27: =0.053*1.1 -> 0.0583 | BJ27: =SUM(K27:BI27) -> 13.0297 | BL27: 0.877 | BN27: =0.139*1.5 -> 0.2085 | BO27: =0.219*2.4 -> 0.5256 | BP27: =0.139 -> 0.139 | BQ27: =0.219*3 -> 0.657 | BS27: =0.044*5.4 -> 0.2376 | BT27: 0.657 | BU27: =0.219*1.9 -> 0.4161 | BV27: 0.069 | BW27: 0.105 | BX27: =0.044*2.1 -> 0.0924 | BY27: =0.044*2 -> 0.088 | BZ27: =0.139 -> 0.139 | CA27: =0.053*4 -> 0.212 | CB27: =0.219*3 -> 0.657 | CC27: =0.263/1.2*3 -> 0.6575 | CD27: =0.053*4 -> 0.212 | CE27: 0.139 | CF27: =0.351/8*6 -> 0.26325 | CG27: 0.061 | CH27: =0.053*0.6 -> 0.0318 | CI27: 0.077 | CK27: =0.112/0.8*0.9 -> 0.126 | CL27: =0.032/0.6*0.9 -> 0.048 | CM27: 0.026 | CN27: 0.174 | CO27: =0.044*2 -> 0.088 | CP27: =0.139*0.3 -> 0.0417 | CQ27: 0.657 | CR27: 0.139 | CS27: 0.035 | CT27: 3.287 | CU27: 1.402 | CV27: 0.122 | CW27: 0.053 | CX27: =1.753 -> 1.753 | CY27: 0.003 | CZ27: =0.112/0.8*3 -> 0.42 | DA27: =0.18/1.3*1.5 -> 0.20769231 | DB27: =0.076*2 -> 0.152 | DC27: =0.877/4*4.5 -> 0.986625 | DD27: 0.131 | DE27: 0.153 | DF27: =0.053*0.6 -> 0.0318 | DG27: =0.139 -> 0.139 | DH27: =0.053 -> 0.053 | DI27: =0.351/8 -> 0.043875 | DK27: 0.002 | DL27: =0.219*3 -> 0.657 | DM27: =0.219*3 -> 0.657 | DN27: =0.139 -> 0.139 | DO27: =0.053*4 -> 0.212 | DP27: =0.351/8*7.5 -> 0.3290625 | DQ27: =0.073*1.5 -> 0.1095 | DR27: 0.016 | DS27: =SUM(BL27:DR27) -> 18.916005 | DU27: 0.526 | DV27: 0.329 | DW27: 0.042 | DX27: =0.112/0.8*0.9 -> 0.126 | DY27: =0.139*1.3 -> 0.1807 | EA27: =0.088 -> 0.088 | EB27: =0.175*10 -> 1.75 | EC27: 0.351 | ED27: 0.015 | EE27: 0.01 | EF27: 0.044 | EG27: =0.105/0.3*0.6 -> 0.21 | EH27: 0.066 | EI27: =0.139*0.8 -> 0.1112 | EJ27: =0.053*1.5 -> 0.0795 | EK27: 0.053 | EL27: 0.053 | EM27: 0.088 | EN27: =0.351/8*5 -> 0.219375 | EO27: =0.139*5 -> 0.695 | EP27: =0.053*2 -> 0.106 | EQ27: 0.657 | ER27: =0.029*0.3 -> 0.0087 | ES27: =0.053*3 -> 0.159 | ET27: 0.026 | EU27: 0.047 | EV27: 0.077 | EW27: =0.076*2 -> 0.152 | EX27: =0.877/4*5 -> 1.09625 | EY27: =0.18/1.3*2 -> 0.27692308 | EZ27: 0.122 | FA27: 0.035 | FB27: =0.032/0.6*1.2 -> 0.064 | FD27: 0.131 | FE27: =0.112/0.8*2.5 -> 0.35 | FF27: =0.329/1.5*1.1 -> 0.24126667 | FG27: 0.877 | FI27: =0.329/1.5*0.6 -> 0.1316 | FJ27: =0.175*10 -> 1.75 | FK27: =0.657 -> 0.657 | FL27: =0.139*0.7 -> 0.0973 | FM27: 0.139 | FO27: =0.044*1.2 -> 0.0528 | FP27: =0.657 -> 0.657 | FQ27: =0.657 -> 0.657 | FR27: 0.111 | FS27: =0.053 -> 0.053 | FT27: =0.105/0.3*0.6 -> 0.21 | FU27: =SUM(DU27:FT27) -> 13.978615 | GP27: =SUM(FW27:GO27) -> 0 | GQ27: =I27-GP27 -> 24.993 | GR27: =I27 -> 24.993 | GS27: =G27 -> 15.296 | GT27: =E27 -> 18.925 | GU27: =B27 -> калий йод
A28: =A27+1 -> 19 | B28: йодат кальция | C28: 0 | D28: 0 | E28: 0 | F28: 0 | G28: =ROUND(AVERAGE(D28:F28),3) -> 0 | H28: 0 | I28: 0 | BJ28: =SUM(K28:BI28) -> 0 | DS28: =SUM(BL28:DR28) -> 0 | FU28: =SUM(DU28:FT28) -> 0 | GP28: =SUM(FW28:GO28) -> 0 | GQ28: =I28-GP28 -> 0 | GR28: =I28 -> 0 | GS28: =G28 -> 0 | GT28: =E28 -> 0 | GU28: =B28 -> йодат кальция
A29: =A28+1 -> 20 | B29: кобальт у/к | C29: =2.445+10.61 -> 13.055 | D29: 7.9 | E29: 13.57 | F29: 8.36 | G29: =ROUND(AVERAGE(D29:F29),3) -> 9.943 | H29: 17.92 | I29: 9.56 | K29: =0.129*3 -> 0.387 | L29: 0.386 | M29: =0.097*8 -> 0.776 | N29: 0.15 | O29: 0.06 | P29: =0.03 -> 0.03 | Q29: 0.013 | R29: =0.03*3 -> 0.09 | T29: =0.075 -> 0.075 | U29: =0.026*1.5 -> 0.039 | V29: =0.03*4 -> 0.12 | W29: =0.129*1.5 -> 0.1935 | X29: =0.026*7 -> 0.182 | Z29: =0.026*2 -> 0.052 | AA29: =0.03*4 -> 0.12 | AB29: =0.026*8 -> 0.208 | AC29: =0.097*6 -> 0.582 | AE29: 0.103 | AF29: 0.023 | AG29: 0.023 | AH29: 0.077 | AI29: =0.129*4 -> 0.516 | AJ29: 0.987 | AK29: 0.047 | AL29: 0.015 | AM29: 0.051 | AN29: 0.075 | AO29: =0.064*2 -> 0.128 | AP29: =0.075*1.3 -> 0.0975 | AQ29: 0.027 | AR29: 0.011 | AS29: 0.017 | AT29: 0.172 | AU29: 0.03 | AV29: =0.075 -> 0.075 | AW29: 0.386 | AX29: =0.129*1.2 -> 0.1548 | AY29: 0.129 | AZ29: 0.05 | BA29: 0.05 | BB29: 0.026 | BD29: =0.023/0.3 -> 0.076666667 | BE29: 0.048 | BF29: 0.019 | BG29: =0.965 -> 0.965 | BH29: =0.075*0.6 -> 0.045 | BI29: =0.03*1.1 -> 0.033 | BJ29: =SUM(K29:BI29) -> 7.9204667 | BL29: 0.429 | BN29: =0.075*1.5 -> 0.1125 | BO29: =0.129*2.4 -> 0.3096 | BP29: =0.075 -> 0.075 | BQ29: =0.129*3 -> 0.387 | BS29: =0.026*5.4 -> 0.1404 | BT29: 0.386 | BU29: =0.129*1.9 -> 0.2451 | BV29: 0.038 | BW29: 0.026 | BX29: =0.026*2.1 -> 0.0546 | BY29: =0.026*2 -> 0.052 | BZ29: =0.075 -> 0.075 | CA29: =0.03*4 -> 0.12 | CB29: =0.129*3 -> 0.387 | CC29: =0.154/1.2*3 -> 0.385 | CD29: =0.03*4 -> 0.12 | CE29: 0.075 | CF29: =0.206/8*6 -> 0.1545 | CG29: 0.023 | CH29: =0.03*0.6 -> 0.018 | CI29: 0.013 | CK29: =0.051/0.8*0.9 -> 0.057375 | CL29: =0.018/0.6*0.9 -> 0.027 | CM29: 0.015 | CN29: 0.15 | CO29: =0.026*2 -> 0.052 | CP29: =0.075*0.3 -> 0.0225 | CQ29: 0.386 | CR29: 0.075 | CS29: 0.386 | CT29: 3.86 | CU29: 0.687 | CV29: 0.143 | CW29: 0.579 | CX29: =0.965 -> 0.965 | CZ29: =0.051/0.8*3 -> 0.19125 | DA29: =0.098/1.3*1.5 -> 0.11307692 | DB29: =0.047*2 -> 0.094 | DC29: =0.515/4*4.5 -> 0.579375 | DD29: 0.077 | DE29: 0.075 | DF29: =0.03*0.6 -> 0.018 | DG29: =0.075 -> 0.075 | DH29: =0.03 -> 0.03 | DI29: =0.206/8 -> 0.02575 | DK29: 0.019 | DL29: =0.129*3 -> 0.387 | DM29: =0.129*3 -> 0.387 | DN29: =0.075 -> 0.075 | DO29: =0.03*4 -> 0.12 | DP29: =0.206/8*7.5 -> 0.193125 | DQ29: =0.032*1.5 -> 0.048 | DR29: 0.008 | DS29: =SUM(BL29:DR29) -> 13.546152 | DU29: 0.309 | DV29: 0.193 | DW29: 0.023 | DX29: =0.051/0.8*0.9 -> 0.057375 | DY29: =0.075*1.3 -> 0.0975 | EA29: =0.103 -> 0.103 | EB29: =0.097*10 -> 0.97 | EC29: 0.172 | ED29: 0.017 | EE29: 0.011 | EF29: 0.026 | EG29: =0.026/0.3*0.6 -> 0.052 | EH29: 0.039 | EI29: =0.075*0.8 -> 0.06 | EJ29: =0.03*1.5 -> 0.045 | EK29: 0.03 | EL29: 0.03 | EM29: 0.097 | EN29: =0.206/8*5 -> 0.12875 | EO29: =0.075*5 -> 0.375 | EP29: =0.03*2 -> 0.06 | EQ29: 0.386 | ER29: =0.032*0.3 -> 0.0096 | ES29: =0.03*3 -> 0.09 | ET29: 0.015 | EU29: 0.027 | EV29: 0.038 | EW29: =0.047*2 -> 0.094 | EX29: =0.515/4*5 -> 0.64375 | EY29: =0.098/1.3*2 -> 0.15076923 | EZ29: 0.143 | FA29: 0.386 | FB29: =0.018/0.6*1.2 -> 0.036 | FD29: 0.077 | FE29: =0.051/0.8*2.5 -> 0.159375 | FF29: =0.193/1.5*1.1 -> 0.14153333 | FG29: 0.515 | FI29: =0.193/1.5*0.6 -> 0.0772 | FJ29: =0.097*10 -> 0.97 | FK29: =0.386 -> 0.386 | FL29: =0.075*0.7 -> 0.0525 | FM29: 0.075 | FN29: =0.005/0.5*0.6 -> 0.006 | FO29: =0.026*1.2 -> 0.0312 | FP29: =0.386 -> 0.386 | FQ29: =0.386 -> 0.386 | FR29: 0.06 | FS29: =0.03 -> 0.03 | FT29: =0.026/0.3*0.6 -> 0.052 | FU29: =SUM(DU29:FT29) -> 8.3195526 | GP29: =SUM(FW29:GO29) -> 0 | GQ29: =I29-GP29 -> 9.56 | GR29: =I29 -> 9.56 | GS29: =G29 -> 9.943 | GT29: =E29 -> 13.57 | GU29: =B29 -> кобальт у/к
A30: =A29+1 -> 21 | B30: селенит натрия | C30: 2.309 | D30: 1.864 | E30: 2.596 | F30: =2.411+0.113 -> 2.524 | G30: =ROUND(AVERAGE(D30:F30),3) -> 2.328 | H30: 2.411 | I30: 19.887 | K30: =0.078*3 -> 0.234 | M30: =0.045*8 -> 0.36 | N30: 0.094 | O30: 0.045 | W30: =0.118*1.5 -> 0.177 | Y30: =0.004*3 -> 0.012 | AC30: =0.045*6 -> 0.27 | AF30: 0.004 | AG30: 0.004 | AJ30: 0.021 | AK30: 0.016 | AM30: 0.013 | AO30: =0.016*2 -> 0.032 | AR30: 0.002 | AS30: 0.003 | AX30: =0.078*1.2 -> 0.0936 | AZ30: 0.008 | BA30: 0.008 | BD30: =0.007/0.3 -> 0.023333333 | BF30: 0.004 | BG30: =0.448 -> 0.448 | BJ30: =SUM(K30:BI30) -> 1.8719333 | BL30: 0.095 | BQ30: =0.078*3 -> 0.234 | BU30: =0.118*1.9 -> 0.2242 | BV30: 0.012 | CB30: =0.078*3 -> 0.234 | CC30: =0.094/1.2*3 -> 0.235 | CG30: 0.017 | CJ30: 0.013 | CK30: =0.013/0.8*0.9 -> 0.014625 | CN30: 0.094 | CS30: 0.076 | CT30: 0.081 | CV30: 0.053 | CW30: 0.114 | CX30: =0.448 -> 0.448 | CZ30: =0.013/0.8*3 -> 0.04875 | DB30: =0.016*2 -> 0.032 | DK30: 0.004 | DL30: =0.078*3 -> 0.234 | DM30: =0.078*3 -> 0.234 | DQ30: =0.056*1.5 -> 0.084 | DR30: 0.002 | DS30: =SUM(BL30:DR30) -> 2.583575 | DV30: 0.176 | DW30: 0.007 | DX30: =0.013/0.8*0.9 -> 0.014625 | EB30: =0.045*10 -> 0.45 | ED30: 0.003 | EE30: 0.002 | EH30: 0.024 | EW30: =0.016*2 -> 0.032 | EZ30: 0.022 | FA30: 0.076 | FE30: =0.013/0.8*2.5 -> 0.040625 | FF30: =0.176/1.5*1.1 -> 0.12906667 | FG30: 0.314 | FI30: =0.176/1.5*0.6 -> 0.0704 | FJ30: =0.045*10 -> 0.45 | FK30: =0.235 -> 0.235 | FN30: =0.017/0.5*0.6 -> 0.0204 | FP30: =0.235 -> 0.235 | FQ30: =0.235 -> 0.235 | FU30: =SUM(DU30:FT30) -> 2.5361167 | GP30: =SUM(FW30:GO30) -> 0 | GQ30: =I30-GP30 -> 19.887 | GR30: =I30 -> 19.887 | GS30: =G30 -> 2.328 | GT30: =E30 -> 2.596 | GU30: =B30 -> селенит натрия
A31: =A30+1 -> 22 | B31: Метионин | C31: 1921.02 | D31: 0 | E31: 0 | F31: 0 | G31: =ROUND(AVERAGE(D31:F31),3) -> 0 | H31: 0 | I31: 0 | BJ31: =SUM(K31:BI31) -> 0 | DS31: =SUM(BL31:DR31) -> 0 | FU31: =SUM(DU31:FT31) -> 0 | GP31: =SUM(FW31:GO31) -> 0 | GQ31: =I31-GP31 -> 0 | GR31: =I31 -> 0 | GS31: =G31 -> 0 | GT31: =E31 -> 0 | GU31: =B31 -> Метионин
A32: =A31+1 -> 23 | B32: МиТаргет (Метионин защищённый) | C32: =60.23+110.33 -> 170.56 | D32: 232.64 | E32: 221.93 | F32: 212.94 | G32: =ROUND(AVERAGE(D32:F32),3) -> 222.503 | H32: 335.1 | I32: =122.16+50 -> 172.16 | P32: =26.784 -> 26.784 | Q32: 25.056 | AH32: 120.528 | AL32: 24.106 | AQ32: 36.158 | BJ32: =SUM(K32:BI32) -> 232.632 | CH32: =26.784*0.6 -> 16.0704 | CI32: =25.056 -> 25.056 | CL32: =24.106/0.6*0.9 -> 36.159 | CM32: 24.106 | DD32: 120.528 | DS32: =SUM(BL32:DR32) -> 221.9194 | ET32: 24.106 | EU32: 36.158 | FB32: =16.07/0.6*1.2 -> 32.14 | FD32: 120.528 | FU32: =SUM(DU32:FT32) -> 212.932 | GP32: =SUM(FW32:GO32) -> 0 | GQ32: =I32-GP32 -> 172.16 | GR32: =I32 -> 172.16 | GS32: =G32 -> 222.503 | GT32: =E32 -> 221.93 | GU32: =B32 -> МиТаргет (Метионин защищённый)
A33: =A32+1 -> 24 | B33: монокальцийфосфат (МКФ) | C33: =5640.84 -> 5640.84 | D33: =64.21+3408.67 -> 3472.88 | E33: 6408.59 | F33: 6041.92 | G33: =ROUND(AVERAGE(D33:F33),3) -> 5307.797 | H33: 7182.74 | I33: =1140.82+20000 -> 21140.82 | K33: =158.76*3 -> 476.28 | L33: 468.72 | O33: 101.645 | T33: =34.272 -> 34.272 | W33: =156.331*1.5 -> 234.4965 | AH33: 51.408 | AI33: =159.264*4 -> 637.056 | AK33: 110.376 | AL33: 10.282 | AM33: 105.719 | AN33: 33.264 | AO33: =132.149*2 -> 264.298 | AP33: =34.272*1.3 -> 44.5536 | AV33: =34.272 -> 34.272 | AW33: 468.72 | AX33: =159.566*1.2 -> 191.4792 | BD33: =10.282/0.3 -> 34.273333 | BE33: 151.2 | BH33: =34.272*0.6 -> 20.5632 | BJ33: =SUM(K33:BI33) -> 3472.8778 | BL33: 428.4 | BN33: =34.272*1.5 -> 51.408 | BO33: =151.2*2.4 -> 362.88 | BP33: 34.272 | BQ33: =158.962*3 -> 476.886 | BT33: 468.72 | BU33: =156.744*1.9 -> 297.8136 | BV33: 17.136 | BW33: 79.834 | BZ33: =34.272 -> 34.272 | CB33: =158.962*3 -> 476.886 | CC33: =191.117/1.2*3 -> 477.7925 | CE33: 34.272 | CG33: 38.117 | CK33: =105.719/0.8*0.9 -> 118.93387 | CM33: 10.282 | CP33: =34.272*0.3 -> 10.2816 | CQ33: 464.184 | CR33: 34.272 | CZ33: =105.719/0.8*3 -> 396.44625 | DA33: =44.554/1.3*1.5 -> 51.408462 | DB33: =110.376*2 -> 220.752 | DC33: =637.056/4*4.5 -> 716.688 | DD33: 51.408 | DE33: 33.264 | DG33: =34.272 -> 34.272 | DL33: =159.264*3 -> 477.792 | DM33: =158.558*3 -> 475.674 | DN33: =34.272 -> 34.272 | DS33: =SUM(BL33:DR33) -> 6408.6193 | DU33: 362.154 | DV33: 235.116 | DW33: 10.282 | DX33: =105.719/0.8*0.9 -> 118.93387 | DY33: =34.272*1.3 -> 44.5536 | EG33: =79.834/0.3*0.6 -> 159.668 | EH33: 47.568 | EI33: =34.272*0.8 -> 27.4176 | EM33: 302.4 | EO33: =34.272*5 -> 171.36 | EQ33: 464.184 | ER33: =100.8*0.3 -> 30.24 | ET33: 10.282 | EV33: 16.632 | EW33: =110.376*2 -> 220.752 | EX33: =637.056/4*5 -> 796.32 | EY33: =44.554/1.3*2 -> 68.544615 | FD33: 51.408 | FE33: =105.719/0.8*2.5 -> 330.37187 | FF33: =234.814/1.5*1.1 -> 172.19693 | FG33: 631.008 | FI33: =234.814/1.5*0.6 -> 93.9256 | FK33: =475.675 -> 475.675 | FL33: =34.272*0.7 -> 23.9904 | FM33: 34.272 | FP33: =477.792 -> 477.792 | FQ33: =477.792 -> 477.792 | FR33: 27.418 | FT33: =79.834/0.3*0.6 -> 159.668 | FU33: =SUM(DU33:FT33) -> 6041.9255 | GP33: =SUM(FW33:GO33) -> 0 | GQ33: =I33-GP33 -> 21140.82 | GR33: =I33 -> 21140.82 | GS33: =G33 -> 5307.797 | GT33: =E33 -> 6408.59 | GU33: =B33 -> монокальцийфосфат (МКФ)
A34: =A33+1 -> 25 | B34: мука известняковая | C34: =32457.14 -> 32457.14 | D34: 24310.71 | E34: =24790.495+4756.595 -> 29547.09 | F34: =14823.405+11459.685 -> 26283.09 | G34: =ROUND(AVERAGE(D34:F34),3) -> 26713.63 | H34: 14823.405 | I34: 55540.315 | K34: =274.378*3 -> 823.134 | L34: 483.84 | M34: =423.698*8 -> 3389.584 | N34: 705.6 | O34: 129.422 | Q34: 14.423 | R34: =282.24*3 -> 846.72 | S34: =254.155*1.6 -> 406.648 | T34: =38.808 -> 38.808 | U34: =100.8*1.5 -> 151.2 | V34: =282.24*4 -> 1128.96 | W34: =274.378*1.5 -> 411.567 | X34: =100.8*7 -> 705.6 | Y34: =34.847*3 -> 104.541 | Z34: =100.8*2 -> 201.6 | AA34: =282.24*4 -> 1128.96 | AB34: =100.8*8 -> 806.4 | AC34: =423.597*6 -> 2541.582 | AE34: 290.304 | AG34: 129.024 | AJ34: 521.64 | AK34: 558.029 | AM34: 382.556 | AN34: 36.59 | AO34: =478.195*2 -> 956.39 | AP34: =38.808*1.3 -> 50.4504 | AQ34: 113.4 | AS34: 94.196 | AT34: 197.013 | AU34: 282.24 | AV34: =38.808 -> 38.808 | AW34: 483.84 | AX34: =274.378*1.2 -> 329.2536 | AY34: 370.57 | BA34: 329.687 | BB34: 100.8 | BC34: =45.36 -> 45.36 | BD34: =11.642/0.3 -> 38.806667 | BE34: 151.2 | BF34: 229.488 | BG34: =4228.731 -> 4228.731 | BH34: =38.808*0.6 -> 23.2848 | BI34: =282.24*1.1 -> 310.464 | BJ34: =SUM(K34:BI34) -> 24310.714 | BL34: 1098.72 | BM34: =254.155*2.5 -> 635.3875 | BN34: =38.808*1.5 -> 58.212 | BO34: =161.28*2.4 -> 387.072 | BP34: 38.808 | BQ34: =274.378*3 -> 823.134 | BR34: 1005.853 | BS34: =100.8*5.4 -> 544.32 | BT34: 483.84 | BU34: =274.378*1.9 -> 521.3182 | BV34: 19.404 | BW34: 56.398 | BX34: =100.8*2.1 -> 211.68 | BY34: =100.8*2 -> 201.6 | BZ34: =38.808 -> 38.808 | CA34: =282.24*4 -> 1128.96 | CB34: =274.378*3 -> 823.134 | CC34: =329.253/1.2*3 -> 823.1325 | CD34: =282.24*4 -> 1128.96 | CE34: 38.808 | CF34: =806.4/8*6 -> 604.8 | CG34: 48.533 | CI34: 14.423 | CJ34: 104.54 | CK34: =382.556/0.8*0.9 -> 430.3755 | CL34: =75.6/0.6*0.9 -> 113.4 | CN34: 705.6 | CO34: =100.8*2 -> 201.6 | CP34: =38.808*0.3 -> 11.6424 | CQ34: 483.84 | CR34: 38.808 | CS34: 524.16 | CT34: 1451.52 | CU34: 786.24 | CW34: 1209.6 | CX34: =4259.556 -> 4259.556 | CZ34: =382.556/0.8*3 -> 1434.585 | DA34: =50.45/1.3*1.5 -> 58.211538 | DB34: =558.029*2 -> 1116.058 | DE34: 36.59 | DF34: =282.24*0.6 -> 169.344 | DG34: =38.808 -> 38.808 | DH34: =282.24 -> 282.24 | DI34: =806.4/8 -> 100.8 | DJ34: =406.648/1.6*1.5 -> 381.2325 | DK34: 229.488 | DL34: =274.378*3 -> 823.134 | DM34: =274.378*3 -> 823.134 | DN34: =38.808 -> 38.808 | DO34: =282.24*4 -> 1128.96 | DP34: =806.4/8*7.5 -> 756 | DQ34: =705.6*1.5 -> 1058.4 | DR34: 15.12 | DS34: =SUM(BL34:DR34) -> 29547.1 | DU34: 387.072 | DV34: 411.566 | DW34: 11.642 | DX34: =382.556/0.8*0.9 -> 430.3755 | DY34: =38.808*1.3 -> 50.4504 | DZ34: 62.436 | EA34: 2177.28 | EB34: =422.876*10 -> 4228.76 | EC34: 197.013 | EE34: 62.797 | EF34: 100.8 | EG34: =56.398/0.3*0.6 -> 112.796 | EH34: 82.313 | EI34: =38.808*0.8 -> 31.0464 | EJ34: =282.24*1.5 -> 423.36 | EK34: 282.24 | EL34: 282.24 | EM34: 302.4 | EN34: =806.4/8*5 -> 504 | EO34: =38.808*5 -> 194.04 | EP34: =282.24*2 -> 564.48 | EQ34: 483.84 | ER34: =100.8*0.3 -> 30.24 | ES34: =282.24*3 -> 846.72 | EU34: 113.4 | EV34: 18.295 | EW34: =558.029*2 -> 1116.058 | EY34: =50.45/1.3*2 -> 77.615385 | EZ34: 1260 | FA34: 524.16 | FC34: 604.8 | FE34: =382.556/0.8*2.5 -> 1195.4875 | FF34: =411.566/1.5*1.1 -> 301.81507 | FG34: 1097.51 | FH34: =170.286/0.3*0.1 -> 56.762 | FI34: =411.566/1.5*0.6 -> 164.6264 | FJ34: =422.876*10 -> 4228.76 | FK34: =823.133 -> 823.133 | FL34: =38.808*0.7 -> 27.1656 | FM34: 38.808 | FN34: =151.2/0.5*0.6 -> 181.44 | FO34: =100.8*1.2 -> 120.96 | FP34: =823.133 -> 823.133 | FQ34: =823.133 -> 823.133 | FR34: 31.046 | FS34: =282.24 -> 282.24 | FT34: =56.398/0.3*0.6 -> 112.796 | FU34: =SUM(DU34:FT34) -> 26283.051 | GP34: =SUM(FW34:GO34) -> 0 | GQ34: =I34-GP34 -> 55540.315 | GR34: =I34 -> 55540.315 | GS34: =G34 -> 26713.63 | GT34: =E34 -> 29547.09 | GU34: =B34 -> мука известняковая
A35: =A34+1 -> 26 | B35: Соль пищ выварочн сорт экстра | C35: =1531.8+1626.27 -> 3158.07 | D35: 2118.11 | E35: =1505.62+2965.14 -> 4470.76 | F35: 2844.9 | G35: =ROUND(AVERAGE(D35:F35),3) -> 3144.59 | H35: 16984.86 | I35: 14139.96 | O35: 102.734 | Q35: 215.945 | R35: =40.32*3 -> 120.96 | T35: =136.08 -> 136.08 | V35: =40.32*4 -> 161.28 | AA35: =40.32*4 -> 161.28 | AK35: 114.408 | AM35: 81.043 | AN35: 135.979 | AO35: =101.304*2 -> 202.608 | AP35: =136.08*1.3 -> 176.904 | AQ35: 27.216 | AU35: 40.32 | AV35: =136.08 -> 136.08 | BC35: =43.189 -> 43.189 | BD35: =40.824/0.3 -> 136.08 | BH35: =136.08*0.6 -> 81.648 | BI35: =40.32*1.1 -> 44.352 | BJ35: =SUM(K35:BI35) -> 2118.106 | BL35: 1496.88 | BN35: =136.08*1.5 -> 204.12 | BP35: 136.08 | BV35: 68.04 | BW35: 43.243 | BZ35: =136.08 -> 136.08 | CA35: =40.32*4 -> 161.28 | CD35: =40.32*4 -> 161.28 | CE35: 136.08 | CG35: 38.525 | CI35: =215.945 -> 215.945 | CK35: =81.043/0.8*0.9 -> 91.173375 | CL35: =18.144/0.6*0.9 -> 27.216 | CP35: =136.08*0.3 -> 40.824 | CR35: 136.08 | CS35: 1.085 | CY35: 6.048 | CZ35: =81.043/0.8*3 -> 303.91125 | DA35: =176.904/1.3*1.5 -> 204.12 | DB35: =114.408*2 -> 228.816 | DE35: 135.979 | DF35: =40.32*0.6 -> 24.192 | DG35: =136.08 -> 136.08 | DH35: =40.32 -> 40.32 | DN35: =136.08 -> 136.08 | DO35: =40.32*4 -> 161.28 | DS35: =SUM(BL35:DR35) -> 4470.7576 | DW35: 40.824 | DX35: =81.043/0.8*0.9 -> 91.173375 | DY35: =136.08*1.3 -> 176.904 | EG35: =43.243/0.3*0.6 -> 86.486 | EI35: =136.08*0.8 -> 108.864 | EJ35: =40.32*1.5 -> 60.48 | EK35: 40.32 | EL35: 40.32 | EO35: =136.08*5 -> 680.4 | EP35: =40.32*2 -> 80.64 | ES35: =40.32*3 -> 120.96 | EU35: 27.216 | EV35: 67.99 | EW35: =114.408*2 -> 228.816 | EY35: =176.904/1.3*2 -> 272.16 | FA35: 1.085 | FE35: =81.043/0.8*2.5 -> 253.25938 | FL35: =136.08*0.7 -> 95.256 | FM35: 136.08 | FR35: 108.864 | FS35: =40.32 -> 40.32 | FT35: =43.243/0.3*0.6 -> 86.486 | FU35: =SUM(DU35:FT35) -> 2844.9038 | GP35: =SUM(FW35:GO35) -> 0 | GQ35: =I35-GP35 -> 14139.96 | GR35: =I35 -> 14139.96 | GS35: =G35 -> 3144.59 | GT35: =E35 -> 4470.76 | GU35: =B35 -> Соль пищ выварочн сорт экстра
H36: =SUM(H19:H35) -> 84131.231
A37: =A35+1 -> 27 | B37: Гидрокарбонат натрия Е500 (сода) | C37: 217.48 | D37: =260.88+37.51 -> 298.39 | E37: 612.99 | F37: =151.56 -> 151.56 | G37: =ROUND(AVERAGE(D37:F37),3) -> 354.313 | H37: 349.5 | I37: =197.94+2000 -> 2197.94 | AG37: 59.733 | AK37: 29.044 | AM37: 6.854 | AO37: =8.568*2 -> 17.136 | AQ37: 9.072 | AS37: 44.8 | BA37: 131.764 | BJ37: =SUM(K37:BI37) -> 298.403 | BL37: 506.066 | BW37: 6.35 | CK37: =6.854/0.8*0.9 -> 7.71075 | CL37: =6.048/0.6*0.9 -> 9.072 | CZ37: =6.854/0.8*3 -> 25.7025 | DB37: =29.044*2 -> 58.088 | DS37: =SUM(BL37:DR37) -> 612.98925 | DX37: =6.854/0.8*0.9 -> 7.71075 | EE37: 29.867 | EG37: =6.35/0.3*0.6 -> 12.7 | EU37: 9.072 | EW37: =29.044*2 -> 58.088 | FE37: =6.854/0.8*2.5 -> 21.41875 | FT37: =6.35/0.3*0.6 -> 12.7 | FU37: =SUM(DU37:FT37) -> 151.5565 | GP37: =SUM(FW37:GO37) -> 0 | GQ37: =I37-GP37 -> 2197.94 | GR37: =I37 -> 2197.94 | GS37: =G37 -> 354.313 | GT37: =E37 -> 612.99 | GU37: =B37 -> Гидрокарбонат натрия Е500 (сода)
A38: =A37+1 -> 28 | B38: Актиген | C38: =96.22+49+175+124+175+5.4 -> 624.62 | D38: =294.6+413.91 -> 708.51 | E38: =585.09+473.53 -> 1058.62 | F38: =250.47+25+164.42 -> 439.89 | G38: =ROUND(AVERAGE(D38:F38),3) -> 735.673 | H38: 200.47 | I38: =260.58+224+249 -> 733.58 | P38: =20.16 -> 20.16 | Q38: 30.24 | R38: =16.128*3 -> 48.384 | U38: =16.128*1.5 -> 24.192 | V38: =16.128*4 -> 64.512 | X38: =16.128*7 -> 112.896 | Y38: =5.04*3 -> 15.12 | Z38: =16.128*2 -> 32.256 | AA38: =16.128*4 -> 64.512 | AB38: =16.128*8 -> 129.024 | AE38: 3.024 | AF38: 0.538 | AG38: 0.538 | AH38: 48.384 | AJ38: 23.184 | AQ38: 10.886 | AR38: 0.269 | AS38: 0.403 | AT38: 3.024 | AY38: 7.56 | AZ38: 0.593 | BA38: 1.187 | BC38: =42.336 -> 42.336 | BE38: 7.56 | BI38: =16.128*1.1 -> 17.7408 | BJ38: =SUM(K38:BI38) -> 708.5228 | BL38: 126 | BR38: 136.08 | BS38: =16.128*5.4 -> 87.0912 | BX38: =16.128*2.1 -> 33.8688 | BY38: =16.128*2 -> 32.256 | CA38: =16.128*4 -> 64.512 | CD38: =16.128*4 -> 64.512 | CE38: 30.139 | CF38: =129.024/8*6 -> 96.768 | CH38: =20.16*0.6 -> 12.096 | CI38: 30.24 | CJ38: 15.12 | CL38: =7.258/0.6*0.9 -> 10.887 | CO38: =16.128*2 -> 32.256 | CS38: 20.16 | DD38: 48.384 | DH38: =16.229 -> 16.229 | DI38: =129.024/8 -> 16.128 | DO38: =16.229*4 -> 64.916 | DP38: =129.024/8*7.5 -> 120.96 | DS38: =SUM(BL38:DR38) -> 1058.603 | DZ38: 8.165 | EA38: 74.39 | EC38: 3.024 | ED38: 0.403 | EE38: 0.269 | EJ38: =16.229*1.5 -> 24.3435 | EM38: 15.12 | EN38: =129.024/8*5 -> 80.64 | EP38: =16.229*2 -> 32.458 | ER38: =5.04*0.3 -> 1.512 | ES38: =16.229*3 -> 48.687 | EU38: 10.886 | FA38: 20.16 | FB38: =12.096/0.6*1.2 -> 24.192 | FD38: 48.384 | FM38: 27.922 | FO38: =16.128*1.2 -> 19.3536 | FU38: =SUM(DU38:FT38) -> 439.9091 | GP38: =SUM(FW38:GO38) -> 0 | GQ38: =I38-GP38 -> 733.58 | GR38: =I38 -> 733.58 | GS38: =G38 -> 735.673 | GT38: =E38 -> 1058.62 | GU38: =B38 -> Актиген
A39: =A38+1 -> 29 | B39: Биогром Энерджи | C39: =49.1+164.19 -> 213.29 | D39: 109 | E39: 0 | F39: 134.41 | G39: =ROUND(AVERAGE(D39:F39),3) -> 81.137 | H39: 100.81 | I39: 16.4 | AF39: 5.376 | AR39: 37.094 | AS39: 66.528 | BJ39: =SUM(K39:BI39) -> 108.998 | DS39: =SUM(BL39:DR39) -> 0 | ED39: 55.642 | EE39: 45.168 | EZ39: 33.602 | FU39: =SUM(DU39:FT39) -> 134.412 | GP39: =SUM(FW39:GO39) -> 0 | GQ39: =I39-GP39 -> 16.4 | GR39: =I39 -> 16.4 | GS39: =G39 -> 81.137 | GT39: =E39 -> 0 | GU39: =B39 -> Биогром Энерджи
A40: =A39+1 -> 30 | B40: Биогром Холин | C40: 379.22 | D40: =344.94+53.58 -> 398.52 | E40: 363.74 | F40: 461.81 | G40: =ROUND(AVERAGE(D40:F40),3) -> 408.023 | H40: 582.68 | I40: 120.87 | P40: =30.24 -> 30.24 | Q40: 75.6 | AH40: 180 | AL40: 36 | AQ40: 54 | BC40: =22.68 -> 22.68 | BJ40: =SUM(K40:BI40) -> 398.52 | CH40: =30.24*0.6 -> 18.144 | CI40: 75.6 | CL40: =36/0.6*0.9 -> 54 | CM40: 36 | DD40: 180 | DS40: =SUM(BL40:DR40) -> 363.744 | EA40: 155.52 | ET40: 36 | EU40: 54 | FB40: =18.144/0.6*1.2 -> 36.288 | FD40: 180 | FU40: =SUM(DU40:FT40) -> 461.808 | GP40: =SUM(FW40:GO40) -> 0 | GQ40: =I40-GP40 -> 120.87 | GR40: =I40 -> 120.87 | GS40: =G40 -> 408.023 | GT40: =E40 -> 363.74 | GU40: =B40 -> Биогром Холин
A41: =A40+1 -> 31 | B41: Биоплекс марганец | C41: =1048.47 -> 1048.47 | D41: =695.01 -> 695.01 | E41: =903.58+300 -> 1203.58 | F41: =833.7 -> 833.7 | G41: =ROUND(AVERAGE(D41:F41),3) -> 910.763 | H41: 996.543 | I41: =162.843+500+499 -> 1161.843 | K41: =11.76*3 -> 35.28 | L41: 70.56 | O41: 0.538 | P41: =6.72 -> 6.72 | Q41: 7.056 | R41: =6.72*3 -> 20.16 | S41: =50.4*1.6 -> 80.64 | T41: =17.674 -> 17.674 | U41: =6.384*1.5 -> 9.576 | V41: =6.72*4 -> 26.88 | W41: =7.056*1.5 -> 10.584 | X41: =2.352*7 -> 16.464 | Z41: =2.352*2 -> 4.704 | AA41: =6.72*4 -> 26.88 | AB41: =2.352*8 -> 18.816 | AD41: 0.108 | AE41: 3.024 | AH41: 14.112 | AI41: =23.52*4 -> 94.08 | AJ41: 0.773 | AK41: 5.544 | AL41: 2.822 | AM41: 6.72 | AN41: 17.674 | AO41: =8.4*2 -> 16.8 | AP41: =17.674*1.3 -> 22.9762 | AQ41: 6.048 | AR41: 0.027 | AS41: 0.02 | AT41: 5.04 | AU41: 3.36 | AV41: =17.674 -> 17.674 | AW41: 70.56 | AX41: =11.76*1.2 -> 14.112 | AY41: 3.78 | BB41: 2.352 | BC41: =1.008 -> 1.008 | BD41: =2.651/0.3 -> 8.8366667 | BE41: 7.056 | BH41: =17.674*0.6 -> 10.6044 | BI41: =6.72*1.1 -> 7.392 | BJ41: =SUM(K41:BI41) -> 695.03527 | BL41: 16.8 | BM41: =50.4*2.5 -> 126 | BN41: =17.674*1.5 -> 26.511 | BO41: =23.52*2.4 -> 56.448 | BP41: 17.674 | BQ41: =11.76*3 -> 35.28 | BS41: =2.352*5.4 -> 12.7008 | BT41: 70.56 | BU41: =7.056*1.9 -> 13.4064 | BV41: 4.418 | BW41: 2.218 | BX41: =2.352*2.1 -> 4.9392 | BY41: =6.384*2 -> 12.768 | BZ41: =17.674 -> 17.674 | CA41: =6.72*4 -> 26.88 | CB41: =11.76*3 -> 35.28 | CC41: =14.112/1.2*3 -> 35.28 | CD41: =6.72*4 -> 26.88 | CE41: 17.674 | CF41: =18.817/8*6 -> 14.11275 | CG41: 0.202 | CH41: =6.72*0.6 -> 4.032 | CI41: 7.056 | CK41: =6.72/0.8*0.9 -> 7.56 | CL41: =4.032/0.6*0.9 -> 6.048 | CM41: 2.822 | CO41: =6.384*2 -> 12.768 | CP41: =17.674*0.3 -> 5.3022 | CQ41: 70.56 | CR41: 17.674 | CT41: 24.192 | CU41: 16.128 | CV41: 17.909 | CZ41: =6.72/0.8*3 -> 25.2 | DA41: =22.976/1.3*1.5 -> 26.510769 | DB41: =5.544*2 -> 11.088 | DC41: =94.08/4*4.5 -> 105.84 | DD41: 14.112 | DE41: 17.674 | DF41: =3.36*0.6 -> 2.016 | DG41: =17.674 -> 17.674 | DH41: =6.72 -> 6.72 | DI41: =18.817/8 -> 2.352125 | DJ41: =80.64/1.6*1.5 -> 75.6 | DL41: =11.76*3 -> 35.28 | DM41: =11.76*3 -> 35.28 | DN41: =17.674 -> 17.674 | DO41: =6.72*4 -> 26.88 | DP41: =18.817/8*7.5 -> 17.640937 | DR41: 0.302 | DS41: =SUM(BL41:DR41) -> 1203.6012 | DU41: 56.448 | DV41: 10.584 | DW41: 2.651 | DX41: =6.72/0.8*0.9 -> 7.56 | DY41: =17.674*1.3 -> 22.9762 | EC41: 5.04 | ED41: 0.04 | EE41: 0.013 | EF41: 2.352 | EG41: =2.218/0.3*0.6 -> 4.436 | EH41: 3.528 | EI41: =17.674*0.8 -> 14.1392 | EJ41: =6.72*1.5 -> 10.08 | EK41: 3.36 | EL41: 3.36 | EM41: 14.112 | EN41: =18.817/8*5 -> 11.760625 | EO41: =17.674*5 -> 88.37 | EP41: =6.72*2 -> 13.44 | EQ41: 70.56 | ER41: =4.704*0.3 -> 1.4112 | ES41: =6.72*3 -> 20.16 | ET41: 2.822 | EU41: 6.048 | EV41: 8.837 | EW41: =5.544*2 -> 11.088 | EX41: =94.08/4*5 -> 117.6 | EY41: =22.976/1.3*2 -> 35.347692 | EZ41: 17.909 | FB41: =4.032/0.6*1.2 -> 8.064 | FD41: 14.112 | FE41: =6.72/0.8*2.5 -> 21 | FF41: =10.584/1.5*1.1 -> 7.7616 | FG41: 47.04 | FI41: =10.584/1.5*0.6 -> 4.2336 | FK41: =35.28 -> 35.28 | FL41: =17.674*0.7 -> 12.3718 | FM41: 17.674 | FO41: =6.384*1.2 -> 7.6608 | FP41: =35.28 -> 35.28 | FQ41: =35.28 -> 35.28 | FR41: 14.139 | FS41: =3.36 -> 3.36 | FT41: =2.218/0.3*0.6 -> 4.436 | FU41: =SUM(DU41:FT41) -> 833.72572 | GP41: =SUM(FW41:GO41) -> 0 | GQ41: =I41-GP41 -> 1161.843 | GR41: =I41 -> 1161.843 | GS41: =G41 -> 910.763 | GT41: =E41 -> 1203.58 | GU41: =B41 -> Биоплекс марганец
A42: =A41+1 -> 32 | B42: Биоплекс медь | C42: 807.13 | D42: =129.313+448.117 -> 577.43 | E42: =750.883+289.387 -> 1040.27 | F42: 652.71 | G42: =ROUND(AVERAGE(D42:F42),3) -> 756.803 | H42: =708.613+1000 -> 1708.613 | I42: =55.903+1000 -> 1055.903 | K42: =10.08*3 -> 30.24 | L42: 60.48 | O42: 0.806 | P42: =4.032 -> 4.032 | Q42: 4.536 | R42: =4.838*3 -> 14.514 | S42: =50.4*1.6 -> 80.64 | T42: =12.751 -> 12.751 | U42: =4.838*1.5 -> 7.257 | V42: =4.838*4 -> 19.352 | W42: =6.048*1.5 -> 9.072 | X42: =2.419*7 -> 16.933 | Z42: =2.419*2 -> 4.838 | AA42: =4.838*4 -> 19.352 | AB42: =2.419*8 -> 19.352 | AE42: 4.536 | AH42: 12.096 | AI42: =20.16*4 -> 80.64 | AJ42: 1.159 | AK42: 3.024 | AL42: 2.419 | AM42: 2.822 | AN42: =12.751 -> 12.751 | AO42: =3.528*2 -> 7.056 | AP42: =12.751*1.3 -> 16.5763 | AQ42: 4.355 | AR42: 0.032 | AS42: 0.03 | AT42: 7.56 | AU42: 2.419 | AV42: =12.751 -> 12.751 | AW42: 60.48 | AX42: =10.08*1.2 -> 12.096 | AY42: 5.67 | BB42: 2.419 | BD42: =1.913/0.3 -> 6.3766667 | BE42: 3.024 | BH42: =12.751*0.6 -> 7.6506 | BI42: =4.838*1.1 -> 5.3218 | BJ42: =SUM(K42:BI42) -> 577.41937 | BL42: =25.2 -> 25.2 | BM42: =50.4*2.5 -> 126 | BN42: =12.751*1.5 -> 19.1265 | BO42: =20.16*2.4 -> 48.384 | BP42: 12.751 | BQ42: =10.08*3 -> 30.24 | BS42: =2.419*5.4 -> 13.0626 | BT42: 60.48 | BU42: =6.048*1.9 -> 11.4912 | BV42: 3.188 | BW42: 3.326 | BX42: =2.419*2.1 -> 5.0799 | BY42: =4.838*2 -> 9.676 | BZ42: =12.751 -> 12.751 | CA42: =4.838*4 -> 19.352 | CB42: =10.08*3 -> 30.24 | CC42: =12.096/1.2*3 -> 30.24 | CD42: =4.838*4 -> 19.352 | CE42: 12.751 | CF42: =19.354/8*6 -> 14.5155 | CG42: 0.302 | CH42: =4.032*0.6 -> 2.4192 | CI42: 4.536 | CK42: =2.822/0.8*0.9 -> 3.17475 | CL42: =2.903/0.6*0.9 -> 4.3545 | CM42: 2.419 | CO42: =4.838*2 -> 9.676 | CP42: =12.751*0.3 -> 3.8253 | CQ42: 60.48 | CR42: =12.751 -> 12.751 | CT42: 36.288 | CU42: 28.224 | CV42: 5.04 | CZ42: =2.822/0.8*3 -> 10.5825 | DA42: =16.577/1.3*1.5 -> 19.127308 | DB42: =3.024*2 -> 6.048 | DC42: =80.64/4*4.5 -> 90.72 | DD42: 12.096 | DE42: =12.751 -> 12.751 | DF42: =2.419*0.6 -> 1.4514 | DG42: =12.751 -> 12.751 | DH42: =4.838 -> 4.838 | DI42: =19.354/8 -> 2.41925 | DJ42: =80.64/1.6*1.5 -> 75.6 | DL42: =10.08*3 -> 30.24 | DM42: =10.08*3 -> 30.24 | DN42: =12.751 -> 12.751 | DO42: =4.838*4 -> 19.352 | DP42: =19.354/8*7.5 -> 18.144375 | DR42: 0.454 | DS42: =SUM(BL42:DR42) -> 1040.2623 | DU42: 48.384 | DV42: 9.072 | DW42: 1.913 | DX42: =2.822/0.8*0.9 -> 3.17475 | DY42: =12.751*1.3 -> 16.5763 | EC42: 7.56 | ED42: 0.048 | EE42: =0.02 -> 0.02 | EF42: 2.419 | EG42: =3.326/0.3*0.6 -> 6.652 | EH42: 3.024 | EI42: =12.751*0.8 -> 10.2008 | EJ42: =4.838*1.5 -> 7.257 | EK42: 2.419 | EL42: 2.419 | EM42: 6.048 | EN42: =19.354/8*5 -> 12.09625 | EO42: =12.751*5 -> 63.755 | EP42: =4.838*2 -> 9.676 | EQ42: 60.48 | ER42: =2.016*0.3 -> 0.6048 | ES42: =4.838*3 -> 14.514 | ET42: 2.419 | EU42: 4.355 | EV42: 6.376 | EW42: =3.024*2 -> 6.048 | EX42: =80.64/4*5 -> 100.8 | EY42: =16.577/1.3*2 -> 25.503077 | EZ42: 5.04 | FB42: =2.419/0.6*1.2 -> 4.838 | FD42: 12.096 | FE42: =2.822/0.8*2.5 -> 8.81875 | FF42: =9.072/1.5*1.1 -> 6.6528 | FG42: 40.32 | FI42: =9.072/1.5*0.6 -> 3.6288 | FK42: =30.24 -> 30.24 | FL42: =12.751*0.7 -> 8.9257 | FM42: 12.751 | FO42: =4.838*1.2 -> 5.8056 | FP42: =30.24 -> 30.24 | FQ42: =30.24 -> 30.24 | FR42: 10.201 | FS42: =2.419 -> 2.419 | FT42: =3.326/0.3*0.6 -> 6.652 | FU42: =SUM(DU42:FT42) -> 652.68263 | GP42: =SUM(FW42:GO42) -> 0 | GQ42: =I42-GP42 -> 1055.903 | GR42: =I42 -> 1055.903 | GS42: =G42 -> 756.803 | GT42: =E42 -> 1040.27 | GU42: =B42 -> Биоплекс медь
A43: =A42+1 -> 33 | B43: Биоплекс цинк | C43: =242.243+500+1171.477 -> 1913.72 | D43: =327.523+890.197 -> 1217.72 | E43: =2128.03 -> 2128.03 | F43: 1367.95 | G43: =ROUND(AVERAGE(D43:F43),3) -> 1571.233 | H43: =179.773+1000 -> 1179.773 | I43: =811.823+499 -> 1310.823 | K43: =21.84*3 -> 65.52 | L43: 131.04 | M43: =7.728*8 -> 61.824 | O43: 3.763 | P43: =6.72 -> 6.72 | Q43: 10.08 | R43: =5.376*3 -> 16.128 | S43: =67.2*1.6 -> 107.52 | T43: =14.515 -> 14.515 | U43: =12.096*1.5 -> 18.144 | V43: =5.376*4 -> 21.504 | W43: =13.104*1.5 -> 19.656 | X43: =4.704*7 -> 32.928 | Z43: =4.704*2 -> 9.408 | AA43: =5.376*4 -> 21.504 | AB43: =4.704*8 -> 37.632 | AC43: =7.728*6 -> 46.368 | AD43: 0.538 | AE43: 6.048 | AH43: 24.192 | AI43: =43.68*4 -> 174.72 | AJ43: 3.091 | AK43: 7.056 | AL43: 4.838 | AM43: 6.72 | AN43: 14.515 | AO43: =8.4*2 -> 16.8 | AP43: =14.515*1.3 -> 18.8695 | AQ43: 4.838 | AS43: 0.012 | AT43: 10.08 | AU43: 2.822 | AV43: =14.515 -> 14.515 | AW43: 131.04 | AX43: =21.84*1.2 -> 26.208 | AY43: 7.56 | BB43: 4.704 | BC43: =8.064 -> 8.064 | BD43: =2.177/0.3 -> 7.2566667 | BE43: 7.056 | BG43: =77.28 -> 77.28 | BH43: =14.515*0.6 -> 8.709 | BI43: =5.376*1.1 -> 5.9136 | BJ43: =SUM(K43:BI43) -> 1217.6998 | BL43: 25.2 | BM43: =67.2*2.5 -> 168 | BN43: =14.515*1.5 -> 21.7725 | BO43: =43.68*2.4 -> 104.832 | BP43: 14.515 | BQ43: =21.84*3 -> 65.52 | BS43: =4.704*5.4 -> 25.4016 | BT43: 131.04 | BU43: =13.104*1.9 -> 24.8976 | BV43: 3.629 | BW43: 4.435 | BX43: =4.704*2.1 -> 9.8784 | BY43: =12.096*2 -> 24.192 | BZ43: =14.515 -> 14.515 | CA43: =5.376*4 -> 21.504 | CB43: =21.84*3 -> 65.52 | CC43: =26.208/1.2*3 -> 65.52 | CD43: =5.376*4 -> 21.504 | CE43: 14.515 | CF43: =37.632/8*6 -> 28.224 | CG43: 1.411 | CH43: =6.72*0.6 -> 4.032 | CI43: 10.08 | CK43: =6.72/0.8*0.9 -> 7.56 | CL43: =3.226/0.6*0.9 -> 4.839 | CM43: 4.838 | CO43: =12.096*2 -> 24.192 | CP43: =14.515*0.3 -> 4.3545 | CQ43: 131.04 | CR43: 14.515 | CT43: 302.4 | CU43: 26.88 | CV43: 33.6 | CX43: =77.28 -> 77.28 | CZ43: =6.72/0.8*3 -> 25.2 | DA43: =18.87/1.3*1.5 -> 21.773077 | DB43: =7.056*2 -> 14.112 | DC43: =174.72/4*4.5 -> 196.56 | DD43: 24.192 | DE43: 14.515 | DF43: =2.822*0.6 -> 1.6932 | DG43: =14.515 -> 14.515 | DH43: =5.376 -> 5.376 | DI43: =37.632/8 -> 4.704 | DJ43: =107.52/1.6*1.5 -> 100.8 | DL43: =21.84*3 -> 65.52 | DM43: =21.84*3 -> 65.52 | DN43: =14.515 -> 14.515 | DO43: =5.376*4 -> 21.504 | DP43: =37.632/8*7.5 -> 35.28 | DR43: 0.605 | DS43: =SUM(BL43:DR43) -> 2128.0209 | DU43: 104.832 | DV43: 19.656 | DW43: 2.177 | DX43: =6.72/0.8*0.9 -> 7.56 | DY43: =14.515*1.3 -> 18.8695 | EB43: =7.728*10 -> 77.28 | EC43: 10.08 | EE43: 0.008 | EF43: 4.704 | EG43: =4.435/0.3*0.6 -> 8.87 | EH43: 6.552 | EI43: =14.515*0.8 -> 11.612 | EJ43: =5.376*1.5 -> 8.064 | EK43: 2.822 | EL43: 2.822 | EM43: 14.112 | EN43: =37.632/8*5 -> 23.52 | EO43: =14.515*5 -> 72.575 | EP43: =5.376*2 -> 10.752 | EQ43: 131.04 | ER43: =4.704*0.3 -> 1.4112 | ES43: =5.376*3 -> 16.128 | ET43: 4.838 | EU43: 4.838 | EV43: 7.258 | EW43: =7.056*2 -> 14.112 | EX43: =174.72/4*5 -> 218.4 | EY43: =18.87/1.3*2 -> 29.030769 | EZ43: 33.6 | FB43: =4.032/0.6*1.2 -> 8.064 | FD43: 24.192 | FE43: =6.72/0.8*2.5 -> 21 | FF43: =19.656/1.5*1.1 -> 14.4144 | FG43: 87.36 | FI43: =19.656/1.5*0.6 -> 7.8624 | FJ43: =7.728*10 -> 77.28 | FK43: =65.52 -> 65.52 | FL43: =14.515*0.7 -> 10.1605 | FM43: 14.515 | FN43: =1.008/0.5*0.6 -> 1.2096 | FO43: =12.096*1.2 -> 14.5152 | FP43: =65.52 -> 65.52 | FQ43: =65.52 -> 65.52 | FR43: 11.612 | FS43: =2.822 -> 2.822 | FT43: =4.435/0.3*0.6 -> 8.87 | FU43: =SUM(DU43:FT43) -> 1367.9606 | GP43: =SUM(FW43:GO43) -> 0 | GQ43: =I43-GP43 -> 1310.823 | GR43: =I43 -> 1310.823 | GS43: =G43 -> 1571.233 | GT43: =E43 -> 2128.03 | GU43: =B43 -> Биоплекс цинк
A44: =A43+1 -> 34 | B44: Биопромис Селен Пауэр | C44: 0 | D44: 0 | E44: 0 | F44: 0 | G44: =ROUND(AVERAGE(D44:F44),3) -> 0 | H44: 0 | I44: 0 | BJ44: =SUM(K44:BI44) -> 0 | DS44: =SUM(BL44:DR44) -> 0 | FU44: =SUM(DU44:FT44) -> 0 | GP44: =SUM(FW44:GO44) -> 0 | GQ44: =I44-GP44 -> 0 | GR44: =I44 -> 0 | GS44: =G44 -> 0 | GT44: =E44 -> 0 | GU44: =B44 -> Биопромис Селен Пауэр
A45: =A44+1 -> 35 | B45: Биопромис Хром пиколинат | C45: 60.06 | D45: =40.07+58.1 -> 98.17 | E45: 34.56 | F45: =7.34+30.92 -> 38.26 | G45: =ROUND(AVERAGE(D45:F45),3) -> 56.997 | H45: 7.34 | I45: 69.08 | AG45: 3.072 | AJ45: 88.319 | AZ45: 6.778 | BJ45: =SUM(K45:BI45) -> 98.169 | CT45: 34.564 | DS45: =SUM(BL45:DR45) -> 34.564 | EZ45: =7.34+27.352 -> 34.692 | FN45: =2.978/0.5*0.6 -> 3.5736 | FU45: =SUM(DU45:FT45) -> 38.2656 | GP45: =SUM(FW45:GO45) -> 0 | GQ45: =I45-GP45 -> 69.08 | GR45: =I45 -> 69.08 | GS45: =G45 -> 56.997 | GT45: =E45 -> 34.56 | GU45: =B45 -> Биопромис Хром пиколинат
A46: =A45+1 -> 36 | B46: Виусид-Вет | C46: 119.35 | D46: 169.44 | E46: 22.07 | F46: 104.05 | G46: =ROUND(AVERAGE(D46:F46),3) -> 98.52 | H46: =17.37+125 -> 142.37 | I46: 38.32 | O46: 4.516 | P46: 6.754 | Q46: 9.541 | R46: =6.804*3 -> 20.412 | T46: =5.645 -> 5.645 | V46: =6.804*4 -> 27.216 | AA46: =6.804*4 -> 27.216 | AD46: 20.16 | AQ46: 3.402 | AR46: 2.258 | BD46: =0.454/0.3 -> 1.5133333 | BE46: 29.938 | BH46: =5.645*0.6 -> 3.387 | BI46: =6.804*1.1 -> 7.4844 | BJ46: =SUM(K46:BI46) -> 169.44273 | BZ46: 3.528 | CH46: =2.066*0.6 -> 1.2396 | CI46: 3.175 | CL46: =1.591/0.6*0.9 -> 2.3865 | CR46: 3.911 | DG46: 3.911 | DN46: 3.911 | DS46: =SUM(BL46:DR46) -> 22.0621 | DY46: =6.048*1.3 -> 7.8624 | ED46: 2.601 | EI46: =3.911*0.8 -> 3.1288 | EM46: 49.896 | EO46: =3.911*5 -> 19.555 | ER46: =18.144*0.3 -> 5.4432 | FB46: =1.089/0.6*1.2 -> 2.178 | FH46: =11.089/0.3*0.1 -> 3.6963333 | FL46: =3.911*0.7 -> 2.7377 | FR46: 6.935 | FU46: =SUM(DU46:FT46) -> 104.03343 | GP46: =SUM(FW46:GO46) -> 0 | GQ46: =I46-GP46 -> 38.32 | GR46: =I46 -> 38.32 | GS46: =G46 -> 98.52 | GT46: =E46 -> 22.07 | GU46: =B46 -> Виусид-Вет
A47: =A46+1 -> 37 | B47: Декстроза | C47: =3476.96+8201 -> 11677.96 | D47: =1799+9632 -> 11431 | E47: =368+4000+8630.17 -> 12998.17 | F47: =1369.83+3000+136.77 -> 4506.6 | G47: =ROUND(AVERAGE(D47:F47),3) -> 9645.257 | H47: 1369.83 | I47: 14863.23 | N47: 1058.4 | P47: =131.04 -> 131.04 | U47: =302.4*1.5 -> 453.6 | X47: =302.4*7 -> 2116.8 | Y47: =756*3 -> 2268 | Z47: =302.4*2 -> 604.8 | AB47: =302.4*8 -> 2419.2 | AD47: 40.32 | AF47: 53.76 | AG47: 80.64 | AH47: 604.8 | AJ47: 695.52 | AL47: 120.96 | AQ47: 54.432 | AR47: 40.32 | AS47: 80.64 | AZ47: 35.576 | BA47: 118.589 | BB47: 302.4 | BE47: 151.2 | BJ47: =SUM(K47:BI47) -> 11430.997 | BS47: =302.4*5.4 -> 1632.96 | BX47: =302.4*2.1 -> 635.04 | BY47: =302.4*2 -> 604.8 | CF47: =2419.2/8*6 -> 1814.4 | CH47: =131.04*0.6 -> 78.624 | CJ47: 2268 | CL47: =36.288/0.6*0.9 -> 54.432 | CM47: 120.96 | CN47: 1058.4 | CO47: =302.4*2 -> 604.8 | CT47: 907.2 | CY47: 28.24 | DD47: 604.8 | DI47: =2419.2/8 -> 302.4 | DP47: =2419.2/8*7.5 -> 2268 | DR47: 15.12 | DS47: =SUM(BL47:DR47) -> 12998.176 | ED47: 60.48 | EE47: 53.76 | EF47: 302.4 | EM47: 302.4 | EN47: =2419.2/8*5 -> 1512 | ER47: =100.8*0.3 -> 30.24 | ET47: 120.96 | EU47: 54.432 | FB47: =78.624/0.6*1.2 -> 157.248 | FC47: 945 | FD47: 604.8 | FO47: =302.4*1.2 -> 362.88 | FU47: =SUM(DU47:FT47) -> 4506.6 | GP47: =SUM(FW47:GO47) -> 0 | GQ47: =I47-GP47 -> 14863.23 | GR47: =I47 -> 14863.23 | GS47: =G47 -> 9645.257 | GT47: =E47 -> 12998.17 | GU47: =B47 -> Декстроза
A48: =A47+1 -> 38 | B48: Диоксид кремния Экстрасил | C48: 0 | D48: 0 | E48: 0 | F48: 0 | G48: =ROUND(AVERAGE(D48:F48),3) -> 0 | H48: 49.97 | I48: 49.97 | BJ48: =SUM(K48:BI48) -> 0 | DS48: =SUM(BL48:DR48) -> 0 | FU48: =SUM(DU48:FT48) -> 0 | GP48: =SUM(FW48:GO48) -> 0 | GQ48: =I48-GP48 -> 49.97 | GR48: =I48 -> 49.97 | GS48: =G48 -> 0 | GT48: =E48 -> 0 | GU48: =B48 -> Диоксид кремния Экстрасил
A49: =A48+1 -> 39 | B49: Дрожжевые клетки Saccharomyces | C49: =14.98+626.89 -> 641.87 | D49: =353.11+470.24 -> 823.35 | E49: =529.76+20+511.06 -> 1060.82 | F49: 462.88 | G49: =ROUND(AVERAGE(D49:F49),3) -> 782.35 | H49: 488.94 | I49: =186.06+840 -> 1026.06 | L49: 66.528 | M49: =16.128*8 -> 129.024 | R49: =4.032*3 -> 12.096 | S49: =100.8*1.6 -> 161.28 | U49: =4.032*1.5 -> 6.048 | V49: =4.032*4 -> 16.128 | X49: =4.032*7 -> 28.224 | Z49: =4.032*2 -> 8.064 | AA49: =4.032*4 -> 16.128 | AB49: =4.032*8 -> 32.256 | AC49: =16.128*6 -> 96.768 | AH49: 12.096 | AL49: 2.419 | AW49: 66.528 | BB49: 4.032 | BG49: =161.28 -> 161.28 | BI49: =4.032*1.1 -> 4.4352 | BJ49: =SUM(K49:BI49) -> 823.3342 | BL49: 34.272 | BM49: =100.8*2.5 -> 252 | BS49: =4.032*5.4 -> 21.7728 | BT49: 66.528 | BX49: =4.032*2.1 -> 8.4672 | BY49: =4.032*2 -> 8.064 | CA49: =4.032*4 -> 16.128 | CD49: =4.032*4 -> 16.128 | CF49: =32.256/8*6 -> 24.192 | CJ49: 60.48 | CM49: 2.419 | CO49: =4.032*2 -> 8.064 | CQ49: 66.528 | CS49: 24.192 | CT49: 72.576 | CX49: =161.28 -> 161.28 | DD49: 12.096 | DH49: =4.032 -> 4.032 | DI49: =32.256/8 -> 4.032 | DJ49: =161.28/1.6*1.5 -> 151.2 | DO49: =4.032*4 -> 16.128 | DP49: =32.256/8*7.5 -> 30.24 | DS49: =SUM(BL49:DR49) -> 1060.819 | EB49: =16.128*10 -> 161.28 | EF49: 4.032 | EJ49: =4.032*1.5 -> 6.048 | EN49: =32.256/8*5 -> 20.16 | EP49: =4.032*2 -> 8.064 | EQ49: 66.528 | ES49: =4.032*3 -> 12.096 | ET49: 2.419 | FD49: 12.096 | FJ49: =16.128*10 -> 161.28 | FO49: =4.032*1.2 -> 4.8384 | FS49: =4.032 -> 4.032 | FU49: =SUM(DU49:FT49) -> 462.8734 | GP49: =SUM(FW49:GO49) -> 0 | GQ49: =I49-GP49 -> 1026.06 | GR49: =I49 -> 1026.06 | GS49: =G49 -> 782.35 | GT49: =E49 -> 1060.82 | GU49: =B49 -> Дрожжевые клетки Saccharomyces
A50: =A49+1 -> 40 | B50: Оксикап | C50: =65.742+6.378 -> 72.12 | D50: 25.19 | E50: =52.89 -> 52.89 | F50: 48.77 | G50: =ROUND(AVERAGE(D50:F50),3) -> 42.283 | H50: 15.542 | I50: 66.772 | K50: =0.449*3 -> 1.347 | L50: 1.216 | O50: 0.403 | P50: =0.05 -> 0.05 | Q50: 0.076 | R50: =0.151*3 -> 0.453 | T50: =0.469 -> 0.469 | U50: =0.151*1.5 -> 0.2265 | V50: =0.151*4 -> 0.604 | W50: =0.449*1.5 -> 0.6735 | X50: =0.151*7 -> 1.057 | Z50: =0.151*2 -> 0.302 | AA50: =0.151*4 -> 0.604 | AB50: =0.151*8 -> 1.208 | AD50: 0.01 | AE50: 1.814 | AH50: 0.454 | AI50: =0.405*4 -> 1.62 | AK50: 0.492 | AL50: 0.091 | AM50: 0.39 | AN50: 0.393 | AO50: =0.488*2 -> 0.976 | AP50: =0.469*1.3 -> 0.6097 | AQ50: 0.136 | AT50: 3.024 | AU50: 0.151 | AV50: =0.469 -> 0.469 | AW50: 1.216 | AX50: =0.449*1.2 -> 0.5388 | AY50: 2.268 | BB50: 0.151 | BC50: =0.015 -> 0.015 | BD50: =0.141/0.3 -> 0.47 | BE50: 0.756 | BH50: =0.469*0.6 -> 0.2814 | BI50: =0.151*1.1 -> 0.1661 | BJ50: =SUM(K50:BI50) -> 25.181 | BL50: 2.47 | BN50: =0.469*1.5 -> 0.7035 | BO50: =0.405*2.4 -> 0.972 | BP50: 0.469 | BQ50: =0.449*3 -> 1.347 | BR50: 0.504 | BS50: =0.151*5.4 -> 0.8154 | BT50: 1.216 | BU50: =0.449*1.9 -> 0.8531 | BV50: 0.234 | BW50: 0.144 | BX50: =0.151*2.1 -> 0.3171 | BY50: =0.151*2 -> 0.302 | BZ50: =0.469 -> 0.469 | CA50: =0.151*4 -> 0.604 | CB50: =0.449*3 -> 1.347 | CC50: =0.538/1.2*3 -> 1.345 | CD50: =0.151*4 -> 0.604 | CE50: 0.469 | CF50: =1.21/8*6 -> 0.9075 | CG50: 0.151 | CH50: =0.05*0.6 -> 0.03 | CI50: 0.076 | CK50: =0.39/0.8*0.9 -> 0.43875 | CL50: =0.091/0.6*0.9 -> 0.1365 | CM50: 0.091 | CO50: =0.151*2 -> 0.302 | CP50: =0.469*0.3 -> 0.1407 | CQ50: 1.216 | CR50: 0.469 | CS50: 20.16 | CU50: 2.016 | CZ50: =0.39/0.8*3 -> 1.4625 | DA50: =0.609/1.3*1.5 -> 0.70269231 | DB50: =0.492*2 -> 0.984 | DC50: =1.621/4*4.5 -> 1.823625 | DD50: 0.454 | DE50: 0.393 | DF50: =0.151*0.6 -> 0.0906 | DG50: =0.469 -> 0.469 | DH50: =0.151 -> 0.151 | DI50: =1.21/8 -> 0.15125 | DL50: =0.449*3 -> 1.347 | DM50: =0.449*3 -> 1.347 | DN50: =0.469 -> 0.469 | DO50: =0.151*4 -> 0.604 | DP50: =1.21/8*7.5 -> 1.134375 | DS50: =SUM(BL50:DR50) -> 52.902592 | DU50: 0.973 | DV50: 0.673 | DW50: 0.141 | DX50: =0.39/0.8*0.9 -> 0.43875 | DY50: =0.469*1.3 -> 0.6097 | DZ50: 0.03 | EC50: 3.024 | EF50: 0.151 | EG50: =0.144/0.3*0.6 -> 0.288 | EH50: 0.135 | EI50: =0.469*0.8 -> 0.3752 | EJ50: =0.151*1.5 -> 0.2265 | EK50: 0.151 | EL50: 0.151 | EM50: 1.512 | EN50: =1.21/8*5 -> 0.75625 | EO50: =0.469*5 -> 2.345 | EP50: =0.151*2 -> 0.302 | EQ50: 1.216 | ER50: =0.504*0.3 -> 0.1512 | ES50: =0.151*3 -> 0.453 | ET50: 0.091 | EU50: 0.136 | EV50: 0.197 | EW50: =0.492*2 -> 0.984 | EX50: =1.621/4*5 -> 2.02625 | EY50: =0.609/1.3*2 -> 0.93692308 | FA50: 20.16 | FB50: =0.03/0.6*1.2 -> 0.06 | FD50: 0.454 | FE50: =0.39/0.8*2.5 -> 1.21875 | FF50: =0.673/1.5*1.1 -> 0.49353333 | FG50: 1.794 | FI50: =0.673/1.5*0.6 -> 0.2692 | FK50: =1.346 -> 1.346 | FL50: =0.469*0.7 -> 0.3283 | FM50: 0.469 | FN50: =0.025/0.5*0.6 -> 0.03 | FO50: =0.151*1.2 -> 0.1812 | FP50: =1.346 -> 1.346 | FQ50: =1.346 -> 1.346 | FR50: 0.375 | FS50: =0.151 -> 0.151 | FT50: =0.144/0.3*0.6 -> 0.288 | FU50: =SUM(DU50:FT50) -> 48.783756 | GP50: =SUM(FW50:GO50) -> 0 | GQ50: =I50-GP50 -> 66.772 | GR50: =I50 -> 66.772 | GS50: =G50 -> 42.283 | GT50: =E50 -> 52.89 | GU50: =B50 -> Оксикап
A51: =A50+1 -> 41 | B51: Олеобиотик | C51: 0 | D51: 3.01 | E51: =16.99+0.3 -> 17.29 | F51: 5.65 | G51: =ROUND(AVERAGE(D51:F51),3) -> 8.65 | H51: 19.7 | I51: 14.05 | Y51: =0.504*3 -> 1.512 | AR51: 0.806 | AS51: 0.685 | BJ51: =SUM(K51:BI51) -> 3.003 | CG51: 0.998 | CH51: =2.016*0.6 -> 1.2096 | CI51: 3.024 | CJ51: 11.76 | DR51: 0.302 | DS51: =SUM(BL51:DR51) -> 17.2936 | ED51: 1.21 | FB51: =1.21/0.6*1.2 -> 2.42 | FS51: =2.016 -> 2.016 | FU51: =SUM(DU51:FT51) -> 5.646 | GP51: =SUM(FW51:GO51) -> 0 | GQ51: =I51-GP51 -> 14.05 | GR51: =I51 -> 14.05 | GS51: =G51 -> 8.65 | GT51: =E51 -> 17.29 | GU51: =B51 -> Олеобиотик
A52: =A51+1 -> 42 | B52: Оптиген | D52: 1474 | E52: 1224 | F52: 0 | G52: =ROUND(AVERAGE(D52:F52),3) -> 899.333 | H52: 0 | I52: 1226 | N52: 1225 | AJ52: 249 | BJ52: =SUM(K52:BI52) -> 1474 | CN52: 1224 | DS52: =SUM(BL52:DR52) -> 1224 | FU52: =SUM(DU52:FT52) -> 0 | GP52: =SUM(FW52:GO52) -> 0 | GQ52: =I52-GP52 -> 1226 | GR52: =I52 -> 1226 | GS52: =G52 -> 899.333 | GT52: =E52 -> 1224 | GU52: =B52 -> Оптиген
A53: =A52+1 -> 43 | B53: Оптима 100 | D53: 0 | E53: 1208.61 | F53: 291.39 | G53: =ROUND(AVERAGE(D53:F53),3) -> 500 | H53: 291.39 | I53: 0 | BJ53: =SUM(K53:BI53) -> 0 | CC53: =53.222/1.2*3 -> 133.055 | CJ53: 226.8 | CS53: 52.416 | CT53: 528.898 | CV53: 10.08 | CX53: 120.053 | DL53: =45.763*3 -> 137.289 | DS53: =SUM(BL53:DR53) -> 1208.591 | EM53: 291.39 | FU53: =SUM(DU53:FT53) -> 291.39 | GP53: =SUM(FW53:GO53) -> 0 | GQ53: =I53-GP53 -> 0 | GR53: =I53 -> 0 | GS53: =G53 -> 500 | GT53: =E53 -> 1208.61 | GU53: =B53 -> Оптима 100
A54: =A53+1 -> 44 | B54: МеноМет | C54: 82.93 | D54: 0 | E54: 0 | F54: 0 | G54: =ROUND(AVERAGE(D54:F54),3) -> 0 | H54: 0 | I54: 0 | BJ54: =SUM(K54:BI54) -> 0 | DS54: =SUM(BL54:DR54) -> 0 | FU54: =SUM(DU54:FT54) -> 0 | GP54: =SUM(FW54:GO54) -> 0 | GQ54: =I54-GP54 -> 0 | GR54: =I54 -> 0 | GS54: =G54 -> 0 | GT54: =E54 -> 0 | GU54: =B54 -> МеноМет
A55: =A54+1 -> 45 | B55: Микосорб | C55: =1725.24+400+1515.55 -> 3640.79 | D55: =508.45+2974+1091.85 -> 4574.3 | E55: =1907.15+75+699+403.78 -> 3084.93 | F55: =596.22+999+1985.56 -> 3580.78 | G55: =ROUND(AVERAGE(D55:F55),3) -> 3746.67 | H55: =596.22+999 -> 1595.22 | I55: =313.44+1000+1000 -> 2313.44 | M55: =141.12*8 -> 1128.96 | N55: 35.28 | O55: 74.189 | P55: =100.8 -> 100.8 | Q55: 60.48 | U55: =30.24*1.5 -> 45.36 | X55: =30.24*7 -> 211.68 | Y55: =5.04*3 -> 15.12 | Z55: =30.24*2 -> 60.48 | AB55: =30.24*8 -> 241.92 | AC55: =141.12*6 -> 846.72 | AD55: 4.032 | AE55: 30.24 | AF55: 5.376 | AG55: 2.688 | AH55: 75.6 | AJ55: 162.288 | AR55: 5.376 | AS55: 8.064 | AT55: 40.32 | AY55: 0.378 | AZ55: 0.058 | BA55: 0.119 | BE55: 7.56 | BG55: =1411.2 -> 1411.2 | BJ55: =SUM(K55:BI55) -> 4574.288 | BS55: =30.24*5.4 -> 163.296 | BX55: =30.24*2.1 -> 63.504 | BY55: =30.24*2 -> 60.48 | CA55: =30.24*4 -> 120.96 | CD55: =30.24*4 -> 120.96 | CF55: =241.92/8*6 -> 181.44 | CG55: 27.821 | CH55: =100.8*0.6 -> 60.48 | CI55: 60.48 | CJ55: 75.6 | CN55: 35.28 | CO55: =30.24*2 -> 60.48 | CS55: 10.08 | CT55: 4.536 | CU55: 141.12 | CV55: 1.346 | CX55: =1411.2 -> 1411.2 | DD55: 75.6 | DH55: =30.24 -> 30.24 | DI55: =241.92/8 -> 30.24 | DO55: =30.24*4 -> 120.96 | DP55: =241.92/8*7.5 -> 226.8 | DR55: 2.016 | DS55: =SUM(BL55:DR55) -> 3084.919 | EB55: =141.12*10 -> 1411.2 | EC55: 40.32 | ED55: 8.064 | EE55: 5.242 | EF55: 40.32 | EJ55: =30.24*1.5 -> 45.36 | EM55: 15.12 | EN55: =241.92/8*5 -> 151.2 | EP55: =30.24*2 -> 60.48 | ER55: =5.04*0.3 -> 1.512 | ES55: =30.24*3 -> 90.72 | EZ55: 67.198 | FB55: =60.48/0.6*1.2 -> 120.96 | FD55: 75.6 | FJ55: =141.12*10 -> 1411.2 | FO55: =30.24*1.2 -> 36.288 | FU55: =SUM(DU55:FT55) -> 3580.784 | GP55: =SUM(FW55:GO55) -> 0 | GQ55: =I55-GP55 -> 2313.44 | GR55: =I55 -> 2313.44 | GS55: =G55 -> 3746.67 | GT55: =E55 -> 3084.93 | GU55: =B55 -> Микосорб
A56: =A55+1 -> 46 | B56: МЕГАсодиум | C56: =4190.64+2372.2 -> 6562.84 | D56: =147.8+4812.05 -> 4959.85 | E56: =186.95+4999+442.82 -> 5628.77 | F56: =4557.18+1160.89 -> 5718.07 | G56: =ROUND(AVERAGE(D56:F56),3) -> 5435.563 | H56: 1557.18 | I56: 3838.11 | K56: =132.048*3 -> 396.144 | L56: 393.12 | M56: =95.76*8 -> 766.08 | Q56: 33.075 | U56: =24.192*1.5 -> 36.288 | W56: =132.048*1.5 -> 198.072 | X56: =24.192*7 -> 169.344 | Z56: =24.192*2 -> 48.384 | AB56: =24.192*8 -> 193.536 | AC56: =95.76*6 -> 574.56 | AH56: 72.576 | AI56: =131.04*4 -> 524.16 | AL56: 14.515 | AW56: 393.12 | AX56: =132.048*1.2 -> 158.4576 | BB56: 24.192 | BC56: =6.615 -> 6.615 | BG56: =957.6 -> 957.6 | BJ56: =SUM(K56:BI56) -> 4959.8386 | BO56: =131.04*2.4 -> 314.496 | BQ56: =132.048*3 -> 396.144 | BS56: =24.192*5.4 -> 130.6368 | BT56: 393.12 | BU56: =132.048*1.9 -> 250.8912 | BX56: =24.192*2.1 -> 50.8032 | BY56: =24.192*2 -> 48.384 | CB56: =132.048*3 -> 396.144 | CC56: =158.458/1.2*3 -> 396.145 | CF56: =193.536/8*6 -> 145.152 | CI56: 33.075 | CM56: 14.515 | CO56: =24.192*2 -> 48.384 | CQ56: 393.12 | CX56: =957.6 -> 957.6 | DC56: =524.16/4*4.5 -> 589.68 | DD56: 72.576 | DI56: =193.536/8 -> 24.192 | DL56: =132.048*3 -> 396.144 | DM56: =132.048*3 -> 396.144 | DP56: =193.536/8*7.5 -> 181.44 | DS56: =SUM(BL56:DR56) -> 5628.7862 | DU56: 314.496 | DV56: 198.072 | EB56: =95.76*10 -> 957.6 | EF56: 24.192 | EH56: 39.614 | EN56: =193.536/8*5 -> 120.96 | EQ56: 393.12 | ET56: 14.515 | EX56: =524.16/4*5 -> 655.2 | FD56: 72.576 | FF56: =198.072/1.5*1.1 -> 145.2528 | FG56: 528.192 | FI56: =198.072/1.5*0.6 -> 79.2288 | FJ56: =95.76*10 -> 957.6 | FK56: =396.144 -> 396.144 | FO56: =24.192*1.2 -> 29.0304 | FP56: =396.144 -> 396.144 | FQ56: =396.144 -> 396.144 | FU56: =SUM(DU56:FT56) -> 5718.081 | GP56: =SUM(FW56:GO56) -> 0 | GQ56: =I56-GP56 -> 3838.11 | GR56: =I56 -> 3838.11 | GS56: =G56 -> 5435.563 | GT56: =E56 -> 5628.77 | GU56: =B56 -> МЕГАсодиум
A57: =A56+1 -> 47 | B57: Менаро сливки | D57: 0 | E57: 0 | F57: 15.12 | G57: =ROUND(AVERAGE(D57:F57),3) -> 5.04 | I57: 4.88 | BJ57: =SUM(K57:BI57) -> 0 | EM57: 15.12 | FU57: =SUM(DU57:FT57) -> 15.12 | GP57: =SUM(FW57:GO57) -> 0 | GQ57: =I57-GP57 -> 4.88 | GR57: =I57 -> 4.88 | GS57: =G57 -> 5.04 | GT57: =E57 -> 0 | GU57: =B57 -> Менаро сливки
A59: =A57+1 -> 48 | B59: Новихол | C59: 423.6 | D59: 443.76 | E59: =408.97+146.24 -> 555.21 | F59: 354.42 | G59: =ROUND(AVERAGE(D59:F59),3) -> 451.13 | H59: 3.76 | I59: 149.34 | AE59: 38.707 | AF59: 51.61 | AR59: 25.805 | AS59: 41.126 | AT59: 16.128 | AZ59: 128.074 | BA59: 142.305 | BJ59: =SUM(K59:BI59) -> 443.755 | CU59: 141.12 | CV59: 403.2 | DR59: 10.886 | DS59: =SUM(BL59:DR59) -> 555.206 | EC59: 16.128 | ED59: 38.707 | EE59: 27.418 | EZ59: 181.44 | FC59: 90.72 | FU59: =SUM(DU59:FT59) -> 354.413 | GP59: =SUM(FW59:GO59) -> 0 | GQ59: =I59-GP59 -> 149.34 | GR59: =I59 -> 149.34 | GS59: =G59 -> 451.13 | GT59: =E59 -> 555.21 | GU59: =B59 -> Новихол
A60: =A59+1 -> 49 | B60: Нупро | D60: 0 | E60: 41.33 | F60: 0 | G60: =ROUND(AVERAGE(D60:F60),3) -> 13.777 | H60: 7.67 | I60: 7.67 | BJ60: =SUM(K60:BI60) -> 0 | CS60: 41.328 | DS60: =SUM(BL60:DR60) -> 41.328 | FU60: =SUM(DU60:FT60) -> 0 | GP60: =SUM(FW60:GO60) -> 0 | GQ60: =I60-GP60 -> 7.67 | GR60: =I60 -> 7.67 | GS60: =G60 -> 13.777 | GT60: =E60 -> 41.33 | GU60: =B60 -> Нупро
A61: =A60+1 -> 50 | B61: Карбонат калия гранул | C61: =703.06+3464.4 -> 4167.46 | D61: 3691.56 | E61: =2844.04+1481.29 -> 4325.33 | F61: 1632.5 | G61: =ROUND(AVERAGE(D61:F61),3) -> 3216.463 | H61: =2518.71+4000 -> 6518.71 | I61: =886.21+4000+3000 -> 7886.21 | Q61: 75.6 | U61: =141.12*1.5 -> 211.68 | X61: =141.12*7 -> 987.84 | Z61: =141.12*2 -> 282.24 | AB61: =141.12*8 -> 1128.96 | AG61: 71.667 | AH61: 483.84 | AL61: 96.768 | AS61: 53.75 | BA61: 158.089 | BB61: 141.12 | BJ61: =SUM(K61:BI61) -> 3691.554 | BS61: =141.12*5.4 -> 762.048 | BX61: =141.12*2.1 -> 296.352 | BY61: =141.12*2 -> 282.24 | CF61: =1128.96/8*6 -> 846.72 | CI61: =75.6 -> 75.6 | CM61: 96.768 | CO61: =141.12*2 -> 282.24 | DD61: 483.84 | DI61: =1128.96/8 -> 141.12 | DP61: =1128.96/8*7.5 -> 1058.4 | DS61: =SUM(BL61:DR61) -> 4325.328 | EE61: 35.834 | EF61: 141.12 | EN61: =1128.96/8*5 -> 705.6 | ET61: 96.768 | FD61: 483.84 | FO61: =141.12*1.2 -> 169.344 | FU61: =SUM(DU61:FT61) -> 1632.506 | GP61: =SUM(FW61:GO61) -> 0 | GQ61: =I61-GP61 -> 7886.21 | GR61: =I61 -> 7886.21 | GS61: =G61 -> 3216.463 | GT61: =E61 -> 4325.33 | GU61: =B61 -> Карбонат калия гранул
A62: =A61+1 -> 51 | B62: Карбонат калия (поташ) | C62: 0 | D62: 0 | E62: 0 | F62: 0 | G62: =ROUND(AVERAGE(D62:F62),3) -> 0 | H62: 0 | I62: 0 | BJ62: =SUM(K62:BI62) -> 0 | DS62: =SUM(BL62:DR62) -> 0 | FU62: =SUM(DU62:FT62) -> 0 | GP62: =SUM(FW62:GO62) -> 0 | GQ62: =I62-GP62 -> 0 | GR62: =I62 -> 0 | GS62: =G62 -> 0 | GT62: =E62 -> 0 | GU62: =B62 -> Карбонат калия (поташ)
A63: =A62+1 -> 52 | B63: кальций хлористый пищ Фудикс | C63: =2753.23+8669.06 -> 11422.29 | D63: 7241.79 | E63: =4089.15+7008.93 -> 11098.08 | F63: =2991.07+1454.21 -> 4445.28 | G63: =ROUND(AVERAGE(D63:F63),3) -> 7595.05 | H63: 2991.07 | I63: =3545.79+5000 -> 8545.79 | P63: =403.2 -> 403.2 | R63: =302.4*3 -> 907.2 | U63: =40.32*1.5 -> 60.48 | V63: =302.4*4 -> 1209.6 | X63: =40.32*7 -> 282.24 | Z63: =40.32*2 -> 80.64 | AA63: =302.4*4 -> 1209.6 | AB63: =40.32*8 -> 322.56 | AF63: 510.72 | AH63: 90.72 | AL63: 18.144 | AQ63: 344.736 | AU63: 302.4 | AZ63: 1126.587 | BB63: 40.32 | BI63: =302.4*1.1 -> 332.64 | BJ63: =SUM(K63:BI63) -> 7241.787 | BR63: 2721.6 | BS63: =40.32*5.4 -> 217.728 | BX63: =40.32*2.1 -> 84.672 | BY63: =40.32*2 -> 80.64 | CA63: =302.4*4 -> 1209.6 | CD63: =302.4*4 -> 1209.6 | CF63: =322.56/8*6 -> 241.92 | CH63: =403.2*0.6 -> 241.92 | CL63: =229.824/0.6*0.9 -> 344.736 | CM63: 18.144 | CO63: =40.32*2 -> 80.64 | CV63: 2520 | DD63: 90.72 | DF63: =302.4*0.6 -> 181.44 | DH63: =302.4 -> 302.4 | DI63: =322.56/8 -> 40.32 | DO63: =302.4*4 -> 1209.6 | DP63: =322.56/8*7.5 -> 302.4 | DS63: =SUM(BL63:DR63) -> 11098.08 | DZ63: 163.296 | EF63: 40.32 | EJ63: =302.4*1.5 -> 453.6 | EK63: 302.4 | EL63: 302.4 | EN63: =322.56/8*5 -> 201.6 | EP63: =302.4*2 -> 604.8 | ES63: =302.4*3 -> 907.2 | ET63: 18.144 | EU63: 344.736 | FB63: =241.92/0.6*1.2 -> 483.84 | FD63: 90.72 | FN63: =151.2/0.5*0.6 -> 181.44 | FO63: =40.32*1.2 -> 48.384 | FS63: =302.4 -> 302.4 | FU63: =SUM(DU63:FT63) -> 4445.28 | GP63: =SUM(FW63:GO63) -> 0 | GQ63: =I63-GP63 -> 8545.79 | GR63: =I63 -> 8545.79 | GS63: =G63 -> 7595.05 | GT63: =E63 -> 11098.08 | GU63: =B63 -> кальций хлористый пищ Фудикс
A64: =A63+1 -> 53 | B64: кальция пропионат | C64: =968.89+2357.72 -> 3326.61 | D64: 2923.56 | E64: =2718.72+829.65 -> 3548.37 | F64: =1170.35+342.08 -> 1512.43 | G64: =ROUND(AVERAGE(D64:F64),3) -> 2661.453 | H64: 1170.35 | I64: 9657.92 | P64: =50.757 -> 50.757 | Q64: 151.2 | U64: =100.8*1.5 -> 151.2 | X64: =100.8*7 -> 705.6 | Z64: =100.8*2 -> 201.6 | AB64: =100.8*8 -> 806.4 | AH64: 604.8 | AL64: 120.96 | BB64: 100.8 | BC64: =30.24 -> 30.24 | BJ64: =SUM(K64:BI64) -> 2923.557 | BS64: =100.8*5.4 -> 544.32 | BX64: =100.8*2.1 -> 211.68 | BY64: =100.8*2 -> 201.6 | CF64: =806.4/8*6 -> 604.8 | CH64: =50.757*0.6 -> 30.4542 | CI64: 151.2 | CM64: 120.96 | CO64: =100.8*2 -> 201.6 | CY64: 20.16 | DD64: 604.8 | DI64: =806.4/8 -> 100.8 | DP64: =806.4/8*7.5 -> 756 | DS64: =SUM(BL64:DR64) -> 3548.3742 | EF64: 100.8 | EN64: =806.4/8*5 -> 504 | ET64: 120.96 | FB64: =30.454/0.6*1.2 -> 60.908 | FD64: 604.8 | FO64: =100.8*1.2 -> 120.96 | FU64: =SUM(DU64:FT64) -> 1512.428 | GP64: =SUM(FW64:GO64) -> 0 | GQ64: =I64-GP64 -> 9657.92 | GR64: =I64 -> 9657.92 | GS64: =G64 -> 2661.453 | GT64: =E64 -> 3548.37 | GU64: =B64 -> кальция пропионат
A65: =A64+1 -> 54 | B65: Концентрат СЖК | D65: 0 | E65: 23.27 | F65: 0 | G65: =ROUND(AVERAGE(D65:F65),3) -> 7.757 | H65: 1.73 | I65: 1.73 | BJ65: =SUM(K65:BI65) -> 0 | CY65: 23.272 | DS65: =SUM(BL65:DR65) -> 23.272 | FU65: =SUM(DU65:FT65) -> 0 | GP65: =SUM(FW65:GO65) -> 0 | GQ65: =I65-GP65 -> 1.73 | GR65: =I65 -> 1.73 | GS65: =G65 -> 7.757 | GT65: =E65 -> 23.27 | GU65: =B65 -> Концентрат СЖК
A66: =A65+1 -> 55 | B66: и-сак | C66: =30.78+299+282.16 -> 611.94 | D66: =166.84+250+331.33 -> 748.17 | E66: =377.21 -> 377.21 | F66: =90.46+75+199+104.81 -> 469.27 | G66: =ROUND(AVERAGE(D66:F66),3) -> 531.55 | H66: =90.46+75+199 -> 364.46 | I66: =194.19+125 -> 319.19 | N66: 42.336 | O66: 7.258 | P66: =23.184 -> 23.184 | Q66: 30.24 | Y66: =100.8*3 -> 302.4 | AD66: 4.032 | AE66: 24.797 | AF66: 18.816 | AG66: 9.408 | AJ66: 177.821 | AQ66: 18.144 | AR66: 5.376 | AS66: 8.064 | AT66: 24.797 | AU66: 20.16 | AY66: 0.378 | AZ66: 0.593 | BA66: 0.119 | BE66: 30.24 | BJ66: =SUM(K66:BI66) -> 748.163 | CG66: 2.722 | CH66: =23.184*0.6 -> 13.9104 | CI66: 30.24 | CL66: =12.096/0.6*0.9 -> 18.144 | CN66: 29.282 | CU66: 143.136 | CV66: 87.358 | CW66: 36.288 | CY66: 1.008 | DF66: =20.16*0.6 -> 12.096 | DR66: 3.024 | DS66: =SUM(BL66:DR66) -> 377.2084 | EC66: 22.478 | ED66: 8.064 | EE66: 5.242 | EK66: 20.16 | EL66: 20.16 | EM66: 60.48 | ER66: =20.16*0.3 -> 6.048 | EU66: 18.144 | EZ66: 119.952 | FA66: 104.026 | FB66: =13.91/0.6*1.2 -> 27.82 | FC66: 56.7 | FU66: =SUM(DU66:FT66) -> 469.274 | GP66: =SUM(FW66:GO66) -> 0 | GQ66: =I66-GP66 -> 319.19 | GR66: =I66 -> 319.19 | GS66: =G66 -> 531.55 | GT66: =E66 -> 377.21 | GU66: =B66 -> и-сак
A67: =A66+1 -> 56 | B67: Селениум Ист 3000 | C67: 27.67 | D67: 7.37 | E67: 34.28 | F67: =12.78+37.08 -> 49.86 | G67: =ROUND(AVERAGE(D67:F67),3) -> 30.503 | H67: 12.78 | I67: 12.92 | Y67: =0.336*3 -> 1.008 | AE67: 2.016 | AJ67: 2.318 | AY67: 2.016 | BJ67: =SUM(K67:BI67) -> 7.358 | CJ67: 1.008 | CT67: 18.144 | CU67: 6.733 | CV67: 8.4 | DS67: =SUM(BL67:DR67) -> 34.285 | EA67: =1.693 -> 1.693 | EZ67: 6.72 | FC67: =5.785+4.37 -> 10.155 | FG67: 31.304 | FU67: =SUM(DU67:FT67) -> 49.872 | GP67: =SUM(FW67:GO67) -> 0 | GQ67: =I67-GP67 -> 12.92 | GR67: =I67 -> 12.92 | GS67: =G67 -> 30.503 | GT67: =E67 -> 34.28 | GU67: =B67 -> Селениум Ист 3000
A68: =A67+1 -> 57 | B68: Сел-плекс 2300 (Сел-плекс ) | C68: =806.79+99+25.87 -> 931.66 | D68: =473.13+313.27 -> 786.4 | E68: 1095.73 | F68: 739.53 | G68: =ROUND(AVERAGE(D68:F68),3) -> 873.887 | H68: =90+1000 -> 1090 | I68: =350.47+999 -> 1349.47 | K68: =10.957*3 -> 32.871 | L68: 65.739 | M68: =7.67*8 -> 61.36 | O68: 1.753 | P68: =3.506 -> 3.506 | Q68: 3.287 | R68: =3.506*3 -> 10.518 | S68: =59.165*1.6 -> 94.664 | T68: =9.203 -> 9.203 | U68: =4.383*1.5 -> 6.5745 | V68: =3.506*4 -> 14.024 | W68: =6.574*1.5 -> 9.861 | X68: =4.383*7 -> 30.681 | Z68: =4.383*2 -> 8.766 | AA68: =3.506*4 -> 14.024 | AB68: =4.383*8 -> 35.064 | AC68: =7.67*6 -> 46.02 | AD68: 0.35 | AH68: 13.148 | AI68: =21.913*4 -> 87.652 | AK68: 3.068 | AL68: 2.63 | AM68: 2.454 | AN68: 9.203 | AO68: =3.068*2 -> 6.136 | AP68: =9.203*1.3 -> 11.9639 | AQ68: 3.155 | AR68: 0.351 | AS68: 0.131 | AT68: 4.383 | AU68: 3.506 | AV68: =9.203 -> 9.203 | AW68: 65.739 | AX68: =10.957*1.2 -> 13.1484 | BB68: 4.3863 | BC68: =5.259 -> 5.259 | BD68: =1.381/0.3 -> 4.6033333 | BE68: 1.972 | BG68: =76.696 -> 76.696 | BH68: =9.203*0.6 -> 5.5218 | BI68: =3.506*1.1 -> 3.8566 | BJ68: =SUM(K68:BI68) -> 786.43183 | BL68: 18.626 | BM68: =59.165*2.5 -> 147.9125 | BN68: =9.203*1.5 -> 13.8045 | BO68: =21.913*2.4 -> 52.5912 | BP68: 9.203 | BQ68: =10.957*3 -> 32.871 | BS68: =4.383*5.4 -> 23.6682 | BT68: 65.739 | BU68: =6.574*1.9 -> 12.4906 | BV68: 2.301 | BW68: 1.841 | BX68: =4.383*2.1 -> 9.2043 | BY68: =4.383*2 -> 8.766 | BZ68: =9.203 -> 9.203 | CA68: =3.506*4 -> 14.024 | CB68: =10.957*3 -> 32.871 | CC68: =13.148/1.2*3 -> 32.87 | CD68: =3.506*4 -> 14.024 | CE68: 9.203 | CF68: =35.061/8*6 -> 26.29575 | CG68: 0.657 | CH68: =3.506*0.6 -> 2.1036 | CI68: 3.287 | CK68: =2.454/0.8*0.9 -> 2.76075 | CL68: =2.104/0.6*0.9 -> 3.156 | CM68: 2.63 | CO68: =4.383*2 -> 8.766 | CP68: =9.203*0.3 -> 2.7609 | CQ68: 65.739 | CR68: 9.203 | CX68: =76.696 -> 76.696 | CY68: 0.083 | CZ68: =2.454/0.8*3 -> 9.2025 | DA68: =11.965/1.3*1.5 -> 13.805769 | DB68: =3.068*2 -> 6.136 | DC68: =87.652/4*4.5 -> 98.6085 | DD68: 13.148 | DE68: 9.203 | DF68: =3.506*0.6 -> 2.1036 | DG68: =9.203 -> 9.203 | DH68: =3.506 -> 3.506 | DI68: =35.061/8 -> 4.382625 | DJ68: =94.664/1.6*1.5 -> 88.7475 | DL68: =10.957*3 -> 32.871 | DM68: =10.957*3 -> 32.871 | DN68: =9.203 -> 9.203 | DO68: =3.506*4 -> 14.024 | DP68: =35.061/8*7.5 -> 32.869687 | DR68: 0.526 | DS68: =SUM(BL68:DR68) -> 1095.7625 | DU68: 52.591 | DV68: 9.861 | DW68: 1.381 | DX68: =2.454/0.8*0.9 -> 2.76075 | DY68: =9.203*1.3 -> 11.9639 | EB68: =7.67*10 -> 76.7 | EC68: 4.383 | ED68: 0.526 | EE68: 0.088 | EF68: 4.383 | EG68: =1.841/0.3*0.6 -> 3.682 | EH68: 3.287 | EI68: =9.203*0.8 -> 7.3624 | EJ68: =3.506*1.5 -> 5.259 | EK68: 3.506 | EL68: 3.506 | EM68: 3.944 | EN68: =35.061/8*5 -> 21.913125 | EO68: =9.203*5 -> 46.015 | EP68: =3.506*2 -> 7.012 | EQ68: 65.739 | ER68: =1.315*0.3 -> 0.3945 | ES68: =3.506*3 -> 10.518 | ET68: 2.63 | EU68: 3.155 | EV68: 4.602 | EW68: =3.068*2 -> 6.136 | EX68: =87.652/4*5 -> 109.565 | EY68: =11.965/1.3*2 -> 18.407692 | FB68: =2.104/0.6*1.2 -> 4.208 | FD68: 13.148 | FE68: =2.454/0.8*2.5 -> 7.66875 | FF68: =9.861/1.5*1.1 -> 7.2314 | FI68: =9.861/1.5*0.6 -> 3.9444 | FJ68: =7.67*10 -> 76.7 | FK68: =32.87 -> 32.87 | FL68: =9.203*0.7 -> 6.4421 | FM68: 9.203 | FN68: =1.096/0.5*0.6 -> 1.3152 | FO68: =4.383*1.2 -> 5.2596 | FP68: =32.87 -> 32.87 | FQ68: =32.87 -> 32.87 | FR68: 7.363 | FS68: =3.506 -> 3.506 | FT68: =1.841/0.3*0.6 -> 3.682 | FU68: =SUM(DU68:FT68) -> 739.55282 | GP68: =SUM(FW68:GO68) -> 0 | GQ68: =I68-GP68 -> 1349.47 | GR68: =I68 -> 1349.47 | GS68: =G68 -> 873.887 | GT68: =E68 -> 1095.73 | GU68: =B68 -> Сел-плекс 2300 (Сел-плекс )
A69: =A68+1 -> 58 | B69: Сыворотка | D69: 0 | E69: 18.14 | F69: 302.4 | G69: =ROUND(AVERAGE(D69:F69),3) -> 106.847 | H69: 6.86 | I69: 4.46 | BJ69: =SUM(K69:BI69) -> 0 | CY69: 18.144 | DS69: =SUM(BL69:DR69) -> 18.144 | FC69: 302.4 | FU69: =SUM(DU69:FT69) -> 302.4 | GP69: =SUM(FW69:GO69) -> 0 | GQ69: =I69-GP69 -> 4.46 | GR69: =I69 -> 4.46 | GS69: =G69 -> 106.847 | GT69: =E69 -> 18.14 | GU69: =B69 -> Сыворотка
A70: =A69+1 -> 59 | B70: Пулкокс С | C70: =109.38+62.19 -> 171.57 | D70: 75.97 | E70: 109.69 | F70: 64.2 | G70: =ROUND(AVERAGE(D70:F70),3) -> 83.287 | H70: 52.15 | I70: 87.95 | R70: =1.599*3 -> 4.797 | U70: =2.084*1.5 -> 3.126 | V70: =1.599*4 -> 6.396 | X70: =2.084*7 -> 14.588 | Z70: =2.084*2 -> 4.168 | AA70: =1.599*4 -> 6.396 | AB70: =2.084*8 -> 16.672 | AH70: 6.252 | AL70: 1.25 | AQ70: 1.439 | AU70: 1.599 | BB70: 2.084 | BE70: 3.024 | BF70: 2.419 | BI70: =1.599*1.1 -> 1.7589 | BJ70: =SUM(K70:BI70) -> 75.9689 | BS70: =2.084*5.4 -> 11.2536 | BX70: =2.084*2.1 -> 4.3764 | BY70: =2.084*2 -> 4.168 | CA70: =1.599*4 -> 6.396 | CD70: =1.599*4 -> 6.396 | CF70: =16.668/8*6 -> 12.501 | CL70: =0.96/0.6*0.9 -> 1.44 | CM70: 1.25 | CO70: =2.084*2 -> 4.168 | CS70: 17.446 | DD70: 6.252 | DF70: =1.599*0.6 -> 0.9594 | DH70: =1.599 -> 1.599 | DI70: =16.668/8 -> 2.0835 | DK70: 2.419 | DO70: =1.599*4 -> 6.396 | DP70: =16.668/8*7.5 -> 15.62625 | DQ70: =3.295*1.5 -> 4.9425 | DS70: =SUM(BL70:DR70) -> 109.67265 | EF70: 2.084 | EJ70: =1.599*1.5 -> 2.3985 | EK70: 1.599 | EL70: 1.599 | EM70: 6.048 | EN70: =16.668/8*5 -> 10.4175 | EP70: =1.599*2 -> 3.198 | ER70: =2.016*0.3 -> 0.6048 | ES70: =1.599*3 -> 4.797 | ET70: 1.25 | EU70: 1.439 | FA70: 17.446 | FD70: 6.252 | FN70: =0.8/0.5*0.6 -> 0.96 | FO70: =2.084*1.2 -> 2.5008 | FS70: =1.599 -> 1.599 | FU70: =SUM(DU70:FT70) -> 64.1926 | GP70: =SUM(FW70:GO70) -> 0 | GQ70: =I70-GP70 -> 87.95 | GR70: =I70 -> 87.95 | GS70: =G70 -> 83.287 | GT70: =E70 -> 109.69 | GU70: =B70 -> Пулкокс С
A71: =A70+1 -> 60 | B71: Луктаром Молочно-Ванильный | C71: 251.89 | D71: =74.44+120.1 -> 194.54 | E71: =29.9+195.39 -> 225.29 | F71: =4.61+103.99 -> 108.6 | G71: =ROUND(AVERAGE(D71:F71),3) -> 176.143 | H71: 4.61 | I71: 96.01 | R71: =5.04*3 -> 15.12 | U71: =5.04*1.5 -> 7.56 | V71: =5.04*4 -> 20.16 | X71: =5.04*7 -> 35.28 | Z71: =5.04*2 -> 10.08 | AA71: =5.04*4 -> 20.16 | AB71: =5.04*8 -> 40.32 | AH71: 15.12 | AL71: 3.024 | AQ71: 4.536 | AU71: 5.04 | BB71: 5.04 | BE71: 7.56 | BI71: =5.04*1.1 -> 5.544 | BJ71: =SUM(K71:BI71) -> 194.544 | BR71: 2.016 | BS71: =5.04*5.4 -> 27.216 | BX71: =5.04*2.1 -> 10.584 | BY71: =5.04*2 -> 10.08 | CA71: =5.04*4 -> 20.16 | CD71: =5.04*4 -> 20.16 | CF71: =40.32/8*6 -> 30.24 | CL71: =3.024/0.6*0.9 -> 4.536 | CM71: 3.024 | CO71: =5.04*2 -> 10.08 | CY71: 1.008 | DD71: 15.12 | DF71: =5.04*0.6 -> 3.024 | DH71: =5.04 -> 5.04 | DI71: =40.32/8 -> 5.04 | DO71: =5.04*4 -> 20.16 | DP71: =40.32/8*7.5 -> 37.8 | DS71: =SUM(BL71:DR71) -> 225.288 | DZ71: 0.121 | EF71: 5.04 | EJ71: =5.04*1.5 -> 7.56 | EK71: 5.04 | EL71: 5.04 | EN71: =40.32/8*5 -> 25.2 | EP71: =5.04*2 -> 10.08 | ER71: =5.04*0.3 -> 1.512 | ES71: =5.04*3 -> 15.12 | ET71: 3.024 | EU71: 4.536 | FD71: 15.12 | FN71: =0.101/0.5*0.6 -> 0.1212 | FO71: =5.04*1.2 -> 6.048 | FS71: =5.04 -> 5.04 | FU71: =SUM(DU71:FT71) -> 108.6022 | GP71: =SUM(FW71:GO71) -> 0 | GQ71: =I71-GP71 -> 96.01 | GR71: =I71 -> 96.01 | GS71: =G71 -> 176.143 | GT71: =E71 -> 225.29 | GU71: =B71 -> Луктаром Молочно-Ванильный
A72: =A71+1 -> 61 | B72: Липро | C72: =675+50.96 -> 725.96 | D72: =45.04+143.99 -> 189.03 | E72: =81.01+523.79 -> 604.8 | F72: =1.21+301.19 -> 302.4 | G72: =ROUND(AVERAGE(D72:F72),3) -> 365.41 | H72: 1.21 | I72: 23.81 | AF72: 21.504 | AG72: 96.768 | AY72: 70.762 | BJ72: =SUM(K72:BI72) -> 189.034 | CT72: 604.803 | DS72: =SUM(BL72:DR72) -> 604.803 | EZ72: 302.4 | FU72: =SUM(DU72:FT72) -> 302.4 | GP72: =SUM(FW72:GO72) -> 0 | GQ72: =I72-GP72 -> 23.81 | GR72: =I72 -> 23.81 | GS72: =G72 -> 365.41 | GT72: =E72 -> 604.8 | GU72: =B72 -> Липро
A73: =A72+1 -> 62 | B73: Фекорд -2012-Ф гр.2 | C73: 16.62 | D73: 3.56 | E73: 0 | F73: 0 | G73: =ROUND(AVERAGE(D73:F73),3) -> 1.187 | H73: 0 | I73: 0 | AK73: 1.008 | AM73: 0.54 | AO73: =1.008*2 -> 2.016 | BJ73: =SUM(K73:BI73) -> 3.564 | DS73: =SUM(BL73:DR73) -> 0 | FU73: =SUM(DU73:FT73) -> 0 | GP73: =SUM(FW73:GO73) -> 0 | GQ73: =I73-GP73 -> 0 | GR73: =I73 -> 0 | GS73: =G73 -> 1.187 | GT73: =E73 -> 0 | GU73: =B73 -> Фекорд -2012-Ф гр.2
A74: =A73+1 -> 63 | B74: Файбрамакс | C74: 830.87 | D74: 362.74 | E74: 87.26 | F74: 0 | G74: =ROUND(AVERAGE(D74:F74),3) -> 150 | H74: 0 | I74: 0 | Y74: =50.4*3 -> 151.2 | AD74: 103.632 | AZ74: 16.602 | BA74: 91.313 | BJ74: =SUM(K74:BI74) -> 362.747 | CJ74: 87.26 | DS74: =SUM(BL74:DR74) -> 87.26 | FU74: =SUM(DU74:FT74) -> 0 | GP74: =SUM(FW74:GO74) -> 0 | GQ74: =I74-GP74 -> 0 | GR74: =I74 -> 0 | GS74: =G74 -> 150 | GT74: =E74 -> 87.26 | GU74: =B74 -> Файбрамакс
A75: =A74+1 -> 64 | B75: Хромсодержащие дрожжи | C75: 294.74 | D75: 356.47 | E75: 540.95 | F75: =136.26+64.95 -> 201.21 | G75: =ROUND(AVERAGE(D75:F75),3) -> 366.21 | H75: =136.26+1000 -> 1136.26 | I75: 935.05 | Q75: 7.56 | R75: =4.032*3 -> 12.096 | S75: =63*1.6 -> 100.8 | U75: =4.536*1.5 -> 6.804 | V75: =4.032*4 -> 16.128 | X75: =4.536*7 -> 31.752 | Y75: =0.756*3 -> 2.268 | Z75: =4.536*2 -> 9.072 | AA75: =4.032*4 -> 16.128 | AB75: =4.536*8 -> 36.288 | AD75: 1.008 | AH75: 15.12 | AI75: =14.364*4 -> 57.456 | AL75: 3.024 | AN75: 10.08 | AQ75: 3.629 | AR75: 0.806 | AS75: 1.21 | AU75: 3.024 | BB75: 4.536 | BC75: =7.56 -> 7.56 | BE75: 5.67 | BI75: =4.032*1.1 -> 4.4352 | BJ75: =SUM(K75:BI75) -> 356.4542 | BM75: =63*2.5 -> 157.5 | BS75: =4.536*5.4 -> 24.4944 | BX75: =4.536*2.1 -> 9.5256 | BY75: =4.536*2 -> 9.072 | CA75: =4.032*4 -> 16.128 | CD75: =4.032*4 -> 16.128 | CF75: =36.288/8*6 -> 27.216 | CI75: 7.56 | CJ75: 2.268 | CL75: =2.419/0.6*0.9 -> 3.6285 | CM75: 3.024 | CO75: =4.536*2 -> 9.072 | CV75: 10.08 | DC75: =57.456/4*4.5 -> 64.638 | DD75: 15.12 | DE75: 10.08 | DF75: =3.024*0.6 -> 1.8144 | DH75: =4.032 -> 4.032 | DI75: =36.288/8 -> 4.536 | DJ75: =100.8/1.6*1.5 -> 94.5 | DO75: =4.032*4 -> 16.128 | DP75: =36.288/8*7.5 -> 34.02 | DR75: 0.378 | DS75: =SUM(BL75:DR75) -> 540.9429 | ED75: 1.21 | EE75: 0.806 | EF75: 4.536 | EJ75: =4.032*1.5 -> 6.048 | EK75: 3.024 | EL75: 3.024 | EM75: 11.34 | EN75: =36.288/8*5 -> 22.68 | EP75: =4.032*2 -> 8.064 | ER75: =3.78*0.3 -> 1.134 | ES75: =4.032*3 -> 12.096 | ET75: 3.024 | EU75: 3.629 | EV75: 5.04 | EX75: =57.456/4*5 -> 71.82 | FD75: 15.12 | FH75: =60.48/0.3*0.1 -> 20.16 | FO75: =4.536*1.2 -> 5.4432 | FS75: =3.024 -> 3.024 | FU75: =SUM(DU75:FT75) -> 201.2222 | GP75: =SUM(FW75:GO75) -> 0 | GQ75: =I75-GP75 -> 935.05 | GR75: =I75 -> 935.05 | GS75: =G75 -> 366.21 | GT75: =E75 -> 540.95 | GU75: =B75 -> Хромсодержащие дрожжи
A76: =A75+1 -> 65 | B76: Энерфат | C76: =1417.71 -> 1417.71 | D76: 1623.53 | E76: 1095.03 | F76: 1950.6 | G76: =ROUND(AVERAGE(D76:F76),3) -> 1556.387 | H76: =6512.43+13200+10000 -> 29712.43 | I76: =4561.83+13200+10000 -> 27761.83 | K76: =39.312*3 -> 117.936 | L76: 28.726 | M76: =13.81*8 -> 110.48 | U76: =16.128*1.5 -> 24.192 | W76: =10.08*1.5 -> 15.12 | X76: =13.104*7 -> 91.728 | Y76: =8.064*3 -> 24.192 | Z76: =13.104*2 -> 26.208 | AB76: =13.104*8 -> 104.832 | AC76: =13.91*6 -> 83.46 | AF76: 26.88 | AG76: 43.008 | AL76: 18.446 | AM76: 7.741 | AQ76: 27.216 | AR76: 26.88 | AS76: 40.32 | AU76: 101.909 | AV76: =114.408 -> 114.408 | AW76: 28.726 | AX76: =59.976*1.2 -> 71.9712 | AZ76: 13.044 | BA76: 59.293 | BB76: 116.424 | BE76: 151.2 | BF76: 3.024 | BG76: =146.16 -> 146.16 | BJ76: =SUM(K76:BI76) -> 1623.5242 | BL76: 35.28 | BN76: =72.576*1.5 -> 108.864 | BO76: =16.128*2.4 -> 38.7072 | BP76: 6.048 | BQ76: =46.368*3 -> 139.104 | BR76: 120.96 | BS76: =13.104*5.4 -> 70.7616 | BT76: 38.707 | BU76: =15.725*1.9 -> 29.8775 | BV76: 14.112 | BW76: 22.136 | BX76: =13.104*2.1 -> 27.5184 | BY76: =6.048*2 -> 12.096 | CB76: =46.368*3 -> 139.104 | CK76: =7.5/0.8*0.9 -> 8.4375 | CL76: =18.144/0.6*0.9 -> 27.216 | CM76: 6.139 | CO76: =0.252*2 -> 0.504 | CP76: =72.576*0.3 -> 21.7728 | CQ76: 18.749 | CZ76: =7.5/0.8*3 -> 28.125 | DB76: =5.342*2 -> 10.684 | DF76: =99.389*0.6 -> 59.6334 | DK76: 3.659 | DM76: =31.248*3 -> 93.744 | DR76: 13.104 | DS76: =SUM(BL76:DR76) -> 1095.0434 | DU76: 13.306 | DV76: 23.587 | DW76: 8.467 | DX76: =7.5/0.8*0.9 -> 8.4375 | DZ76: 4.99 | EB76: =15.12*10 -> 151.2 | ED76: 40.32 | EE76: 26.88 | EF76: 18.043 | EG76: =20.866/0.3*0.6 -> 41.732 | EH76: 6.048 | EK76: 74.592 | EL76: 78.12 | EM76: 11.01 | ER76: =100.8*0.3 -> 30.24 | EU76: 26.762 | EW76: =5.342*2 -> 10.684 | FC76: =252*3 -> 756 | FE76: =7.5/0.8*2.5 -> 23.4375 | FF76: =9.072/1.5*1.1 -> 6.6528 | FI76: =9.072/1.5*0.6 -> 3.6288 | FJ76: =15.12*10 -> 151.2 | FK76: =71.669 -> 71.669 | FN76: =4.032/0.5*0.6 -> 4.8384 | FP76: =119.448 -> 119.448 | FQ76: =119.448 -> 119.448 | FS76: =78.12 -> 78.12 | FT76: =20.866/0.3*0.6 -> 41.732 | FU76: =SUM(DU76:FT76) -> 1950.593 | GP76: =SUM(FW76:GO76) -> 0 | GQ76: =I76-GP76 -> 27761.83 | GR76: =I76 -> 27761.83 | GS76: =G76 -> 1556.387 | GT76: =E76 -> 1095.03 | GU76: =B76 -> Энерфат
A77: =A76+1 -> 66 | B77: Эсид-Пак | C77: =37.91+12.45 -> 50.36 | D77: 12.09 | E77: 0 | F77: 0 | G77: =ROUND(AVERAGE(D77:F77),3) -> 4.03 | H77: 0 | I77: 0 | K77: =0.252*3 -> 0.756 | L77: 0.756 | M77: =0.252*8 -> 2.016 | N77: 0.882 | O77: 0.202 | P77: =0.252 -> 0.252 | Q77: 0.378 | Y77: =0.252*3 -> 0.756 | AC77: =0.252*6 -> 1.512 | AQ77: 0.227 | AU77: 0.252 | AV77: =0.252 -> 0.252 | AW77: 0.756 | AX77: =0.252*1.2 -> 0.3024 | BB77: 0.252 | BC77: =0.076 -> 0.076 | BD77: =0.076/0.3 -> 0.25333333 | BG77: =2.2 -> 2.2 | BJ77: =SUM(K77:BI77) -> 12.080733 | DS77: =SUM(BL77:DR77) -> 0 | FU77: =SUM(DU77:FT77) -> 0 | GP77: =SUM(FW77:GO77) -> 0 | GQ77: =I77-GP77 -> 0 | GR77: =I77 -> 0 | GS77: =G77 -> 4.03 | GT77: =E77 -> 0 | GU77: =B77 -> Эсид-Пак
A78: =A77+1 -> 67 | B78: ДП60-3/40/плц-127 | G78: =ROUND(AVERAGE(D78:F78),3) -> #DIV/0! | BJ78: =SUM(K78:BI78) -> 0 | DS78: =SUM(BL78:DR78) -> 0 | FU78: =SUM(DU78:FT78) -> 0 | GP78: =SUM(FW78:GO78) -> 0 | GQ78: =I78-GP78 -> 0 | GR78: =I78 -> 0 | GT78: =E78 -> 0 | GU78: =B78 -> ДП60-3/40/плц-127
A79: =A78+1 -> 68 | B79: ДП60-3/40/плц-233 | G79: =ROUND(AVERAGE(D79:F79),3) -> #DIV/0! | BJ79: =SUM(K79:BI79) -> 0 | DS79: =SUM(BL79:DR79) -> 0 | FU79: =SUM(DU79:FT79) -> 0 | GP79: =SUM(FW79:GO79) -> 0 | GQ79: =I79-GP79 -> 0 | GR79: =I79 -> 0 | GT79: =E79 -> 0 | GU79: =B79 -> ДП60-3/40/плц-233
C80: =SUM(C9:C79) -> 126749.37 | D80: =SUM(D9:D79) -> 96932.916 | E80: =SUM(E9:E79) -> 126098.34 | F80: =SUM(F9:F79) -> 89535.389 | H80: =SUM(H9:H17,H19:H35,H37:H56,H59:H79) -> 139766.88 | I80: =SUM(I9:I17,I19:I35,I37:I57,I59:I79) -> 206214.5 | GO80: =SUM(GO9:GO79) -> 0 | GP80: =SUM(GP9:GP79) -> 0 | GQ80: =SUM(GQ9:GQ79) -> 206214.5 | GR80: =SUM(GR9:GR17,GR19:GR35,GR37:GR57,GR59:GR79) -> 206214.5 | GT80: =SUM(GT9:GT79) -> 126098.34
A81: отруби/мука пшеничная | K81: =44.228*3 -> 132.684 | L81: 442.823 | M81: =100.8*8 -> 806.4 | N81: 377.436 | O81: 110.765 | P81: 19.804 | Q81: 433.208 | R81: =108.287*3 -> 324.861 | S81: =20.16*1.6 -> 32.256 | T81: =362.882 -> 362.882 | U81: =120.711*1.5 -> 181.0665 | V81: =108.287*4 -> 433.148 | W81: =80.548*1.5 -> 120.822 | X81: =131.803*7 -> 922.621 | Y81: =25.614*3 -> 76.842 | Z81: =131.803*2 -> 263.606 | AA81: =108.287*4 -> 433.148 | AB81: =131.803*8 -> 1054.424 | AC81: =100.8*6 -> 604.8 | AD81: 413.729 | AE81: 643.548 | AF81: 107.534 | AG81: 305.729 | AH81: 161.948 | AI81: =38.533*4 -> 154.132 | AJ81: 232.363 | AK81: 69.052 | AL81: 38.741 | AM81: 99.113 | AN81: 361.782 | AO81: =133.236*2 -> 266.472 | AP81: =368.527*1.3 -> 479.0851 | AQ81: 16.025 | AR81: 255.692 | AS81: 161.726 | AT81: 427.498 | AU81: 17.993 | AV81: =253.867 -> 253.867 | AW81: 442.823 | AX81: =22.757*1.2 -> 27.3084 | AY81: 839.208 | AZ81: 678.644 | BA81: 974.426 | BB81: 14.602 | BC81: =62.72 -> 62.72 | BD81: =115.276/0.3 -> 384.25333 | BE81: 741.604 | BF81: 62.624 | BG81: =1007.999 -> 1007.999 | BH81: =362.882*0.6 -> 217.7292 | BI81: =108.287*1.1 -> 119.1157 | BL81: 182.253 | BM81: =20.16*2.5 -> 50.4 | BN81: =295.901*1.5 -> 443.8515 | BO81: =168.473*2.4 -> 404.3352 | BP81: 362.479 | BQ81: =37.172*3 -> 111.516 | BR81: 151.198 | BS81: =131.803*5.4 -> 711.7362 | BT81: 433.6 | BU81: =74.49*1.9 -> 141.531 | BV81: 178.897 | BW81: 10.453 | BX81: =131.803*2.1 -> 276.7863 | BY81: =130.791*2 -> 261.582 | BZ81: 360.161 | CA81: =84.851*4 -> 339.404 | CB81: =37.222*3 -> 111.666 | CC81: =46.723/1.2*3 -> 116.8075 | CD81: =84.851*4 -> 339.404 | CE81: 338.388 | CF81: =1159.258/8*6 -> 869.4435 | CG81: 42.308 | CH81: =22.727*0.6 -> 13.6362 | CI81: 436.927 | CJ81: 110.121 | CK81: =100.054/0.8*0.9 -> 112.56075 | CL81: =11.623/0.6*0.9 -> 17.4345 | CM81: 51.048 | CN81: 392.372 | CO81: =136.635*2 -> 273.27 | CP81: =295.901*0.3 -> 88.7703 | CQ81: 458.622 | CR81: 360.248 | CS81: 1208.08 | CT81: 3254.157 | CU81: 1639.344 | CV81: 1652.462 | CW81: 1631.915 | CX81: =1007.998 -> 1007.998 | CY81: 2 | CZ81: =100.054/0.8*3 -> 375.2025 | DA81: =478.74/1.3*1.5 -> 552.39231 | DB81: =64.876*2 -> 129.752 | DC81: =153.085/4*4.5 -> 172.22063 | DD81: 162.09 | DE81: 362.158 | DF81: =20.765*0.6 -> 12.459 | DG81: 359.607 | DH81: =84.451 -> 84.451 | DI81: =1157.615/8 -> 144.70188 | DJ81: =32.255/1.6*1.5 -> 30.239063 | DK81: 61.957 | DL81: =37.27*3 -> 111.81 | DM81: =52.491*3 -> 157.473 | DN81: 359.607 | DO81: =84.451*4 -> 337.804 | DP81: =1157.615/8*7.5 -> 1085.2641 | DQ81: =272.079*1.5 -> 408.1185 | DR81: 35.686 | DU81: 429.861 | DV81: 111.779 | DW81: 107.258 | DX81: =100.054/0.8*0.9 -> 112.56075 | DY81: =362.213*1.3 -> 470.8769 | DZ81: 9.072 | EA81: 1197.235 | EB81: =100.8*10 -> 1008 | EC81: 429.876 | ED81: 384.329 | EE81: 107.729 | EF81: 72.816 | EG81: =11.682/0.3*0.6 -> 23.364 | EH81: 19.074 | EI81: =359.607*0.8 -> 287.6856 | EJ81: =84.451*1.5 -> 126.6765 | EK81: 45.262 | EL81: 41.734 | EM81: 1493.437 | EN81: =1157.615/8*5 -> 723.50937 | EO81: =359.607*5 -> 1798.035 | EP81: =84.451*2 -> 168.902 | EQ81: 476.058 | ER81: =(0.012+496.3)*0.3 -> 148.8936 | ES81: =84.451*3 -> 253.353 | ET81: 57.128 | EU81: 20.007 | EV81: 180.758 | EW81: =64.876*2 -> 129.752 | EX81: =153.085/4*5 -> 191.35625 | EY81: =478.74/1.3*2 -> 736.52308 | EZ81: 2900.141 | FA81: 1231.499 | FB81: =13.667/0.6*1.2 -> 27.334 | FC81: 249.386 | FD81: 161.656 | FE81: =100.054/0.8*2.5 -> 312.66875 | FF81: =126.171/1.5*1.1 -> 92.5254 | FG81: 350.702 | FH81: =60.48/0.3*0.1 -> 20.16 | FI81: =126.171/1.5*0.6 -> 50.4684 | FJ81: =100.8*10 -> 1008 | FK81: =207.958 -> 207.958 | FL81: =359.607*0.7 -> 251.7249 | FM81: 340.34 | FN81: =135.22/0.5*0.6 -> 162.264 | FO81: =136.63*1.2 -> 163.956 | FP81: =129.603 -> 129.603 | FQ81: =129.603 -> 129.603 | FR81: 287.664 | FS81: =66.447 -> 66.447 | FT81: =11.682/0.3*0.6 -> 23.364
A82: % мехпот. | K82: =SUM(K9:K81)/K8 -> 1008.001 | L82: =SUM(L9:L81)/L8 -> 1007.9993 | M82: =SUM(M9:M81)/M8 -> 1008.002 | N82: =SUM(N9:N81)/N8 -> 1007.9994 | O82: =SUM(O9:O81)/O8 -> 1008.0013 | P82: =SUM(P9:P81)/P8 -> 1008 | Q82: =SUM(Q9:Q81)/Q8 -> 1008.0007 | R82: =SUM(R9:R81)/R8 -> 1007.999 | ... BI82: =SUM(BI9:BI81)/BI8 -> 1007.999 | BL82: =SUM(BL9:BL81)/BL8 -> 1008 | BM82: =SUM(BM9:BM81)/BM8 -> 1008 | BN82: =SUM(BN9:BN81)/BN8 -> 1007.999 | BO82: =SUM(BO9:BO81)/BO8 -> 1007.998 | BP82: =SUM(BP9:BP81)/BP8 -> 1007.999 | BQ82: =SUM(BQ9:BQ81)/BQ8 -> 1008.001 | BR82: =SUM(BR9:BR81)/BR8 -> 1008 | BS82: =SUM(BS9:BS81)/BS8 -> 1008.001 | ... DR82: =SUM(DR9:DR81)/DR8 -> 1008 | DU82: =SUM(DU9:DU81)/DU8 -> 1008 | DV82: =SUM(DV9:DV81)/DV8 -> 1007.9993 | DW82: =SUM(DW9:DW81)/DW8 -> 1008.0033 | DX82: =SUM(DX9:DX81)/DX8 -> 1007.9987 | DY82: =SUM(DY9:DY81)/DY8 -> 1007.998 | DZ82: =SUM(DZ9:DZ81)/DZ8 -> 1008 | EA82: =SUM(EA9:EA81)/EA8 -> 1007.9997 | EB82: =SUM(EB9:EB81)/EB8 -> 1008.001 | ... FT82: =SUM(FT9:FT81)/FT8 -> 1008
H84: Полоцк
A85: МЕШКИ | C85: =C6 -> декабрь | D85: =D6 -> январь | E85: =E6 -> февраль | F85: =F6 -> март | G85: СРЕДНЕМЕСЯЧНЫЙ РАСХОД за текущий квартал | H85: Остаток на начало месяца | I85: Остаток ЗА ОТЧЕТНУЮ дату | GP85: ИТОГО | GQ85: Планируемый остаток | GR85: Запас на нач. мес. | GS85: =GS5 -> СРЕДНЕМЕСЯЧНЫЙ РАСХОД за текущий квартал | GT85: РАСХОД ЗА ПРЕДЫДУЩИЙ МЕСЯЦ
A86: первый сухостой | B86: МКТ2 560*900*140 1ый сух ОРАНЖЕВЫЕ | C86: 604 | D86: 376 | E86: 544 | F86: 508 | G86: =ROUND(AVERAGE(D86:F86),0) -> 476 | H86: 7594 | I86: =H86-FU86 -> 7086 | O86: =O8/0.025 -> 32 | T86: =T8/0.025 -> 40 | AE86: =AE8/0.025 -> 48 | AP86: =AP8/0.025 -> 52 | AT86: =AT8/0.025 -> 40 | AV86: =AV8/0.025 -> 40 | AY86: =AY8/0.025 -> 60 | BD86: =BD8/0.025 -> 40 | BH86: =BH$8/0.025 -> 24 | BJ86: =SUM(K86:BI86) -> 376 | BN86: =BN8/0.025 -> 60 | BP86: =BP8/0.025 -> 40 | BZ86: =BZ8/0.025 -> 40 | CE86: =CE8/0.025 -> 40 | CG86: =CG8/0.025 -> 12 | CP86: =CP8/0.025 -> 12 | CR86: =CR8/0.025 -> 40 | CU86: =CU8/0.025 -> 160 | DA86: =DA8/0.025 -> 60 | DG86: =DG8/0.025 -> 40 | DN86: =DN8/0.025 -> 40 | DS86: =SUM(BL86:DR86) -> 544 | DY86: =DY$8/0.025 -> 52 | EC86: =EC$8/0.025 -> 40 | EI86: =EI$8/0.025 -> 32 | EO86: =EO8/0.025 -> 200 | EY86: =EY8/0.025 -> 80 | FH86: =FH8/0.025 -> 4 | FL86: =FL$8/0.025 -> 28 | FM86: =FM$8/0.025 -> 40 | FR86: =FR$8/0.025 -> 32 | FU86: =SUM(DU86:FT86) -> 508 | GP86: =SUM(FV86:GO86) -> 0 | GQ86: =I86-GP86 -> 7086 | GR86: =H86 -> 7594 | GS86: =G86 -> 476 | GT86: =D86 -> 376
A87: второй сухостой | B87: МКТ2 560*900*140 2ой сух БИРЮЗОВЫЕ | C87: 982 | D87: 768 | E87: 876 | F87: 712 | G87: =ROUND(AVERAGE(D87:F87),0) -> 785 | H87: 2144 | I87: =H87-FU87 -> 1432 | P87: =P8/0.025 -> 40 | R87: =R8/0.025 -> 120 | V87: =V8/0.025 -> 160 | AA87: =AA8/0.025 -> 160 | AF87: =AF8/0.025 -> 32 | AN87: =AN8/0.025 -> 40 | AQ87: =AQ8/0.025 -> 36 | AR87: =AR8/0.025 -> 16 | AU87: =AU8/0.025 -> 40 | AZ87: =AZ8/0.025 -> 80 | BI87: =BI$8/0.025 -> 44 | BJ87: =SUM(K87:BI87) -> 768 | BV87: =BV8/0.025 -> 20 | BW87: =BW8/0.025 -> 12 | CA87: =CA8/0.025 -> 160 | CD87: =CD8/0.025 -> 160 | CH87: =CH8/0.025 -> 24 | CL87: =CL8/0.025 -> 36 | CV87: =CV8/0.025 -> 200 | DE87: =DE8/0.025 -> 40 | DF87: =DF8/0.025 -> 24 | DH87: =DH8/0.025 -> 40 | DO87: =DO8/0.025 -> 160 | DS87: =SUM(BL87:DR87) -> 876 | DW87: =DW8/0.025 -> 12 | EA87: =EA$8/0.025 -> 144 | ED87: =ED$8/0.025 -> 24 | EG87: =EG$8/0.025 -> 24 | EJ87: =EJ$8/0.025 -> 60 | EK87: =EK$8/0.025 -> 40 | EL87: =EL8/0.025 -> 40 | EP87: =EP8/0.025 -> 80 | ES87: =ES8/0.025 -> 120 | EU87: =EU8/0.025 -> 36 | EV87: =EV8/0.025 -> 20 | FB87: =FB8/0.025 -> 48 | FS87: =FS8/0.025 -> 40 | FT87: =FT$8/0.025 -> 24 | FU87: =SUM(DU87:FT87) -> 712 | GP87: =SUM(FV87:GO87) -> 0 | GQ87: =I87-GP87 -> 1432 | GR87: =H87 -> 2144 | GS87: =G87 -> 785 | GT87: =D87 -> 768
A88: Дойное | B88: МТЛК (о) 56*90*13 (Украина) Дойное ЗЕЛЕНЫЕ | C88: =1296+1200 -> 2496 | D88: =900+1052 -> 1952 | E88: 2512 | F88: 1996 | G88: =ROUND(AVERAGE(D88:F88),0) -> 2153 | H88: 6436 | I88: =H88-FU88 -> 4440 | K88: =K8/0.025 -> 120 | L88: =L8/0.025 -> 120 | M88: =M8/0.025 -> 320 | N88: =N8/0.025 -> 140 | W88: =W8/0.025 -> 60 | Y88: =Y8/0.025 -> 120 | AC88: =AC8/0.025 -> 240 | AI88: =AI8/0.025 -> 160 | AJ88: =AJ8/0.025 -> 92 | AW88: =AW8/0.025 -> 120 | AX88: =AX8/0.025 -> 48 | BC88: =BC8/0.025 -> 12 | BG88: =BG8/0.025 -> 400 | BJ88: =SUM(K88:BI88) -> 1952 | BL88: =BL8/0.025 -> 200 | BM88: =BM8/0.025 -> 100 | BO88: =BO8/0.025 -> 96 | BQ88: =BQ8/0.025 -> 120 | BT88: =BT8/0.025 -> 120 | BU88: =BU8/0.025 -> 76 | CB88: =CB8/0.025 -> 120 | CC88: =CC8/0.025 -> 120 | CJ88: =CJ8/0.025 -> 120 | CN88: =CN8/0.025 -> 140 | CQ88: =CQ8/0.025 -> 120 | CT88: =CT8/0.025 -> 360 | CX88: =CX8/0.025 -> 400 | DC88: =DC8/0.025 -> 180 | DL88: =DL8/0.025 -> 120 | DM88: =DM8/0.025 -> 120 | DS88: =SUM(BL88:DR88) -> 2512 | DU88: =DU8/0.025 -> 96 | DV88: =DV8/0.025 -> 60 | EB88: =EB$8/0.025 -> 400 | EH88: =EH$8/0.025 -> 12 | EQ88: =EQ$8/0.025 -> 120 | EX88: =EX8/0.025 -> 200 | FC88: =FC$8/0.025 -> 120 | FF88: =FF8/0.025 -> 44 | FG88: =FG$8/0.025 -> 160 | FI88: =FI8/0.025 -> 24 | FJ88: =FJ$8/0.025 -> 400 | FK88: =FK8/0.025 -> 120 | FP88: =FP8/0.025 -> 120 | FQ88: =FQ8/0.025 -> 120 | FU88: =SUM(DU88:FT88) -> 1996 | GP88: =SUM(FV88:GO88) -> 0 | GQ88: =I88-GP88 -> 4440 | GR88: =H88 -> 6436 | GS88: =G88 -> 2153 | GT88: =D88 -> 1952
A89: ОБЩИЙ | B89: МКТ2 560*900*140 (ОРАНЖЕВЫЙ, ОБЩИЙ): СтартАп, Антистресс, Антимастит, Калф, Хайфер и др. | C89: 892 | D89: 312 | E89: 776 | F89: 464 | G89: =ROUND(AVERAGE(D89:F89),0) -> 517 | H89: 4860 | I89: =H89-FU89 -> 4396 | S89: =S8/0.025 -> 64 | AD89: =AD8/0.025 -> 24 | AK89: =AK8/0.025 -> 40 | AM89: =AM8/0.025 -> 32 | AO89: =AO8/0.025 -> 80 | BE89: =BE8/0.025 -> 60 | BF89: =BF8/0.025 -> 12 | BJ89: =SUM(K89:BI89) -> 312 | BR89: =BR8/0.025 -> 200 | CK89: =CK8/0.025 -> 36 | CS89: =CS8/0.025 -> 80 | CW89: =CW8/0.025 -> 120 | CY89: =CY8/0.025 -> 4 | CZ89: =CZ8/0.025 -> 120 | DB89: =DB8/0.025 -> 80 | DJ89: =DJ8/0.025 -> 60 | DK89: =DK8/0.025 -> 12 | DQ89: =DQ8/0.025 -> 60 | DR89: =DR8/0.025 -> 4 | DS89: =SUM(BL89:DR89) -> 776 | DX89: =DX$8/0.025 -> 36 | DZ89: =DZ$8/0.025 -> 12 | EM89: =EM$8/0.025 -> 120 | ER89: =ER8/0.025 -> 12 | EW89: =EW8/0.025 -> 80 | FA89: =FA8/0.025 -> 80 | FE89: =FE8/0.025 -> 100 | FN89: =FN$8/0.025 -> 24 | FU89: =SUM(DU89:FT89) -> 464 | GP89: =SUM(FV89:GO89) -> 0 | GQ89: =I89-GP89 -> 4396 | GR89: =H89 -> 4860 | GS89: =G89 -> 517 | GT89: =D89 -> 312
A90: Новотел | B90: МКТ2 560*900*140 СИНИЕ | C90: 1224 | D90: 1120 | E90: 1244 | F90: 648 | G90: =ROUND(AVERAGE(D90:F90),0) -> 1004 | H90: 2440 | I90: =H90-FU90 -> 1792 | Q90: =Q8/0.025 -> 60 | U90: =U8/0.025 -> 60 | X90: =X8/0.025 -> 280 | Z90: =Z8/0.025 -> 80 | AB90: =AB8/0.025 -> 320 | AG90: =AG8/0.025 -> 32 | AH90: =AH8/0.025 -> 120 | AL90: =AL8/0.025 -> 24 | AS90: =AS8/0.025 -> 24 | BA90: =BA8/0.025 -> 80 | BB90: =BB8/0.025 -> 40 | BJ90: =SUM(K90:BI90) -> 1120 | BS90: =BS8/0.025 -> 216 | BX90: =BX8/0.025 -> 84 | BY90: =BY8/0.025 -> 80 | CF90: =CF8/0.025 -> 240 | CI90: =CI8/0.025 -> 60 | CM90: =CM8/0.025 -> 24 | CO90: =CO8/0.025 -> 80 | DD90: =DD8/0.025 -> 120 | DI90: =DI8/0.025 -> 40 | DP90: =DP8/0.025 -> 300 | DS90: =SUM(BL90:DR90) -> 1244 | EE90: =EE$8/0.025 -> 16 | EF90: =EF$8/0.025 -> 40 | EN90: =EN8/0.025 -> 200 | ET90: =ET8/0.025 -> 24 | EZ90: =EZ8/0.025 -> 200 | FD90: =FD8/0.025 -> 120 | FO90: =FO8/0.025 -> 48 | FU90: =SUM(DU90:FT90) -> 648 | GP90: =SUM(FV90:GO90) -> 0 | GQ90: =I90-GP90 -> 1792 | GR90: =H90 -> 2440 | GS90: =G90 -> 1004 | GT90: =D90 -> 1120
A91: ИТОГО МЕШКИ | H91: =SUM(H86:H90) -> 23474 | I91: =SUM(I86:I90) -> 19146 | GQ91: =SUM(GQ86:GQ90) -> 19146 | GR91: =SUM(GR86:GR90) -> 23474 | GS91: =SUM(GS86:GS90) -> 4935
B92: Стретч-пленка для паллетообмотчика (кг) | D92: 78.54 | E92: 111.5 | F92: =2.5+63 -> 65.5 | G92: =ROUND(AVERAGE(D92:F92),2) -> 85.18 | I92: 17 | GP92: =SUM(FV92:GO92) -> 0
B93: Стретч-пленка для пал/обмотчика У (кг) | F93: 4.5 | G93: =ROUND(AVERAGE(D93:F93),2) -> 4.5 | I93: 77.5 | GP93: =SUM(FV93:GO93) -> 0
C95: =H7 -> 46082
B96: Наличие на площадках: | C96: Липковская | D96: Береза | E96: Мацкевичи | F96: Сохим | G96: ИТОГО
A97: Мешки полипропиленовые | B97: 1й сух | C97: 0 | G97: =SUM(C97:F97) -> 0
B98: 2й сух | C98: 0 | G98: =SUM(C98:F98) -> 0
B99: дойное | C99: 0 | F99: 27850 | G99: =SUM(C99:F99) -> 27850
B100: общий | C100: 0 | D100: 6415 | E100: =700+5821 -> 6521 | F100: 40000 | G100: =SUM(C100:F100) -> 52936
B101: Новотел | C101: 0 | G101: =SUM(C101:F101) -> 0
B102: ламинированный | C102: 0 | E102: =4+162+29 -> 195 | G102: =SUM(C102:F102) -> 195
B103: КДК-1 Мумуша | C103: 5000 | D103: 5969 | E103: 2896 | F103: 40000 | G103: =SUM(C103:F103) -> 53865
...

Sheet 2_квартал
B1: ПРЕМИКСЫ | FN1: число | FO1: планировать закупку, держать на контроле | FT1: п. - партия | GP1: число | GQ1: планировать закупку, держать на контроле
A2: число | B2: остатки, которые надо закрыть | FN2: число | FO2: перевезти с Липковской или закупить | GP2: число | GQ2: перевезти с Липковской или закупить
A3: число | B3: на пересчет рецепта | FN3: отр. число | FO3: СРОЧНО ЗАКУПАТЬ!!!! | GP3: отр. число | GQ3: СРОЧНО ЗАКУПАТЬ!!!!
J4: ФАКТ | GC4: ПЛАН | GI4: КАЗАХСТАН
A5: № п/п | B5: сырье | C5: Полоцк КХП | G5: СРЕДНЕМЕСЯЧНЫЙ РАСХОД за текущий квартал | J5: апрель | K5: 1 | L5: 1 | M5: 3 | N5: 4 | O5: 6 | P5: 7 | Q5: 8 | R5: 12 | S5: 16 | T5: 18 | U5: 17 | V5: 14 | W5: 15 | X5: 18 | Y5: 17 | Z5: 27 | AA5: 13 | AB5: 16 | AC5: 1 | AD5: 36 | AE5: 26 | AF5: 29 | AG5: 35 | AH5: 39 | AI5: 39 | AJ5: 46 | AK5: 47 | AL5: 31 | AM5: 44 | AN5: 51 | AO5: 41 | AP5: 50 | AQ5: 58 | AR5: 57 | AS5: 59 | AT5: 12 | AU5: 25 | AV5: 24 | AW5: 21 | AX5: 63 | AY5: 22 | AZ5: 66 | BA5: 23 | BB5: 64 | BC5: 70 | BD5: 7 | BE5: 69 | BF5: 57 | BG5: 76 | BH5: 61 | BI5: 40 | BJ5: 75 | BK5: 75 | BL5: 57 | BM5: 29 | BN5: 73 | BO5: 72 | BP5: 75 | BQ5: 77 | BR5: 11 | BS5: 27 | BT5: 61 | BU5: 79 | BV5: 81 | BW5: 83 | BX5: 84 | BY5: 16 | BZ5: 17 | CA5: Расход за мес. (оперативный) | CB5: май | CC5: 7 | CD5: 92 | CE5: 15 | CF5: 46 | CG5: 90 | CH5: 40 | CI5: 13 | CJ5: 91 | CK5: 1 | CL5: 97 | CM5: 95 | CN5: 15 | CO5: 101 | CP5: 103 | CQ5: 102 | CR5: 105 | CS5: 106 | CT5: 107 | CU5: 45 | CV5: 111 | CW5: 44 | CX5: 113 | CY5: 110 | CZ5: 110 | DA5: 112 | DB5: 116 | DC5: 109 | DD5: 129 | DE5: 129 | DF5: 123 | DG5: 117 | DH5: 128 | DI5: 130 | DJ5: 135 | DK5: 131 | DL5: 137 | DM5: 140 | DN5: 138 | DO5: 139 | DP5: 141 | DQ5: 142 | DR5: 143 | DS5: 145 | DT5: 144 | DU5: Расход за текущий мес. (оперативный) | DV5: июнь | DW5: 148 | DX5: 149 | DY5: 141 | DZ5: 150 | EA5: 151 | EB5: 157 | EC5: 160 | ED5: 159 | EE5: 164 | GA5: Расход за текущий мес. (оперативный) | GD5: 155 | GE5: 166 | GF5: 167 | GG5: 168 | GH5: 171 | GO5: ИТОГО | GP5: Остаток на Полоцке после произв-ва | GQ5: Запас на ОТЧЕТНУЮ дату | GR5: среднемесячный расход за предыдущий квартал | GS5: РАСХОД ЗА предыдущий месяц
C6: среднемесячный расход за предыдущий квартал | D6: апрель | E6: май | F6: июнь | H6: Остаток на начало месяца | I6: Остаток ЗА ОТЧЕТНУЮ дату | K6: ДП60-3 дойное, Агро-Солы | L6: ДПКР-2, в к/к ФХ Юлиан, Сестричество | M6: ДП60-3 2й сух АС, Журавлиное, БИРЖА | N6: ДП60-3 дойное Мумуша, Дубрава-Агро | O6: ДП60-3 НОВОТЕЛ, Орешковичи | P6: ДП60-3 дойное, ФХ Юлиан | Q6: ДП60-3 2й сух, Орешковичи | R6: ДП60-3 дойное Мумуша, ДейриБаланс, Макарово-Агро, БИРЖА | S6: ДП60-3 НОВОТЕЛ, Савушкино | T6: ДП60-3 2й сух, Савушкино | U6: ДП60-3 1й сух, Савушкино | V6: ДП60-3 дойное Мумуша, Видомлянское | W6: ДП60-3 НОВОТЕЛ, Бакуново | X6: ДП60-3 2й сух, Савушкина пуща | Y6: ДП60-3 1й сух, Савушкина пуща | Z6: ДП60-3 НОВОТЕЛ, ФХ Юлиан | AA6: ДПКР-2 Хайфер, ФХ Юлиан | AB6: ДП60-3 НОВОТЕЛ, Савушкина пуща | AC6: ДП60-3 дойное, Агро-Солы | AD6: ДП60-3, дойное, Полесская нива | AE6: ДП60-3 1й сух, ФХ Юлиан | AF6: ДП60-3 1й сух, 1 Мая | AG6: ДП60-3 2й сух, ФХ Юлиан | AH6: ДП60-3 дойное, Савушкина пуща | AI6: ДП60-3 дойное, Савушкина пуща | AJ6: ДП60-3 дойное, Киселевцы | AK6: ДП60-3 дойное, 1 Мая | AL6: ДП60-3, ЭНЕРГЕТИК | AM6: ДП60-3 дойное, Бакуново | AN6: ДП60-3 1й сух, Осовецкий | AO6: ДП60-3 2й сух, Бакуново | AP6: ДП60-3 АС, Киселевцы | AQ6: ДП60-3 2й сух, Осовецкий | AR6: ДП60-3 АС, 1 Мая | AS6: ДП60-3 НОВОТЕЛ, Осовецкий | AT6: ПКР-2, Красный боец, ТЕНДЕР | AU6: П60-3, Красный боец, ТЕНДЕР | AV6: ДП60-3 сухостой, Красный боец, ТЕНДЕР | AW6: ПКР-2, Гаховик-Сипаково, БИРЖА | AX6: ДП60-3 дойное, Восх.заря | AY6: ДПКР-2, Калф, Восх.заря | AZ6: ДП60-3 НОВОТЕЛ, Восх.заря | BA6: ДПКР-2 Хайфер, Восх.заря | BB6: ДП60-3 1й сух, Восх. Заря | BC6: ДП60-3 дойное, в к/к Сестричество | BD6: ДПКР-1 Мумуша в к/к Сестричество | BE6: ДП60-3 ТРАНЗИТ, в к/к Сестричество | BF6: ДП60-3 АС, Путь новый | BG6: ДП60-3, Биохром, ФХ Юлиан | BH6: ДП60-3 Антистресс в КК | BI6: ДП60-3 1й сух, Шапчицы | BJ6: ДП60-3 НОВОТЕЛ, КАЗАХСТАН | BK6: ДП60-3 НОВОТЕЛ, КАЗАХСТАН | BL6: ДП60-3 АС, 1 Мая | BM6: ДП60-3 1й сух, 1 Мая | BN6: ДП60-3, 1%, Малюшичи | BO6: ДП60-3 НОВОТЕЛ, АгроСолы | BP6: ДП60-3 НОВОТЕЛ, КАЗАХСТАН | BQ6: ДП60-3 дойное Осовецкий | BR6: ДПКР-1 Мумуша в к/к КАЗАХСТАН | BS6: ПКР-2, КАЗАХСТАН | BT6: ДП60-3 Антистресс 1 Мая | BU6: ДП60-3 НОВОТЕЛ, Красноармейская ПФ | BV6: ДП60-3 2й сух, Припять-2009, БИРЖА | BW6: ДП60-3 дойное, Бакуново | BX6: ДП60-3 2й сух, Свитязянка | BY6: ДП60-3 НОВОТЕЛ, Савушкино | BZ6: ДП60-3 1й сух, Савушкино | CC6: ДП60-3 дойное, ФХ Юлиан | CD6: ДП60-3 Биохром, 1% | CE6: ДП60-3 НОВОТЕЛ, Бакуново | CF6: ДП60-3 дойное, Киселевцы | CG6: ДП60-3 дойное, с-з Минский | CH6: ДП60-3 1й сух, Шапчицы | CI6: ДПКР-2 Хайфер, ФХ Юлиан | CJ6: ДП60-3 1й сух ФХ Юлиан | CK6: ДП60-3 дойное, Агро-Солы | CL6: ДП60-3 2й сух, Киселевцы | CM6: ДП60-3 дойное Мумуша, Лебедева Ветка, БИРЖА | CN6: ДПКР-1 Мумуша в к/к Восх.заря, ФХ Юлиан | CO6: ДП60-3 НОВОТЕЛ, Савушкина пуща | CP6: ДП60-3 1й сух, 1 Мая | CQ6: ДП60-3 1й сух, Савушкина пуща | CR6: ДП60-3 АС, 1 мая | CS6: ДП60-3 дойное Мумуша, Дубрава-Агро, БИРЖА | CT6: ДП60-3 НОВОТЕЛ, АгроСолы | CU6: ДПКР-2 Хайфер, Восх.заря | CV6: ДП60-3 пп про Дойное, Восх.заря | CW6: ДПКР-2, Калф, Восх.заря | CX6: ДП60-3 Антистресс, 1 мая | CY6: ДП60-3 пп про 1й сух, Покровский | CZ6: ДП60-3 пп про 1й сух, Восх. Заря | DA6: ДП60-3 пп про 2й сух, Восх. Заря | DB6: ДП60-3 Дойное 1 мая | DC6: ДП60-3 про-s Новотел, Восх.заря | DD6: ДП60-3 дойное, Савушкина Пуща | DE6: ДП60-3 дойное, Савушкина Пуща | DF6: ДП60-3 транзит, Видомлянское | DG6: ДП60-3 дойное Осовецкий | DH6: ДП60-3 2й сух, Мум, Припять-2009, биржа | DI6: ДП60-3 Биохром, ФХ Юлиан | DJ6: ДП60-3 дойное, Макарово-Агро (ДейриБаланс) | DK6: ДП60-3 НОВОТЕЛ, Савушкина пуща | DL6: ДП60-3 АС, Малюшичи | DM6: ДП60-3 НОВОТЕЛ, Савушкино | DN6: ДП60-3 Антистресс, 1 Мая | DO6: ДП60-3 АС, 1 мая | DP6: ДП60-3 2й сух, Савушкино | DQ6: ДП60-3 дойное, Киселевцы | DR6: ДП60-3 2й сух, Киселевцы | DS6: ДП60-3 АС, Киселевцы | DT6: ДП60-3 дойное, Савушкина Пуща | DW6: ДП60-3 дойное, ФХ Юлиан | DX6: ДП60-3 1й сух ФХ Юлиан | DY6: ДП60-3 2й сух, Утес | DZ6: ДП60-3 1й сух Шапчицы | EA6: ДП60-3 дойное, АгроСолы, БИРЖА | EB6: ДП60-3 Антистресс, Осовецкий | EC6: ДП60-3 1й сух, Савушкино | ED6: ДП60-3 Антистресс, 1 мая | EE6: ДП60-3 , Малюшичи | GD6: ДП60-3 2й сух ФХ Юлиан | GE6: ДП60-3 НОВОТЕЛ ФХ Юлиан | GF6: ДП60-3 дойное, 1 мая | GG6: ДП60-3 1й сух, 1 мая | GH6: ДП60-3 дойное, Бакуново | GN6: Отгрузка | GU6: годность
B7: дата выработки/планирования | D7: 2026 | H7: 46174 | I7: 46181 | K7: 46113 | L7: 46113 | M7: 46114 | N7: 46114 | O7: 46115 | P7: 46115 | Q7: 46115 | R7: 46118 | S7: 46118 | T7: 46119 | U7: 46119 | V7: 46119 | W7: 46119 | X7: 46120 | Y7: 46120 | Z7: 46120 | AA7: 46120 | AB7: 46120 | AC7: 46120 | AD7: 46121 | AE7: 46121 | AF7: 46121 | AG7: 46121 | AH7: 46121 | AI7: 46122 | AJ7: 46125 | AK7: 46126 | AL7: 46126 | AM7: 46126 | AN7: 46126 | AO7: 46126 | AP7: 46126 | AQ7: 46127 | AR7: 46127 | AS7: 46127 | AT7: 46127 | AU7: 46128 | AV7: 46128 | AW7: 46128 | AX7: 46134 | AY7: 46134 | AZ7: 46134 | BA7: 46134 | BB7: 46134 | BC7: 46134 | BD7: 46135 | BE7: 46135 | BF7: 46135 | BG7: 46135 | BH7: 46135 | BI7: 46135 | BJ7: 46136 | BK7: 46137 | BL7: 46137 | BM7: 46137 | BN7: 46137 | BO7: 46137 | BP7: 46139 | BQ7: 46139 | BR7: 46140 | BS7: 46140 | BT7: 46141 | BU7: 46141 | BV7: 46141 | BW7: 46141 | BX7: 46141 | BY7: 46142 | BZ7: 46142 | CA7: =J5 -> апрель | CC7: 46146 | CD7: 46146 | CE7: 46146 | CF7: 46147 | CG7: 46147 | CH7: 46148 | CI7: 46148 | CJ7: 46148 | CK7: 46148 | CL7: 46149 | CM7: 46149 | CN7: 46150 | CO7: 46154 | CP7: 46154 | CQ7: 46155 | CR7: 46156 | CS7: 46156 | CT7: 46157 | CU7: 46157 | CV7: 46160 | CW7: 46160 | CX7: 46160 | CY7: 46160 | CZ7: 46161 | DA7: 46161 | DB7: 46161 | DC7: 46163 | DD7: 46163 | DE7: 46164 | DF7: 46164 | DG7: 46164 | DH7: 46164 | DI7: 46164 | DJ7: 46168 | DK7: 46168 | DL7: 46169 | DM7: 46169 | DN7: 46170 | DO7: 46170 | DP7: 46170 | DQ7: 46170 | DR7: 46170 | DS7: 46170 | DT7: 46171 | DU7: =CB5 -> май | DW7: 46174 | DX7: 46174 | DY7: 46175 | DZ7: 46175 | EA7: 46176 | EB7: 46178 | EC7: 46178 | ED7: 46181 | EE7: 46181 | GA7: =DV5 -> июнь | GD7: 46182 | GE7: 46182 | GF7: 46182 | GG7: 46183 | GH7: 46183 | GQ7: =I7 -> 46181
B8: Выработка, т | D8: =CA8 -> 136.7 | E8: =DU8 -> 99.6 | F8: =GA8 -> 19.5 | K8: =1*3 -> 3 | L8: 0.6 | M8: =1*5 -> 5 | N8: =1*5 -> 5 | O8: =1*2.7 -> 2.7 | P8: =1*2.4 -> 2.4 | Q8: =1*0.6 -> 0.6 | R8: 2 | S8: =1*7.5 -> 7.5 | T8: =1*3.5 -> 3.5 | U8: =1*0.6 -> 0.6 | V8: =1*1.6 -> 1.6 | W8: =1*0.6 -> 0.6 | X8: =1*3 -> 3 | Y8: =1 -> 1 | Z8: 0.6 | AA8: =1*0.9 -> 0.9 | AB8: =1*3 -> 3 | AC8: =1*2 -> 2 | AD8: =1*5 -> 5 | AE8: =1*1.3 -> 1.3 | AF8: =1*0.6 -> 0.6 | AG8: 0.9 | AH8: =1*2 -> 2 | AI8: =1*8 -> 8 | AJ8: =1*1.4 -> 1.4 | AK8: 0.3 | AL8: 0.1 | AM8: =1*3 -> 3 | AN8: 1 | AO8: 1 | AP8: =1*0.3 -> 0.3 | AQ8: 0.6 | AR8: 0.6 | AS8: 0.4 | AT8: =1*3.6 -> 3.6 | AU8: =1*9 -> 9 | AV8: =1*2.3 -> 2.3 | AW8: 2 | AX8: =1*5 -> 5 | AY8: =1 -> 1 | AZ8: 3 | BA8: =1 -> 1 | BB8: =1*1.5 -> 1.5 | BC8: =1.2/1.2*0.3 -> 0.3 | BD8: =0.3/0.3*0.1 -> 0.1 | BE8: 0.1 | BF8: =0.6/0.6*0.7 -> 0.7 | BG8: 0.1 | BH8: =1*0.6 -> 0.6 | BI8: 1 | BJ8: =8/8*1.8 -> 1.8 | BK8: =8/8*1.5 -> 1.5 | BL8: 0.6 | BM8: =1*0.6 -> 0.6 | BN8: =1*0.6 -> 0.6 | BO8: =1*5 -> 5 | BP8: =8/8*4.7 -> 4.7 | BQ8: 3 | BR8: =0.9/0.9*0.8 -> 0.8 | BS8: 4 | BT8: =1*1.2 -> 1.2 | BU8: =1*0.4 -> 0.4 | BV8: 0.6 | BW8: =1*3 -> 3 | BX8: 1.2 | BY8: =1*3.8 -> 3.8 | BZ8: =1*0.5 -> 0.5 | CA8: =SUM(K8:BZ8) -> 136.7 | CC8: =1*2.4 -> 2.4 | CD8: 0.1 | CE8: =1*0.6 -> 0.6 | CF8: =1*1.8 -> 1.8 | CG8: =1*1.3 -> 1.3 | CH8: 1 | CI8: =1*0.9 -> 0.9 | CJ8: =1*1.3 -> 1.3 | CK8: =1*5 -> 5 | CL8: =0.3/0.3*0.2 -> 0.2 | CM8: =1*5 -> 5 | CN8: 3 | CO8: =1*6 -> 6 | CP8: =1.2/1.2*0.6 -> 0.6 | CQ8: 2 | CR8: 0.6 | CS8: 5 | CT8: =1*5 -> 5 | CU8: 1.5 | CV8: 4 | CW8: =1 -> 1 | CX8: 1.2 | CY8: 0.5 | CZ8: =1*1.5 -> 1.5 | DA8: 1 | DB8: 3 | DC8: 3.5 | DD8: 7 | DE8: 3 | DF8: 1.5 | DG8: 3 | DH8: 0.3 | DI8: 0.3 | DJ8: 1 | DK8: =1*5 -> 5 | DL8: 1 | DM8: =1*7 -> 7 | DN8: =1*1.5 -> 1.5 | DO8: =1*1.2 -> 1.2 | DP8: =1*1.5 -> 1.5 | DQ8: =1*1.7 -> 1.7 | DR8: =1*0.3 -> 0.3 | DS8: =1*0.3 -> 0.3 | DT8: =1*5 -> 5 | DU8: =SUM(CC8:DT8) -> 99.6 | DW8: =1*2.4 -> 2.4 | DX8: =1*1.3 -> 1.3 | DY8: =1*1.5 -> 1.5 | DZ8: 1 | EA8: =1*5 -> 5 | EB8: =1*3 -> 3 | EC8: =1*2 -> 2 | ED8: =1*1.5 -> 1.5 | EE8: =1*1.8 -> 1.8 | GA8: =SUM(DW8:FZ8) -> 19.5 | GD8: =1*0.9 -> 0.9 | GE8: =1*0.9 -> 0.9 | GF8: =1*3 -> 3 | GG8: =1*1.2 -> 1.2 | GH8: =1*3 -> 3 | GO8: =SUM(GC8:GN8) -> 9
A9: 1 | B9: вит А 1000 | C9: ='1_квартал'!G9 -> 70.447 | D9: =18.069+72.082 -> 90.151 | E9: =2.918+47.806 -> 50.724 | G9: =ROUND(AVERAGE(D9:F9),3) -> 70.438 | H9: 77.194 | I9: 64.364 | K9: =0.675*3 -> 2.025 | L9: 0.302 | N9: =0.171*5 -> 0.855 | O9: =0.181*2.7 -> 0.4887 | P9: =0.675*2.4 -> 1.62 | Q9: =0.181*0.6 -> 0.1086 | S9: =0.181*7.5 -> 1.3575 | T9: =0.181*3.5 -> 0.6335 | U9: =0.66*0.6 -> 0.396 | V9: =0.675*1.6 -> 1.08 | W9: =0.181*0.6 -> 0.1086 | X9: =0.181*3 -> 0.543 | Y9: =0.66 -> 0.66 | Z9: 0.109 | AA9: =0.534*0.9 -> 0.4806 | AB9: =0.181*3 -> 0.543 | AC9: =0.675*2 -> 1.35 | AD9: =0.504*5 -> 2.52 | AE9: =0.66*1.3 -> 0.858 | AF9: =0.66*0.6 -> 0.396 | AG9: =0.163 -> 0.163 | AH9: =0.842*2 -> 1.684 | AI9: =0.842*8 -> 6.736 | AJ9: =0.675*1.4 -> 0.945 | AL9: 0.01 | AM9: =0.675*3 -> 2.025 | AN9: 2.621 | AO9: 0.181 | AQ9: 0.105 | AR9: 0.121 | AS9: 0.07 | AT9: =1.512*3.6 -> 5.4432 | AU9: =2.621*9 -> 23.589 | AV9: =0.731*2.3 -> 1.6813 | AW9: 3.024 | AX9: =1.008*5 -> 5.04 | AY9: =0.302 -> 0.302 | AZ9: 0.544 | BA9: =0.534 -> 0.534 | BB9: =0.66*1.5 -> 0.99 | BC9: =0.726/1.2*0.3 -> 0.1815 | BD9: =0.091/0.3*0.1 -> 0.030333333 | BE9: 0.06 | BF9: =0.121/0.6*0.7 -> 0.14116667 | BG9: 0.001 | BI9: 0.66 | BJ9: =1.613/8*1.8 -> 0.362925 | BK9: =1.613/8*1.5 -> 0.3024375 | BL9: 0.121 | BM9: =0.66*0.6 -> 0.396 | BN9: =2.621*0.6 -> 1.5726 | BP9: =1.613/8*4.7 -> 0.9476375 | BQ9: 3.024 | BR9: =0.227/0.9*0.8 -> 0.20177778 | BS9: =1.512*4 -> 6.048 | BU9: =0.605*0.4 -> 0.242 | BV9: 0.345 | BW9: =0.675*3 -> 2.025 | BX9: 0.242 | BY9: =0.181*3.8 -> 0.6878 | BZ9: =0.66*0.5 -> 0.33 | CA9: =SUM(K9:BZ9) -> 90.165178 | CC9: =0.675*2.4 -> 1.62 | CD9: 0.001 | CE9: =0.181*0.6 -> 0.1086 | CF9: =0.675*1.8 -> 1.215 | CG9: =0.675*1.3 -> 0.8775 | CH9: 0.66 | CI9: =0.534*0.9 -> 0.4806 | CJ9: =0.66*1.3 -> 0.858 | CK9: =0.675*5 -> 3.375 | CL9: =0.198/0.3*0.2 -> 0.132 | CM9: =0.675*5 -> 3.375 | CN9: 0.756 | CO9: =0.181*6 -> 1.086 | CP9: =0.792/1.2*0.6 -> 0.396 | CQ9: =0.66*2 -> 1.32 | CR9: 0.121 | CS9: =0.171*5 -> 0.855 | CU9: =0.534/1*1.5 -> 0.801 | CV9: =1.008*4 -> 4.032 | CW9: =0.302 -> 0.302 | CY9: =0.99/1.5*0.5 -> 0.33 | CZ9: =0.66*1.5 -> 0.99 | DA9: =0.353*2 -> 0.706 | DB9: 3.629 | DC9: =0.544/3*3.5 -> 0.63466667 | DD9: =0.68*7 -> 4.76 | DE9: =0.68*3 -> 2.04 | DF9: =1.31*1.5 -> 1.965 | DG9: 3.024 | DH9: 0.172 | DI9: 0.003 | DK9: =0.181*5 -> 0.905 | DL9: 2.621 | DM9: =0.181*7 -> 1.267 | DO9: =0.202*1.2 -> 0.2424 | DP9: =0.181*1.5 -> 0.2715 | DQ9: =0.675*1.7 -> 1.1475 | DR9: =0.66*0.3 -> 0.198 | DT9: =0.68*5 -> 3.4 | DU9: =SUM(CC9:DT9) -> 50.677767 | DW9: =0.675*2.4 -> 1.62 | DX9: =0.66*1.3 -> 0.858 | DY9: =0.181*1.5 -> 0.2715 | DZ9: 0.66 | EA9: =0.675*5 -> 3.375 | EC9: =0.66*2 -> 1.32 | EE9: =2.621*1.8 -> 4.7178 | GA9: =SUM(DW9:FZ9) -> 12.8223 | GD9: =0.181*0.9 -> 0.1629 | GE9: =0.181*0.9 -> 0.1629 | GF9: =1.21*3 -> 3.63 | GG9: =0.66*1.2 -> 0.792 | GH9: =0.675*3 -> 2.025 | GO9: =SUM(GC9:GN9) -> 6.7728 | GP9: =I9-GO9 -> 57.5912 | GQ9: =I9 -> 64.364 | GR9: =C9 -> 70.447 | GS9: =E9 -> 50.724 | GT9: =B9 -> вит А 1000
A10: =A9+1 -> 2 | B10: вит Д3 500 | C10: ='1_квартал'!G10 -> 32.712 | D10: =0.845+41.565 -> 42.41 | E10: =29.144 -> 29.144 | G10: =ROUND(AVERAGE(D10:F10),3) -> 35.777 | H10: 25.091 | I10: 19.401 | K10: =0.413*3 -> 1.239 | L10: 0.153 | N10: =0.081*5 -> 0.405 | O10: =0.097*2.7 -> 0.2619 | P10: =0.413*2.4 -> 0.9912 | Q10: =0.097*0.6 -> 0.0582 | S10: =0.101*7.5 -> 0.7575 | T10: =0.101*3.5 -> 0.3535 | U10: =0.323*0.6 -> 0.1938 | V10: =0.413*1.6 -> 0.6608 | W10: =0.101*0.6 -> 0.0606 | X10: =0.101*3 -> 0.303 | Y10: =0.323 -> 0.323 | Z10: 0.058 | AA10: =0.202*0.9 -> 0.1818 | AB10: =0.101*3 -> 0.303 | AC10: =0.413*2 -> 0.826 | AD10: =0.135*5 -> 0.675 | AE10: =0.31*1.3 -> 0.403 | AF10: =0.323*0.6 -> 0.1938 | AG10: 0.091 | AH10: =0.423*2 -> 0.846 | AI10: =0.423*8 -> 3.384 | AJ10: =0.413*1.4 -> 0.5782 | AK10: 0.024 | AL10: 0.005 | AM10: =0.413*3 -> 1.239 | AN10: 0.605 | AO10: 0.101 | AQ10: 0.024 | AR10: 0.06 | AS10: 0.016 | AT10: =0.766*3.6 -> 2.7576 | AU10: =0.605*9 -> 5.445 | AV10: =0.605*2.3 -> 1.3915 | AW10: 1.532 | AX10: =0.413*5 -> 2.065 | AY10: =0.171 -> 0.171 | AZ10: 0.302 | BA10: =0.202 -> 0.202 | BB10: =0.323*1.5 -> 0.4845 | BC10: =(0.099+0.045)/1.2*0.3 -> 0.036 | BD10: =0.018/0.3*0.1 -> 0.006 | BE10: 0.02 | BF10: =0.06/0.6*0.7 -> 0.07 | BG10: 0.001 | BI10: 0.323 | BJ10: =0.435/8*1.8 -> 0.097875 | BK10: =0.435/8*1.5 -> 0.0815625 | BL10: 0.06 | BM10: =0.323*0.6 -> 0.1938 | BN10: =0.605*0.6 -> 0.363 | BP10: =0.435/8*4.7 -> 0.2555625 | BQ10: 6.048 | BR10: =0.054/0.9*0.8 -> 0.048 | BS10: =0.766*4 -> 3.064 | BV10: 0.169 | BW10: =0.413*3 -> 1.239 | BX10: =0.085+0.034 -> 0.119 | BY10: =0.101*3.8 -> 0.3838 | BZ10: =0.323*0.5 -> 0.1615 | CA10: =SUM(K10:BZ10) -> 42.465 | CC10: =0.413*2.4 -> 0.9912 | CD10: 0.001 | CE10: =0.101*0.6 -> 0.0606 | CF10: =0.413*1.8 -> 0.7434 | CG10: =0.413*1.3 -> 0.5369 | CH10: 0.323 | CI10: =0.202*0.9 -> 0.1818 | CJ10: =0.323*1.3 -> 0.4199 | CK10: =0.413*5 -> 2.065 | CL10: =0.097/0.3*0.2 -> 0.064666667 | CM10: =0.413*5 -> 2.065 | CN10: 0.181 | CO10: =0.101*6 -> 0.606 | CP10: =0.387/1.2*0.6 -> 0.1935 | CQ10: =0.323*2 -> 0.646 | CR10: 0.06 | CS10: =0.081*5 -> 0.405 | CU10: =0.202/1*1.5 -> 0.303 | CV10: =0.413*4 -> 1.652 | CW10: =0.171 -> 0.171 | CY10: =0.484/1.5*0.5 -> 0.16133333 | CZ10: =0.323*1.5 -> 0.4845 | DA10: 0.323 | DB10: 1.512 | DC10: =0.302/3*3.5 -> 0.35233333 | DD10: =0.348*7 -> 2.436 | DE10: =0.348*3 -> 1.044 | DF10: =0.302*1.5 -> 0.453 | DG10: 6.048 | DH10: 0.085 | DI10: 0.003 | DK10: =0.101*5 -> 0.505 | DL10: 0.605 | DM10: =0.101*7 -> 0.707 | DO10: =0.101*1.2 -> 0.1212 | DP10: =0.101*1.5 -> 0.1515 | DQ10: =0.413*1.7 -> 0.7021 | DR10: =0.323*0.3 -> 0.0969 | DT10: =0.348*5 -> 1.74 | DU10: =SUM(CC10:DT10) -> 29.200833 | DW10: =0.413*2.4 -> 0.9912 | DX10: =0.323*1.3 -> 0.4199 | DY10: =0.101*1.5 -> 0.1515 | DZ10: 0.323 | EA10: =0.413*5 -> 2.065 | EC10: =0.323*2 -> 0.646 | EE10: =0.605*1.8 -> 1.089 | GA10: =SUM(DW10:FZ10) -> 5.6856 | GD10: =0.101*0.9 -> 0.0909 | GE10: =0.101*0.9 -> 0.0909 | GF10: =0.504*3 -> 1.512 | GG10: =0.323*1.2 -> 0.3876 | GH10: =0.413*3 -> 1.239 | GO10: =SUM(GC10:GN10) -> 3.3204 | GP10: =I10-GO10 -> 16.0806 | GQ10: =I10 -> 19.401 | GR10: =C10 -> 32.712 | GS10: =E10 -> 29.144 | GT10: =B10 -> вит Д3 500
A11: =A10+1 -> 3 | B11: вит Е 50% | C11: ='1_квартал'!G11 -> 951.46 | D11: =370.44+460.86 -> 831.3 | E11: =87.31+631.63 -> 718.94 | G11: =ROUND(AVERAGE(D11:F11),3) -> 775.12 | H11: 907.51 | I11: 724.39 | K11: =8.795*3 -> 26.385 | L11: 0.395 | M11: =2.965*5 -> 14.825 | N11: =2.866*5 -> 14.33 | O11: =2.372*2.7 -> 6.4044 | P11: =8.795*2.4 -> 21.108 | Q11: =9.289*0.6 -> 5.5734 | S11: =2.372*7.5 -> 17.79 | T11: =9.289*3.5 -> 32.5115 | U11: =23.52*0.6 -> 14.112 | V11: =8.795*1.6 -> 14.072 | W11: =2.372*0.6 -> 1.4232 | X11: =9.289*3 -> 27.867 | Y11: =23.52 -> 23.52 | Z11: 1.423 | AA11: =9.882*0.9 -> 8.8938 | AB11: =2.372*3 -> 7.116 | AC11: =8.795*2 -> 17.59 | AD11: =4.032*5 -> 20.16 | AE11: =18.776*1.3 -> 24.4088 | AF11: =19.152*0.6 -> 11.4912 | AG11: 8.528 | AH11: =12.096*2 -> 24.192 | AI11: =12.096*8 -> 96.768 | AJ11: =8.971*1.4 -> 12.5594 | AK11: 2.298 | AL11: 0.484 | AM11: =8.971*3 -> 26.913 | AN11: 3.024 | AO11: 9.475 | AP11: =3.024*0.3 -> 0.9072 | AQ11: 0.242 | AR11: 5.443 | AS11: 0.081 | AT11: =1.976*3.6 -> 7.1136 | AU11: =2.965*9 -> 26.685 | AV11: =15.713*2.3 -> 36.1399 | AW11: 4.032 | AX11: =8.971*5 -> 44.855 | AY11: =8.064 -> 8.064 | AZ11: 7.258 | BA11: 10.08 | BB11: =19.152*1.5 -> 28.728 | BC11: =4.355/1.2*0.3 -> 1.08875 | BD11: =0.423/0.3*0.1 -> 0.141 | BE11: 0.363 | BF11: =5.443/0.6*0.7 -> 6.3501667 | BG11: 0.02 | BI11: 19.152 | BJ11: =16.128/8*1.8 -> 3.6288 | BK11: =16.128/8*1.5 -> 3.024 | BL11: 5.443 | BM11: =19.152*0.6 -> 11.4912 | BN11: =4.032*0.6 -> 2.4192 | BO11: =2.419*5 -> 12.095 | BP11: =16.128/8*4.7 -> 9.4752 | BR11: =4.81/0.9*0.8 -> 4.2755556 | BS11: =2.016*4 -> 8.064 | BU11: =10.08*0.4 -> 4.032 | BV11: 6.29 | BW11: =8.971*3 -> 26.913 | BX11: 11.032 | BY11: =2.372*3.8 -> 9.0136 | BZ11: =23.52*0.5 -> 11.76 | CA11: =SUM(K11:BZ11) -> 831.34087 | CC11: =8.795*2.4 -> 21.108 | CD11: 0.02 | CE11: =2.372*0.6 -> 1.4232 | CF11: =8.971*1.8 -> 16.1478 | CG11: =8.971*1.3 -> 11.6623 | CH11: 19.152 | CI11: =9.882*0.9 -> 8.8938 | CJ11: =19.152*1.3 -> 24.8976 | CK11: =8.795*5 -> 43.975 | CL11: =5.746/0.3*0.2 -> 3.8306667 | CM11: =8.971*5 -> 44.855 | CN11: 16.033 | CO11: =2.419*6 -> 14.514 | CP11: =22.982/1.2*0.6 -> 11.491 | CQ11: =23.99*2 -> 47.98 | CR11: =5.443 -> 5.443 | CS11: =2.923*5 -> 14.615 | CT11: =2.419*5 -> 12.095 | CU11: =2.96+11.92 -> 14.88 | CV11: =8.971*4 -> 35.884 | CW11: =8.064 -> 8.064 | CY11: =28.728/1.5*0.5 -> 9.576 | CZ11: =19.152*1.5 -> 28.728 | DA11: 19.152 | DB11: 54.432 | DC11: =7.258/3*3.5 -> 8.4676667 | DD11: =9.072*7 -> 63.504 | DE11: =9.072*3 -> 27.216 | DF11: =1.512*1.5 -> 2.268 | DH11: 3.145 | DI11: 0.06 | DK11: =2.419*5 -> 12.095 | DL11: 4.032 | DM11: =2.419*7 -> 16.933 | DO11: =9.072*1.2 -> 10.8864 | DP11: =9.475*1.5 -> 14.2125 | DQ11: =8.971*1.7 -> 15.2507 | DR11: =19.152*0.3 -> 5.7456 | DS11: =3.024*0.3 -> 0.9072 | DT11: =9.072*5 -> 45.36 | DU11: =SUM(CC11:DT11) -> 718.93543 | DW11: =8.971*2.4 -> 21.5304 | DX11: =19.152*1.3 -> 24.8976 | DY11: =9.475*1.5 -> 14.2125 | DZ11: 19.152 | EA11: =8.971*5 -> 44.855 | EB11: =1.075*3 -> 3.225 | EC11: =23.99*2 -> 47.98 | EE11: =4.032*1.8 -> 7.2576 | GA11: =SUM(DW11:FZ11) -> 183.1101 | GD11: =9.475*0.9 -> 8.5275 | GE11: =2.419*0.9 -> 2.1771 | GF11: =18.144*3 -> 54.432 | GG11: =19.152*1.2 -> 22.9824 | GH11: =8.971*3 -> 26.913 | GO11: =SUM(GC11:GN11) -> 115.032 | GP11: =I11-GO11 -> 609.358 | GQ11: =I11 -> 724.39 | GR11: =C11 -> 951.46 | GS11: =E11 -> 718.94 | GT11: =B11 -> вит Е 50%
A12: =A11+1 -> 4 | B12: вит В1 (тиамин) | C12: ='1_квартал'!G12 -> 0 | D12: 0 | E12: 0 | G12: =ROUND(AVERAGE(D12:F12),3) -> 0 | H12: 0 | I12: 0 | CA12: =SUM(K12:BZ12) -> 0 | DU12: =SUM(CC12:DT12) -> 0 | GA12: =SUM(DW12:FZ12) -> 0 | GO12: =SUM(GC12:GN12) -> 0 | GP12: =I12-GO12 -> 0 | GQ12: =I12 -> 0 | GR12: =C12 -> 0 | GS12: =E12 -> 0 | GT12: =B12 -> вит В1 (тиамин)
A13: =A12+1 -> 5 | B13: вит В2 | C13: ='1_квартал'!G13 -> 0.43 | D13: 0 | E13: 0 | G13: =ROUND(AVERAGE(D13:F13),3) -> 0 | H13: 0 | I13: 0 | CA13: =SUM(K13:BZ13) -> 0 | DU13: =SUM(CC13:DT13) -> 0 | GA13: =SUM(DW13:FZ13) -> 0 | GO13: =SUM(GC13:GN13) -> 0 | GP13: =I13-GO13 -> 0 | GQ13: =I13 -> 0 | GR13: =C13 -> 0.43 | GS13: =E13 -> 0 | GT13: =B13 -> вит В2
A14: =A13+1 -> 6 | B14: вит В3, Нутравит В5 (кальпан) | C14: ='1_квартал'!G14 -> 0.083 | D14: 4.83 | E14: 2.42 | G14: =ROUND(AVERAGE(D14:F14),3) -> 3.625 | H14: 6.87 | I14: 6.87 | S14: =0.103*7.5 -> 0.7725 | T14: =0.103*3.5 -> 0.3605 | U14: =0.103*0.6 -> 0.0618 | W14: =0.103*0.6 -> 0.0618 | X14: =0.103*3 -> 0.309 | Y14: =0.103 -> 0.103 | AB14: =0.103*3 -> 0.309 | AD14: =0.103*5 -> 0.515 | AH14: =0.103*2 -> 0.206 | AI14: =0.103*8 -> 0.824 | AM14: =0.103*3 -> 0.309 | AO14: 0.103 | BD14: =0.062/0.3*0.1 -> 0.020666667 | BI14: 0.103 | BR14: =0.046/0.9*0.8 -> 0.040888889 | BW14: =0.103*3 -> 0.309 | BY14: =0.103*3.8 -> 0.3914 | BZ14: =0.103*0.5 -> 0.0515 | CA14: =SUM(K14:BZ14) -> 4.8510556 | CE14: =0.103*0.6 -> 0.0618 | CG14: =0.103*1.3 -> 0.1339 | CH14: 0.103 | CJ14: =0.103*1.3 -> 0.1339 | CM14: =0.103*5 -> 0.515 | CN14: 0.154 | CO14: =0.103*6 -> 0.618 | CQ14: =0.103*2 -> 0.206 | DK14: =0.103*5 -> 0.515 | DU14: =SUM(CC14:DT14) -> 2.4406 | GA14: =SUM(DW14:FZ14) -> 0 | GO14: =SUM(GC14:GN14) -> 0 | GP14: =I14-GO14 -> 6.87 | GQ14: =I14 -> 6.87 | GR14: =C14 -> 0.083 | GS14: =E14 -> 2.42 | GT14: =B14 -> вит В3, Нутравит В5 (кальпан) | GU14: 46455
A15: =A14+1 -> 7 | B15: вит В5 (ниацин) | C15: ='1_квартал'!G15 -> 0.247 | D15: 0.13 | E15: 1.59 | G15: =ROUND(AVERAGE(D15:F15),3) -> 0.86 | H15: 17.747 | I15: 16.507 | BD15: =0.031/0.3*0.1 -> 0.010333333 | BR15: =0.137/0.9*0.8 -> 0.12177778 | CA15: =SUM(K15:BZ15) -> 0.13211111 | CN15: 0.458 | CX15: =0.102*1.2 -> 0.1224 | DM15: =0.102*7 -> 0.714 | DN15: =0.102*1.5 -> 0.153 | DP15: =0.102*1.5 -> 0.153 | DU15: =SUM(CC15:DT15) -> 1.6004 | DX15: =0.102*1.3 -> 0.1326 | DY15: =0.102*1.5 -> 0.153 | DZ15: 0.102 | EA15: =0.102*5 -> 0.51 | EC15: =0.102*2 -> 0.204 | ED15: =0.102*1.5 -> 0.153 | GA15: =SUM(DW15:FZ15) -> 1.2546 | GH15: =0.102*3 -> 0.306 | GO15: =SUM(GC15:GN15) -> 0.306 | GP15: =I15-GO15 -> 16.201 | GQ15: =I15 -> 16.507 | GR15: =C15 -> 0.247 | GS15: =E15 -> 1.59 | GT15: =B15 -> вит В5 (ниацин) | GU15: 46890
A16: =A15+1 -> 8 | B16: вит В6 (пиридоксин) | C16: ='1_квартал'!G16 -> 0.221 | D16: 1.54 | E16: 1.05 | G16: =ROUND(AVERAGE(D16:F16),3) -> 1.295 | H16: 11.377 | I16: 11.377 | K16: =0.102*3 -> 0.306 | N16: =0.102*5 -> 0.51 | AC16: =0.102*2 -> 0.204 | AD16: =0.102*5 -> 0.51 | BR16: =0.009/0.9*0.8 -> 0.008 | CA16: =SUM(K16:BZ16) -> 1.538 | CK16: =0.102*5 -> 0.51 | CN16: 0.031 | CS16: =0.102*5 -> 0.51 | DU16: =SUM(CC16:DT16) -> 1.051 | GA16: =SUM(DW16:FZ16) -> 0 | GO16: =SUM(GC16:GN16) -> 0 | GP16: =I16-GO16 -> 11.377 | GQ16: =I16 -> 11.377 | GR16: =C16 -> 0.221 | GS16: =E16 -> 1.05 | GT16: =B16 -> вит В6 (пиридоксин) | GU16: 46941
A17: =A16+1 -> 9 | B17: вит Н (биотин) | C17: ='1_квартал'!G17 -> 218.507 | D17: =129.78 -> 129.78 | E17: =4.23+149.19 -> 153.42 | G17: =ROUND(AVERAGE(D17:F17),3) -> 141.6 | H17: =6.36+350.81 -> 357.17 | I17: =3.34+350.81 -> 354.15 | O17: =2.016*2.7 -> 5.4432 | Q17: =2.016*0.6 -> 1.2096 | S17: =2.016*7.5 -> 15.12 | T17: =2.016*3.5 -> 7.056 | W17: =2.016*0.6 -> 1.2096 | X17: =2.016*3 -> 6.048 | Z17: 1.21 | AB17: =2.016*3 -> 6.048 | AG17: 1.814 | AH17: =5.796*2 -> 11.592 | AI17: =5.796*8 -> 46.368 | AK17: 1.21 | AO17: 2.016 | AQ17: 0.402 | AS17: 0.268 | AZ17: 6.048 | BC17: =3.81/1.2*0.3 -> 0.9525 | BE17: 0.318 | BJ17: =5.363/8*1.8 -> 1.206675 | BK17: =5.363/8*1.5 -> 1.0055625 | BP17: =5.363/8*4.7 -> 3.1507625 | BX17: 2.419 | BY17: =2.016*3.8 -> 7.6608 | CA17: =SUM(K17:BZ17) -> 129.7757 | CE17: =2.016*0.6 -> 1.2096 | CO17: =2.016*6 -> 12.096 | DB17: 30.24 | DC17: =6.048/3*3.5 -> 7.056 | DD17: =5.04*7 -> 35.28 | DE17: =5.04*3 -> 15.12 | DK17: =2.016*5 -> 10.08 | DM17: =2.016*7 -> 14.112 | DP17: =2.016*1.5 -> 3.024 | DT17: =5.04*5 -> 25.2 | DU17: =SUM(CC17:DT17) -> 153.4176 | DY17: =2.016*1.5 -> 3.024 | GA17: =SUM(DW17:FZ17) -> 3.024 | GD17: =2.016*0.9 -> 1.8144 | GE17: =2.016*0.9 -> 1.8144 | GF17: =10.08*3 -> 30.24 | GO17: =SUM(GC17:GN17) -> 33.8688 | GP17: =I17-GO17 -> 320.2812 | GQ17: =I17 -> 354.15 | GR17: =C17 -> 218.507 | GS17: =E17 -> 153.42 | GT17: =B17 -> вит Н (биотин)
D18: =SUM(D9:D17) -> 1100.141 | E18: =SUM(E9:E17) -> 957.288 | F18: =SUM(F9:F17) -> 0 | G18: =SUM(G9:G17) -> 1028.715 | H18: =SUM(H9:H17) -> 1402.959 | I18: =SUM(I9:I17) -> 1197.059
A19: =A17+1 -> 10 | B19: окись магния, порошок магнезитовый | C19: ='1_квартал'!G19 -> 12526.257 | D19: 11486.2 | E19: 9827.7 | G19: =ROUND(AVERAGE(D19:F19),3) -> 10656.95 | H19: 10136.12 | I19: =7169.28+20000 -> 27169.28 | K19: =159.472*3 -> 478.416 | L19: 0.55 | O19: =93.433*2.7 -> 252.2691 | P19: =159.472*2.4 -> 382.7328 | Q19: =93.348*0.6 -> 56.0088 | T19: =93.347*3.5 -> 326.7145 | U19: =208.212*0.6 -> 124.9272 | V19: =160.014*1.6 -> 256.0224 | W19: =93.433*0.6 -> 56.0598 | X19: =93.347*3 -> 280.041 | Y19: =208.212 -> 208.212 | Z19: 60.452 | AA19: =109.964*0.9 -> 98.9676 | AC19: =159.472*2 -> 318.944 | AD19: =121.391*5 -> 606.955 | AE19: =208.212*1.3 -> 270.6756 | AF19: =208.212*0.6 -> 124.9272 | AG19: 92.38 | AH19: =70.362*2 -> 140.724 | AI19: =70.362*8 -> 562.896 | AJ19: =160.014*1.4 -> 224.0196 | AM19: =160.014*3 -> 480.042 | AN19: 249.251 | AO19: 93.347 | AQ19: 1.466 | AS19: 0.977 | AT19: =2.749*3.6 -> 9.8964 | AU19: =36.655*9 -> 329.895 | AV19: =164.945*2.3 -> 379.3735 | AW19: 5.498 | AX19: =444.203*5 -> 2221.015 | AY19: =91.636 -> 91.636 | AZ19: 302.262 | BA19: =109.964 -> 109.964 | BB19: =208.212*1.5 -> 312.318 | BC19: =16.495/1.2*0.3 -> 4.12375 | BD19: =4.399/0.3*0.1 -> 1.4663333 | BE19: 1.375 | BH19: =403.2*0.6 -> 241.92 | BI19: 208.212 | BJ19: =98.234/8*1.8 -> 22.10265 | BK19: =98.234/8*1.5 -> 18.418875 | BM19: =208.212*0.6 -> 124.9272 | BN19: =36.655*0.6 -> 21.993 | BP19: =98.234/8*4.7 -> 57.712475 | BR19: =24.742/0.9*0.8 -> 21.992889 | BS19: =2.749*4 -> 10.996 | BT19: =403.2*1.2 -> 483.84 | BV19: 90.179 | BW19: =160.014*3 -> 480.042 | BX19: 82.922 | BZ19: =208.212*0.5 -> 104.106 | CA19: =SUM(K19:BZ19) -> 11486.165 | CC19: =159.472*2.4 -> 382.7328 | CE19: =93.433*0.6 -> 56.0598 | CF19: =160.014*1.8 -> 288.0252 | CG19: =160.014*1.3 -> 208.0182 | CH19: 208.212 | CI19: =109.964*0.9 -> 98.9676 | CJ19: =208.212*1.3 -> 270.6756 | CK19: =159.472*5 -> 797.36 | CL19: =62.464/0.3*0.2 -> 41.642667 | CM19: =160.014*5 -> 800.07 | CN19: 82.473 | CP19: =249.855/1.2*0.6 -> 124.9275 | CQ19: =208.212*2 -> 416.424 | CU19: =109.964*1.5 -> 164.946 | CV19: =444.203*4 -> 1776.812 | CW19: =91.636 -> 91.636 | CX19: =403.2*1.2 -> 483.84 | CY19: =312.319/1.5*0.5 -> 104.10633 | CZ19: =208.212*1.5 -> 312.318 | DA19: =104.11*2 -> 208.22 | DB19: =1209.6 -> 1209.6 | DC19: =302.262/3*3.5 -> 352.639 | DF19: =124.625*1.5 -> 186.9375 | DH19: 45.09 | DL19: 36.655 | DN19: =403.2*1.5 -> 604.8 | DP19: =93.347*1.5 -> 140.0205 | DQ19: =160.014*1.7 -> 272.0238 | DR19: =208.213*0.3 -> 62.4639 | DU19: =SUM(CC19:DT19) -> 9827.6964 | DW19: =159.472*2.4 -> 382.7328 | DX19: =208.212*1.3 -> 270.6756 | DY19: =93.347*1.5 -> 140.0205 | DZ19: 208.212 | EA19: =159.472*5 -> 797.36 | EB19: =26.88*3 -> 80.64 | EC19: =208.212*2 -> 416.424 | ED19: =403.2*1.5 -> 604.8 | EE19: =36.655*1.8 -> 65.979 | GA19: =SUM(DW19:FZ19) -> 2966.8439 | GD19: =102.644*0.9 -> 92.3796 | GE19: =100.754*0.9 -> 90.6786 | GF19: =403.2*3 -> 1209.6 | GG19: =208.212*1.2 -> 249.8544 | GH19: =160.014*3 -> 480.042 | GO19: =SUM(GC19:GN19) -> 2122.5546 | GP19: =I19-GO19 -> 25046.725 | GQ19: =I19 -> 27169.28 | GR19: =C19 -> 12526.257 | GS19: =E19 -> 9827.7 | GT19: =B19 -> окись магния, порошок магнезитовый
A20: =A19+1 -> 11 | B20: сульфат магния б/водный, магний с/кисл. | C20: ='1_квартал'!G20 -> 9027.017 | D20: =8795.96+665.67 -> 9461.63 | E20: 7540.5 | G20: =ROUND(AVERAGE(D20:F20),3) -> 8501.065 | H20: =4394.27+8000+2000 -> 14394.27 | I20: =2845.68+8000+2000 -> 12845.68 | K20: =100.724*3 -> 302.172 | M20: =178.004*5 -> 890.02 | N20: =201.6*5 -> 1008 | O20: =33.544*2.7 -> 90.5688 | P20: =100.724*2.4 -> 241.7376 | Q20: =111.812*0.6 -> 67.0872 | R20: =665.67+21.929 -> 687.599 | S20: =67.086*7.5 -> 503.145 | T20: =111.812*3.5 -> 391.342 | U20: =147.793*0.6 -> 88.6758 | V20: =99.068*1.6 -> 158.5088 | W20: =33.544*0.6 -> 20.1264 | X20: =111.812*3 -> 335.436 | Y20: =147.793 -> 147.793 | Z20: 20.126 | AB20: =67.086*3 -> 201.258 | AC20: =100.724*2 -> 201.448 | AD20: =77.082*5 -> 385.41 | AE20: =147.793*1.3 -> 192.1309 | AF20: =147.793*0.6 -> 88.6758 | AG20: 61.369 | AH20: =72.678*2 -> 145.356 | AI20: =72.678*8 -> 581.424 | AJ20: =99.068*1.4 -> 138.6952 | AK20: 19.385 | AM20: =99.068*3 -> 297.204 | AO20: 111.812 | AP20: =178.004*0.3 -> 53.4012 | AR20: 60.48 | AX20: =100.631*5 -> 503.155 | AZ20: 100.631 | BB20: =147.793*1.5 -> 221.6895 | BF20: =60.48/0.6*0.7 -> 70.56 | BI20: 147.793 | BL20: 60.48 | BM20: =147.793*0.6 -> 88.6758 | BV20: 47.012 | BW20: =99.068*3 -> 297.204 | BX20: 105.205 | BY20: =67.086*3.8 -> 254.9268 | BZ20: =147.793*0.5 -> 73.8965 | CA20: =SUM(K20:BZ20) -> 9461.6153 | CC20: =100.724*2.4 -> 241.7376 | CE20: =33.544*0.6 -> 20.1264 | CF20: =99.068*1.8 -> 178.3224 | CG20: =99.068*1.3 -> 128.7884 | CH20: 147.793 | CJ20: =147.793*1.3 -> 192.1309 | CK20: =100.724*5 -> 503.62 | CL20: =44.338/0.3*0.2 -> 29.558667 | CM20: =99.068*5 -> 495.34 | CO20: =67.086*6 -> 402.516 | CP20: =177.352/1.2*0.6 -> 88.676 | CQ20: =147.793*2 -> 295.586 | CR20: 60.48 | CS20: =201.6*5 -> 1008 | CV20: =100.631*4 -> 402.524 | CY20: =221.69/1.5*0.5 -> 73.896667 | CZ20: =147.793*1.5 -> 221.6895 | DA20: 147.793 | DB20: =302.4 -> 302.4 | DC20: =100.631/3*3.5 -> 117.40283 | DD20: =50.4*7 -> 352.8 | DE20: =50.4*3 -> 151.2 | DH20: 23.506 | DJ20: 342.72 | DK20: =67.086*5 -> 335.43 | DM20: =67.086*7 -> 469.602 | DO20: =100.8*1.2 -> 120.96 | DP20: =111.812*1.5 -> 167.718 | DQ20: =99.068*1.7 -> 168.4156 | DR20: =147.793*0.3 -> 44.3379 | DS20: =178.004*0.3 -> 53.4012 | DT20: =50.4*5 -> 252 | DU20: =SUM(CC20:DT20) -> 7540.4721 | DW20: =100.724*2.4 -> 241.7376 | DX20: =147.793*1.3 -> 192.1309 | DY20: =111.812*1.5 -> 167.718 | DZ20: 147.793 | EA20: =100.724*5 -> 503.62 | EC20: =147.793*2 -> 295.586 | GA20: =SUM(DW20:FZ20) -> 1548.5855 | GD20: =68.188*0.9 -> 61.3692 | GE20: =33.544*0.9 -> 30.1896 | GF20: =100.8*3 -> 302.4 | GG20: =147.793*1.2 -> 177.3516 | GH20: =99.068*3 -> 297.204 | GO20: =SUM(GC20:GN20) -> 868.5144 | GP20: =I20-GO20 -> 11977.166 | GQ20: =I20 -> 12845.68 | GR20: =C20 -> 9027.017 | GS20: =E20 -> 7540.5 | GT20: =B20 -> сульфат магния б/водный, магний с/кисл.
A21: =A20+1 -> 12 | B21: сульфат магния Кизерит | C21: ='1_квартал'!G21 -> 0 | D21: 0 | E21: 0 | G21: =ROUND(AVERAGE(D21:F21),3) -> 0 | H21: 0 | I21: 0 | CA21: =SUM(K21:BZ21) -> 0 | DU21: =SUM(CC21:DT21) -> 0 | GA21: =SUM(DW21:FZ21) -> 0 | GO21: =SUM(GC21:GN21) -> 0 | GP21: =I21-GO21 -> 0 | GQ21: =I21 -> 0 | GR21: =C21 -> 0 | GS21: =E21 -> 0 | GT21: =B21 -> сульфат магния Кизерит
A22: =A21+1 -> 13 | B22: сера | C22: ='1_квартал'!G22 -> 93.417 | D22: 123.55 | E22: =43.61+63.07 -> 106.68 | G22: =ROUND(AVERAGE(D22:F22),3) -> 115.115 | H22: 136.93 | I22: 136.93 | L22: 2.036 | AK22: 4.435 | AN22: 13.135 | AT22: =10.182*3.6 -> 36.6552 | AW22: 20.364 | BD22: =1.527/0.3*0.1 -> 0.509 | BR22: =1.833/0.9*0.8 -> 1.6293333 | BS22: =10.182*4 -> 40.728 | BX22: 4.061 | CA22: =SUM(K22:BZ22) -> 123.55253 | CN22: 6.109 | DB22: =90.72 -> 90.72 | DF22: =6.567*1.5 -> 9.8505 | DU22: =SUM(CC22:DT22) -> 106.6795 | GA22: =SUM(DW22:FZ22) -> 0 | GF22: =30.24*3 -> 90.72 | GO22: =SUM(GC22:GN22) -> 90.72 | GP22: =I22-GO22 -> 46.21 | GQ22: =I22 -> 136.93 | GR22: =C22 -> 93.417 | GS22: =E22 -> 106.68 | GT22: =B22 -> сера
A23: =A22+1 -> 14 | B23: сульфат железа+моносульфер | C23: ='1_квартал'!G23 -> 38.557 | D23: 133.85 | E23: 5.38 | G23: =ROUND(AVERAGE(D23:F23),3) -> 69.615 | H23: =5.01+1500 -> 1505.01 | I23: 1498.96 | L23: 2.016 | AL23: 0.064 | AQ23: 0.134 | AS23: 0.09 | AT23: =10.08*3.6 -> 36.288 | AU23: =3.36*9 -> 30.24 | AW23: 20.16 | BD23: =0.605/0.3*0.1 -> 0.20166667 | BJ23: =1.792/8*1.8 -> 0.4032 | BK23: =1.792/8*1.5 -> 0.336 | BN23: =3.36*0.6 -> 2.016 | BP23: =1.792/8*4.7 -> 1.0528 | BR23: =0.605/0.9*0.8 -> 0.53777778 | BS23: =10.08*4 -> 40.32 | CA23: =SUM(K23:BZ23) -> 133.85944 | CN23: 2.016 | DL23: 3.36 | DU23: =SUM(CC23:DT23) -> 5.376 | EE23: =3.36*1.8 -> 6.048 | GA23: =SUM(DW23:FZ23) -> 6.048 | GO23: =SUM(GC23:GN23) -> 0 | GP23: =I23-GO23 -> 1498.96 | GQ23: =I23 -> 1498.96 | GR23: =C23 -> 38.557 | GS23: =E23 -> 5.38 | GT23: =B23 -> сульфат железа+моносульфер
A24: =A23+1 -> 15 | B24: медный купорос | C24: ='1_квартал'!G24 -> 214.34 | D24: 207.37 | E24: =22.122+161.508 -> 183.63 | G24: =ROUND(AVERAGE(D24:F24),3) -> 195.5 | H24: 838.492 | I24: 833.772 | L24: 0.403 | O24: =0.968*2.7 -> 2.6136 | Q24: =1.21*0.6 -> 0.726 | S24: =0.968*7.5 -> 7.26 | V24: =4.435*1.6 -> 7.096 | W24: =0.968*0.6 -> 0.5808 | AA24: =1.411*0.9 -> 1.2699 | AB24: =0.968*3 -> 2.904 | AD24: =2.016*5 -> 10.08 | AF24: =2.55*0.6 -> 1.53 | AH24: =6.048*2 -> 12.096 | AI24: =6.048*8 -> 48.384 | AJ24: =6.653*1.4 -> 9.3142 | AM24: =4.435*3 -> 13.305 | AO24: 1.21 | AQ24: =0.113 -> 0.113 | AS24: 0.075 | AT24: =2.016*3.6 -> 7.2576 | AU24: =2.822*9 -> 25.398 | AV24: =8.467*2.3 -> 19.4741 | AW24: 4.032 | AY24: =1.21 -> 1.21 | BA24: =1.411 -> 1.411 | BC24: =4.355/1.2*0.3 -> 1.08875 | BD24: =0.097/0.3*0.1 -> 0.032333333 | BE24: 0.363 | BM24: =2.55*0.6 -> 1.53 | BN24: =2.621*0.6 -> 1.5726 | BS24: =2.016*4 -> 8.064 | BW24: =4.435*3 -> 13.305 | BY24: =0.968*3.8 -> 3.6784 | CA24: =SUM(K24:BZ24) -> 207.37728 | CE24: =0.968*0.6 -> 0.5808 | CF24: =6.653*1.8 -> 11.9754 | CG24: =4.435*1.3 -> 5.7655 | CI24: =1.411*0.9 -> 1.2699 | CL24: =0.765/0.3*0.2 -> 0.51 | CM24: =4.435*5 -> 22.175 | CO24: =0.968*6 -> 5.808 | CP24: =3.06/1.2*0.6 -> 1.53 | CU24: =1.411*1.5 -> 2.1165 | CW24: =1.21 -> 1.21 | DB24: =28.764 -> 28.764 | DD24: =5.04*7 -> 35.28 | DE24: =5.04*3 -> 15.12 | DK24: =0.968*5 -> 4.84 | DL24: 2.621 | DM24: =0.968*7 -> 6.776 | DQ24: =6.653*1.7 -> 11.3101 | DR24: =2.55*0.3 -> 0.765 | DT24: =5.04*5 -> 25.2 | DU24: =SUM(CC24:DT24) -> 183.6172 | EE24: =2.621*1.8 -> 4.7178 | GA24: =SUM(DW24:FZ24) -> 4.7178 | GF24: =9.588*3 -> 28.764 | GG24: =2.55*1.2 -> 3.06 | GH24: =4.435*3 -> 13.305 | GO24: =SUM(GC24:GN24) -> 45.129 | GP24: =I24-GO24 -> 788.643 | GQ24: =I24 -> 833.772 | GR24: =C24 -> 214.34 | GS24: =E24 -> 183.63 | GT24: =B24 -> медный купорос
A25: =A24+1 -> 16 | B25: цинковый купорос+ сульфат цинка | C25: ='1_квартал'!G25 -> 836.95 | D25: =574.64+251.82 -> 826.46 | E25: 732.29 | G25: =ROUND(AVERAGE(D25:F25),3) -> 779.375 | H25: =15.89+1000 -> 1015.89 | I25: 989.63 | L25: 1.326 | N25: =10.345*5 -> 51.725 | O25: =2.918*2.7 -> 7.8786 | Q25: =1.273*0.6 -> 0.7638 | S25: =2.918*7.5 -> 21.885 | V25: =18.568*1.6 -> 29.7088 | W25: =2.918*0.6 -> 1.7508 | AA25: =3.316*0.9 -> 2.9844 | AB25: =2.918*3 -> 8.754 | AD25: =1.989*5 -> 9.945 | AF25: =2.865*0.6 -> 1.719 | AH25: =24.802*2 -> 49.604 | AI25: =24.802*8 -> 198.416 | AJ25: =27.853*1.4 -> 38.9942 | AK25: 1.194 | AL25: 0.119 | AM25: =18.568*3 -> 55.704 | AO25: 1.273 | AQ25: 0.637 | AR25: 1.114 | AS25: 0.424 | AT25: =6.632*3.6 -> 23.8752 | AU25: =15.916*9 -> 143.244 | AV25: =18.568*2.3 -> 42.7064 | AW25: 13.263 | AY25: =2.785 -> 2.785 | BA25: =3.316 -> 3.316 | BC25: =5.73/1.2*0.3 -> 1.4325 | BD25: =0.159/0.3*0.1 -> 0.053 | BE25: 0.477 | BF25: =1.114/0.6*0.7 -> 1.2996667 | BL25: 1.114 | BM25: =2.865*0.6 -> 1.719 | BN25: =14.589*0.6 -> 8.7534 | BS25: =6.632*4 -> 26.528 | BW25: =18.568*3 -> 55.704 | BX25: 3.183 | BY25: =2.918*3.8 -> 11.0884 | CA25: =SUM(K25:BZ25) -> 826.46117 | CE25: =2.918*0.6 -> 1.7508 | CF25: =27.853*1.8 -> 50.1354 | CG25: =18.568*1.3 -> 24.1384 | CI25: =3.316*0.9 -> 2.9844 | CL25: =0.859/0.3*0.2 -> 0.57266667 | CM25: =18.568*5 -> 92.84 | CO25: =2.918*6 -> 17.508 | CP25: =3.438/1.2*0.6 -> 1.719 | CR25: =1.114 -> 1.114 | CS25: =11.141*5 -> 55.705 | CU25: =3.316*1.5 -> 4.974 | CW25: =2.785 -> 2.785 | DB25: =67.642 -> 67.642 | DD25: =20.558*7 -> 143.906 | DE25: =20.558*3 -> 61.674 | DK25: =2.918*5 -> 14.59 | DL25: 14.589 | DM25: =2.918*7 -> 20.426 | DO25: =1.857*1.2 -> 2.2284 | DQ25: =27.853*1.7 -> 47.3501 | DR25: =2.865*0.3 -> 0.8595 | DT25: =20.558*5 -> 102.79 | DU25: =SUM(CC25:DT25) -> 732.28167 | EE25: =14.589*1.8 -> 26.2602 | GA25: =SUM(DW25:FZ25) -> 26.2602 | GF25: =22.547*3 -> 67.641 | GG25: =2.865*1.2 -> 3.438 | GH25: =18.568*3 -> 55.704 | GO25: =SUM(GC25:GN25) -> 126.783 | GP25: =I25-GO25 -> 862.847 | GQ25: =I25 -> 989.63 | GR25: =C25 -> 836.95 | GS25: =E25 -> 732.29 | GT25: =B25 -> цинковый купорос+ сульфат цинка
A26: =A25+1 -> 17 | B26: сульфат марганца | C26: ='1_квартал'!G26 -> 532.47 | D26: 565.8 | E26: 523.61 | G26: =ROUND(AVERAGE(D26:F26),3) -> 544.705 | H26: 208.43 | I26: 205.59 | L26: 2.52 | N26: =10.71*5 -> 53.55 | O26: =1.89*2.7 -> 5.103 | Q26: =1.796*0.6 -> 1.0776 | S26: =1.89*7.5 -> 14.175 | V26: =11.813*1.6 -> 18.9008 | W26: =1.89*0.6 -> 1.134 | AA26: =3.938*0.9 -> 3.5442 | AB26: =1.89*3 -> 5.67 | AD26: =1.575*5 -> 7.875 | AF26: =4.142*0.6 -> 2.4852 | AH26: =14.648*2 -> 29.296 | AI26: =14.648*8 -> 117.184 | AJ26: =17.719*1.4 -> 24.8066 | AL26: 0.054 | AM26: =11.813*3 -> 35.439 | AO26: 1.796 | AQ26: 0.009 | AR26: 0.472 | AS26: 0.042 | AT26: =12.6*3.6 -> 45.36 | AU26: =1.575*9 -> 14.175 | AV26: =22.05*2.3 -> 50.715 | AW26: 25.2 | AY26: =2.599 -> 2.599 | BA26: =3.938 -> 3.938 | BC26: =3.402/1.2*0.3 -> 0.8505 | BD26: =0.189/0.3*0.1 -> 0.063 | BE26: 0.283 | BF26: =0.472/0.6*0.7 -> 0.55066667 | BL26: 0.472 | BM26: =4.142*0.6 -> 2.4852 | BN26: =1.575*0.6 -> 0.945 | BS26: =12.6*4 -> 50.4 | BW26: =11.813*3 -> 35.439 | BY26: =1.89*3.8 -> 7.182 | CA26: =SUM(K26:BZ26) -> 565.79077 | CE26: =1.89*0.6 -> 1.134 | CF26: =17.719*1.8 -> 31.8942 | CG26: =11.813*1.3 -> 15.3569 | CI26: =3.938*0.9 -> 3.5442 | CL26: =1.243/0.3*0.2 -> 0.82866667 | CM26: =11.813*5 -> 59.065 | CO26: =1.89*6 -> 11.34 | CP26: =4.971/1.2*0.6 -> 2.4855 | CR26: =0.472 -> 0.472 | CS26: =10.71*5 -> 53.55 | CU26: =3.938*1.5 -> 5.907 | CW26: =2.599 -> 2.599 | DB26: =94.594 -> 94.594 | DD26: =12.285*7 -> 85.995 | DE26: =12.285*3 -> 36.855 | DK26: =1.89*5 -> 9.45 | DL26: 1.575 | DM26: =1.89*7 -> 13.23 | DO26: =0.787*1.2 -> 0.9444 | DQ26: =17.719*1.7 -> 30.1223 | DR26: =4.142*0.3 -> 1.2426 | DT26: =12.285*5 -> 61.425 | DU26: =SUM(CC26:DT26) -> 523.60977 | EE26: =1.575*1.8 -> 2.835 | GA26: =SUM(DW26:FZ26) -> 2.835 | GF26: =31.531*3 -> 94.593 | GG26: =4.142*1.2 -> 4.9704 | GH26: =11.813*3 -> 35.439 | GO26: =SUM(GC26:GN26) -> 135.0024 | GP26: =I26-GO26 -> 70.5876 | GQ26: =I26 -> 205.59 | GR26: =C26 -> 532.47 | GS26: =E26 -> 523.61 | GT26: =B26 -> сульфат марганца
A27: =A26+1 -> 18 | B27: калий йод | C27: ='1_квартал'!G27 -> 15.296 | D27: 15.108 | E27: 8.01 | G27: =ROUND(AVERAGE(D27:F27),3) -> 11.559 | H27: 1.875 | I27: 1.595 | K27: =0.219*3 -> 0.657 | L27: 0.004 | O27: =0.044*2.7 -> 0.1188 | P27: =0.219*2.4 -> 0.5256 | Q27: =0.053*0.6 -> 0.0318 | S27: =0.044*7.5 -> 0.33 | T27: =0.053*3.5 -> 0.1855 | U27: =0.139*0.6 -> 0.0834 | V27: =0.219*1.6 -> 0.3504 | W27: =0.044*0.6 -> 0.0264 | X27: =0.053*3 -> 0.159 | Y27: =0.139 -> 0.139 | Z27: 0.026 | AA27: =0.14*0.9 -> 0.126 | AB27: =0.044*3 -> 0.132 | AC27: =0.219*2 -> 0.438 | AD27: =0.175*5 -> 0.875 | AE27: =0.139*1.3 -> 0.1807 | AF27: =0.139*0.6 -> 0.0834 | AG27: 0.047 | AH27: =0.175*2 -> 0.35 | AI27: =0.175*8 -> 1.4 | AJ27: =0.219*1.4 -> 0.3066 | AL27: 0.003 | AM27: =0.219*3 -> 0.657 | AN27: 0.351 | AO27: 0.053 | AQ27: 0.015 | AS27: 0.01 | AT27: =0.018*3.6 -> 0.0648 | AU27: =0.365*9 -> 3.285 | AV27: =0.205*2.3 -> 0.4715 | AW27: 0.035 | AX27: =0.219*5 -> 1.095 | AY27: =0.076 -> 0.076 | AZ27: 0.131 | BA27: =0.14 -> 0.14 | BB27: =0.139*1.5 -> 0.2085 | BC27: =0.189/1.2*0.3 -> 0.04725 | BD27: =0.004/0.3*0.1 -> 0.0013333333 | BE27: 0.016 | BI27: 0.139 | BJ27: =0.195/8*1.8 -> 0.043875 | BK27: =0.195/8*1.5 -> 0.0365625 | BM27: =0.139*0.6 -> 0.0834 | BN27: =0.365*0.6 -> 0.219 | BP27: =0.195/8*4.7 -> 0.1145625 | BR27: =0.026/0.9*0.8 -> 0.023111111 | BS27: =0.018*4 -> 0.072 | BV27: 0.21 | BW27: =0.219*3 -> 0.657 | BX27: 0.063 | BY27: =0.044*3.8 -> 0.1672 | BZ27: =0.139*0.5 -> 0.0695 | CA27: =SUM(K27:BZ27) -> 15.134194 | CC27: =0.219*2.4 -> 0.5256 | CE27: =0.044*0.6 -> 0.0264 | CF27: =0.219*1.8 -> 0.3942 | CG27: =0.219*1.3 -> 0.2847 | CH27: 0.139 | CI27: =0.14*0.9 -> 0.126 | CJ27: =0.139*1.3 -> 0.1807 | CK27: =0.219*5 -> 1.095 | CL27: =0.042/0.3*0.2 -> 0.028 | CM27: =0.219*5 -> 1.095 | CN27: 0.088 | CO27: =0.044*6 -> 0.264 | CP27: =0.167/1.2*0.6 -> 0.0835 | CQ27: =0.139*2 -> 0.278 | CU27: =0.14*1.5 -> 0.21 | CV27: =0.219*4 -> 0.876 | CW27: =0.076 -> 0.076 | CY27: =0.208/1.5*0.5 -> 0.069333333 | CZ27: =0.139*1.5 -> 0.2085 | DA27: 0.153 | DB27: =0.789 -> 0.789 | DC27: =0.131/3*3.5 -> 0.15283333 | DF27: =0.175*1.5 -> 0.2625 | DH27: 0.105 | DK27: =0.044*5 -> 0.22 | DM27: =0.044*7 -> 0.308 | DU27: =SUM(CC27:DT27) -> 8.0382667 | EC27: =0.139*2 -> 0.278 | GA27: =SUM(DW27:FZ27) -> 0.278 | GF27: =0.263*3 -> 0.789 | GG27: =0.139*1.2 -> 0.1668 | GH27: =0.219*3 -> 0.657 | GO27: =SUM(GC27:GN27) -> 1.6128 | GP27: =I27-GO27 -> -0.0178 | GQ27: =I27 -> 1.595 | GR27: =C27 -> 15.296 | GS27: =E27 -> 8.01 | GT27: =B27 -> калий йод
A28: =A27+1 -> 19 | B28: йодат кальция | C28: ='1_квартал'!G28 -> 0 | D28: 0 | E28: 3.4 | G28: =ROUND(AVERAGE(D28:F28),3) -> 1.7 | H28: 46.6 | I28: 43.62 | CA28: =SUM(K28:BZ28) -> 0 | DD28: =0.163*7 -> 1.141 | DE28: =0.163*3 -> 0.489 | DL28: 0.406 | DP28: =0.059*1.5 -> 0.0885 | DQ28: =0.244*1.7 -> 0.4148 | DR28: =0.154*0.3 -> 0.0462 | DT28: =0.163*5 -> 0.815 | DU28: =SUM(CC28:DT28) -> 3.4005 | DW28: =0.244*2.4 -> 0.5856 | DX28: =0.154*1.3 -> 0.2002 | DY28: =0.059*1.5 -> 0.0885 | DZ28: 0.154 | EA28: =0.244*5 -> 1.22 | EE28: =0.406*1.8 -> 0.7308 | GA28: =SUM(DW28:FZ28) -> 2.9791 | GD28: =0.059*0.9 -> 0.0531 | GE28: =0.049*0.9 -> 0.0441 | GO28: =SUM(GC28:GN28) -> 0.0972 | GP28: =I28-GO28 -> 43.5228 | GQ28: =I28 -> 43.62 | GR28: =C28 -> 0 | GS28: =E28 -> 3.4 | GT28: =B28 -> йодат кальция
A29: =A28+1 -> 20 | B29: кобальт у/к | C29: ='1_квартал'!G29 -> 9.943 | D29: 12.69 | E29: 6.4 | G29: =ROUND(AVERAGE(D29:F29),3) -> 9.545 | H29: =15.47+25 -> 40.47 | I29: =13.37+25 -> 38.37 | K29: =0.129*3 -> 0.387 | L29: 0.039 | O29: =0.026*2.7 -> 0.0702 | P29: =0.129*2.4 -> 0.3096 | Q29: =0.03*0.6 -> 0.018 | S29: =0.026*7.5 -> 0.195 | T29: =0.03*3.5 -> 0.105 | U29: =0.075*0.6 -> 0.045 | V29: =0.129*1.6 -> 0.2064 | W29: =0.026*0.6 -> 0.0156 | X29: =0.03*3 -> 0.09 | Y29: =0.075 -> 0.075 | Z29: 0.015 | AA29: =0.064*0.9 -> 0.0576 | AB29: =0.026*3 -> 0.078 | AC29: =0.129*2 -> 0.258 | AD29: =0.086*5 -> 0.43 | AE29: =0.075*1.3 -> 0.0975 | AF29: =0.075*0.6 -> 0.045 | AG29: 0.027 | AH29: =0.097*2 -> 0.194 | AI29: =0.097*8 -> 0.776 | AJ29: =0.129*1.4 -> 0.1806 | AM29: =0.129*3 -> 0.387 | AN29: 0.172 | AO29: 0.03 | AQ29: 0.017 | AR29: 0.006 | AS29: 0.011 | AT29: =0.193*3.6 -> 0.6948 | AU29: =0.429*9 -> 3.861 | AV29: =0.15*2.3 -> 0.345 | AW29: 0.386 | AX29: =0.129*5 -> 0.645 | AY29: =0.047 -> 0.047 | AZ29: 0.077 | BA29: =0.064 -> 0.064 | BB29: =0.075*1.5 -> 0.1125 | BC29: =0.093/1.2*0.3 -> 0.02325 | BD29: =0.023/0.3*0.1 -> 0.0076666667 | BE29: 0.008 | BF29: =0.006/0.6*0.7 -> 0.007 | BI29: 0.075 | BJ29: =0.228/8*1.8 -> 0.0513 | BK29: =0.228/8*1.5 -> 0.04275 | BL29: 0.006 | BM29: =0.075*0.6 -> 0.045 | BN29: =0.429*0.6 -> 0.2574 | BP29: =0.228/8*4.7 -> 0.13395 | BR29: =0.029/0.9*0.8 -> 0.025777778 | BS29: =0.193*4 -> 0.772 | BV29: 0.051 | BW29: =0.129*3 -> 0.387 | BX29: 0.036 | BY29: =0.026*3.8 -> 0.0988 | BZ29: =0.075*0.5 -> 0.0375 | CA29: =SUM(K29:BZ29) -> 12.635194 | CC29: =0.129*2.4 -> 0.3096 | CE29: =0.026*0.6 -> 0.0156 | CF29: =0.129*1.8 -> 0.2322 | CG29: =0.129*1.3 -> 0.1677 | CH29: 0.075 | CI29: =0.064*0.9 -> 0.0576 | CJ29: =0.075*1.3 -> 0.0975 | CK29: =0.129*5 -> 0.645 | CL29: =0.023/0.3*0.2 -> 0.015333333 | CM29: =0.129*5 -> 0.645 | CN29: 0.097 | CO29: =0.026*6 -> 0.156 | CP29: =0.09/1.2*0.6 -> 0.045 | CQ29: =0.075*2 -> 0.15 | CR29: 0.006 | CU29: =0.064*1.5 -> 0.096 | CV29: =0.129*4 -> 0.516 | CW29: =0.047 -> 0.047 | CY29: =0.113/1.5*0.5 -> 0.037666667 | CZ29: =0.075*1.5 -> 0.1125 | DA29: 0.075 | DB29: 0.29 | DC29: =0.077/3*3.5 -> 0.089833333 | DD29: =0.08*7 -> 0.56 | DE29: =0.08*3 -> 0.24 | DF29: =0.086*1.5 -> 0.129 | DH29: 0.026 | DK29: =0.026*5 -> 0.13 | DL29: 0.429 | DM29: =0.026*7 -> 0.182 | DO29: =0.011*1.2 -> 0.0132 | DP29: =0.03*1.5 -> 0.045 | DQ29: =0.129*1.7 -> 0.2193 | DR29: =0.075*0.3 -> 0.0225 | DT29: =0.08*5 -> 0.4 | DU29: =SUM(CC29:DT29) -> 6.3745333 | DW29: =0.129*2.4 -> 0.3096 | DX29: =0.075*1.3 -> 0.0975 | DY29: =0.03*1.5 -> 0.045 | DZ29: 0.075 | EA29: =0.129*5 -> 0.645 | EC29: =0.075*2 -> 0.15 | EE29: =0.429*1.8 -> 0.7722 | GA29: =SUM(DW29:FZ29) -> 2.0943 | GD29: =0.03*0.9 -> 0.027 | GE29: =0.026*0.9 -> 0.0234 | GF29: =0.097*3 -> 0.291 | GG29: =0.075*1.2 -> 0.09 | GH29: =0.129*3 -> 0.387 | GO29: =SUM(GC29:GN29) -> 0.8184 | GP29: =I29-GO29 -> 37.5516 | GQ29: =I29 -> 38.37 | GR29: =C29 -> 9.943 | GS29: =E29 -> 6.4 | GT29: =B29 -> кобальт у/к
A30: =A29+1 -> 21 | B30: селенит натрия | C30: ='1_квартал'!G30 -> 2.328 | D30: 2.486 | E30: 1.825 | G30: =ROUND(AVERAGE(D30:F30),3) -> 2.156 | H30: 15.576 | I30: 15.556 | L30: 0.008 | N30: =0.016*5 -> 0.08 | V30: =0.078*1.6 -> 0.1248 | AA30: =0.016*0.9 -> 0.0144 | AD30: =0.019*5 -> 0.095 | AF30: =0.024*0.6 -> 0.0144 | AH30: =0.045*2 -> 0.09 | AI30: =0.045*8 -> 0.36 | AJ30: =0.118*1.4 -> 0.1652 | AM30: =0.078*3 -> 0.234 | AQ30: 0.003 | AR30: 0.02 | AS30: 0.002 | AT30: =0.038*3.6 -> 0.1368 | AU30: =0.009*9 -> 0.081 | AV30: =0.179*2.3 -> 0.4117 | AW30: 0.076 | AY30: =0.016 -> 0.016 | BA30: =0.016 -> 0.016 | BC30: =0.02/1.2*0.3 -> 0.005 | BE30: 0.002 | BF30: =0.02/0.6*0.7 -> 0.023333333 | BJ30: =0.036/8*1.8 -> 0.0081 | BK30: =0.036/8*1.5 -> 0.00675 | BL30: 0.02 | BM30: =0.024*0.6 -> 0.0144 | BN30: =0.009*0.6 -> 0.0054 | BP30: =0.036/8*4.7 -> 0.02115 | BS30: =0.038*4 -> 0.152 | BU30: =0.027*0.4 -> 0.0108 | BW30: =0.078*3 -> 0.234 | CA30: =SUM(K30:BZ30) -> 2.4512333 | CF30: =0.118*1.8 -> 0.2124 | CG30: =0.078*1.3 -> 0.1014 | CI30: =0.016*0.9 -> 0.0144 | CL30: =0.007/0.3*0.2 -> 0.0046666667 | CM30: =0.078*5 -> 0.39 | CP30: =0.028/1.2*0.6 -> 0.014 | CR30: 0.02 | CS30: =0.016*5 -> 0.08 | CU30: =0.016*1.5 -> 0.024 | CW30: =0.016 -> 0.016 | DB30: =0.202 -> 0.202 | DD30: =0.034*7 -> 0.238 | DE30: =0.034*3 -> 0.102 | DL30: 0.009 | DO30: =0.034*1.2 -> 0.0408 | DQ30: =0.118*1.7 -> 0.2006 | DR30: =0.024*0.3 -> 0.0072 | DT30: =0.034*5 -> 0.17 | DU30: =SUM(CC30:DT30) -> 1.8464667 | EE30: =0.009*1.8 -> 0.0162 | GA30: =SUM(DW30:FZ30) -> 0.0162 | GF30: =0.067*3 -> 0.201 | GG30: =0.024*1.2 -> 0.0288 | GH30: =0.078*3 -> 0.234 | GO30: =SUM(GC30:GN30) -> 0.4638 | GP30: =I30-GO30 -> 15.0922 | GQ30: =I30 -> 15.556 | GR30: =C30 -> 2.328 | GS30: =E30 -> 1.825 | GT30: =B30 -> селенит натрия
A31: =A30+1 -> 22 | B31: Метионин | C31: ='1_квартал'!G31 -> 0 | D31: 0 | E31: 0 | G31: =ROUND(AVERAGE(D31:F31),3) -> 0 | H31: 0 | I31: 0 | CA31: =SUM(K31:BZ31) -> 0 | DU31: =SUM(CC31:DT31) -> 0 | GA31: =SUM(DW31:FZ31) -> 0 | GO31: =SUM(GC31:GN31) -> 0 | GP31: =I31-GO31 -> 0 | GQ31: =I31 -> 0 | GR31: =C31 -> 0 | GS31: =E31 -> 0 | GT31: =B31 -> Метионин
A32: =A31+1 -> 23 | B32: МиТаргет (Метионин защищённый) | C32: ='1_квартал'!G32 -> 222.503 | D32: =172.16+40.78 -> 212.94 | E32: 140.62 | G32: =ROUND(AVERAGE(D32:F32),3) -> 176.78 | H32: 143.6 | I32: 143.6 | Z32: 24.106 | AG32: 36.158 | AZ32: 120.528 | BX32: 32.141 | CA32: =SUM(K32:BZ32) -> 212.933 | DC32: =120.528/3*3.5 -> 140.616 | DU32: =SUM(CC32:DT32) -> 140.616 | GA32: =SUM(DW32:FZ32) -> 0 | GD32: =40.176*0.9 -> 36.1584 | GE32: =40.176*0.9 -> 36.1584 | GO32: =SUM(GC32:GN32) -> 72.3168 | GP32: =I32-GO32 -> 71.2832 | GQ32: =I32 -> 143.6 | GR32: =C32 -> 222.503 | GS32: =E32 -> 140.62 | GT32: =B32 -> МиТаргет (Метионин защищённый)
A33: =A32+1 -> 24 | B33: монокальцийфосфат (МКФ) | C33: ='1_квартал'!G33 -> 5307.797 | D33: =1140.82+3637.39 -> 4778.21 | E33: 5986.13 | G33: =ROUND(AVERAGE(D33:F33),3) -> 5382.17 | H33: 9782.48 | I33: 8499.81 | K33: =154.728*3 -> 464.184 | P33: =150.696*2.4 -> 361.6704 | U33: =34.272*0.6 -> 20.5632 | V33: =157.752*1.6 -> 252.4032 | Y33: =34.272 -> 34.272 | Z33: 10.282 | AA33: =132.149*0.9 -> 118.9341 | AC33: =154.728*2 -> 309.456 | AD33: =85.68*5 -> 428.4 | AE33: =34.272*1.3 -> 44.5536 | AF33: =34.272*0.6 -> 20.5632 | AJ33: =156.24*1.4 -> 218.736 | AM33: =158.256*3 -> 474.768 | AU33: =10.08*9 -> 90.72 | AX33: =159.264*5 -> 796.32 | AY33: =110.376 -> 110.376 | AZ33: 51.408 | BA33: =132.149 -> 132.149 | BB33: =34.272*1.5 -> 51.408 | BI33: 34.272 | BM33: =34.272*0.6 -> 20.5632 | BR33: =90.72/0.9*0.8 -> 80.64 | BV33: 159.667 | BW33: =158.256*3 -> 474.768 | BZ33: =34.272*0.5 -> 17.136 | CA33: =SUM(K33:BZ33) -> 4778.2129 | CC33: =150.696*2.4 -> 361.6704 | CF33: =156.24*1.8 -> 281.232 | CG33: =159.264*1.3 -> 207.0432 | CH33: 34.272 | CI33: =132.149*0.9 -> 118.9341 | CJ33: =34.272*1.3 -> 44.5536 | CK33: =154.728*5 -> 773.64 | CL33: =10.282/0.3*0.2 -> 6.8546667 | CM33: =158.256*5 -> 791.28 | CN33: 302.4 | CP33: =41.126/1.2*0.6 -> 20.563 | CQ33: =34.272*2 -> 68.544 | CU33: =132.149*1.5 -> 198.2235 | CV33: =159.264*4 -> 637.056 | CW33: =110.376 -> 110.376 | CY33: =51.408/1.5*0.5 -> 17.136 | CZ33: =34.272*1.5 -> 51.408 | DA33: =16.632*2 -> 33.264 | DC33: =51.408/3*3.5 -> 59.976 | DD33: =100.8*7 -> 705.6 | DE33: =100.8*3 -> 302.4 | DH33: 79.834 | DQ33: =156.24*1.7 -> 265.608 | DR33: =34.272*0.3 -> 10.2816 | DT33: =100.8*5 -> 504 | DU33: =SUM(CC33:DT33) -> 5986.1501 | DW33: =150.696*2.4 -> 361.6704 | DX33: =34.272*1.3 -> 44.5536 | DZ33: 34.272 | EA33: =154.728*5 -> 773.64 | EC33: =34.272*2 -> 68.544 | GA33: =SUM(DW33:FZ33) -> 1282.68 | GE33: =17.136*0.9 -> 15.4224 | GG33: =34.272*1.2 -> 41.1264 | GH33: =157.752*3 -> 473.256 | GO33: =SUM(GC33:GN33) -> 529.8048 | GP33: =I33-GO33 -> 7970.0052 | GQ33: =I33 -> 8499.81 | GR33: =C33 -> 5307.797 | GS33: =E33 -> 5986.13 | GT33: =B33 -> монокальцийфосфат (МКФ)
A34: =A33+1 -> 25 | B34: мука известняковая | C34: ='1_квартал'!G34 -> 26713.63 | D34: 28611.91 | E34: 15181.66 | G34: =ROUND(AVERAGE(D34:F34),3) -> 21896.785 | H34: =11512.745+67000 -> 78512.745 | I34: =8979.615+67000 -> 75979.615 | K34: =161.28*3 -> 483.84 | L34: 458.975 | M34: =221.727*5 -> 1108.635 | N34: =403.2*5 -> 2016 | O34: =100.8*2.7 -> 272.16 | P34: =161.28*2.4 -> 387.072 | Q34: =282.24*0.6 -> 169.344 | R34: 506.149 | S34: =100.8*7.5 -> 756 | T34: =282.24*3.5 -> 987.84 | U34: =38.808*0.6 -> 23.2848 | V34: =274.378*1.6 -> 439.0048 | W34: =100.8*0.6 -> 60.48 | X34: =282.24*3 -> 846.72 | Y34: =38.808 -> 38.808 | AA34: =478.195*0.9 -> 430.3755 | AB34: =100.8*3 -> 302.4 | AC34: =161.28*2 -> 322.56 | AD34: =219.744*5 -> 1098.72 | AE34: =38.808*1.3 -> 50.4504 | AF34: =38.808*0.6 -> 23.2848 | AG34: 113.4 | AH34: =422.876*2 -> 845.752 | AI34: =422.876*8 -> 3383.008 | AJ34: =274.378*1.4 -> 384.1292 | AK34: 45.36 | AM34: =274.378*3 -> 823.134 | AN34: 197.013 | AO34: 282.24 | AP34: =221.667*0.3 -> 66.5001 | AR34: 181.44 | AS34: 62.797 | AT34: =241.92*3.6 -> 870.912 | AU34: =292.32*9 -> 2630.88 | AW34: 806.4 | AY34: =558.029 -> 558.029 | BA34: =478.195 -> 478.195 | BB34: =38.808*1.5 -> 58.212 | BC34: =252.383/1.2*0.3 -> 63.09575 | BE34: 15.12 | BF34: =181.44/0.6*0.7 -> 211.68 | BG34: 58.442 | BH34: =60.228*0.6 -> 36.1368 | BI34: 38.808 | BJ34: =2016/8*1.8 -> 453.6 | BK34: =2016/8*1.5 -> 378 | BL34: 181.44 | BM34: =38.808*0.6 -> 23.2848 | BN34: =322.56*0.6 -> 193.536 | BP34: =2016/8*4.7 -> 1184.4 | BQ34: 604.8 | BR34: =90.72/0.9*0.8 -> 80.64 | BS34: =262.08*4 -> 1048.32 | BT34: =60.228*1.2 -> 72.2736 | BU34: =151.2*0.4 -> 60.48 | BV34: 112.795 | BW34: =274.378*3 -> 823.134 | BY34: =100.8*3.8 -> 383.04 | BZ34: =38.808*0.5 -> 19.404 | CA34: =SUM(K34:BZ34) -> 28611.935 | CC34: =161.28*2.4 -> 387.072 | CD34: 52.374 | CE34: =100.8*0.6 -> 60.48 | CF34: =274.378*1.8 -> 493.8804 | CG34: =274.378*1.3 -> 356.6914 | CH34: 38.808 | CI34: =478.195*0.9 -> 430.3755 | CJ34: =38.808*1.3 -> 50.4504 | CK34: =161.28*5 -> 806.4 | CL34: =11.642/0.3*0.2 -> 7.7613333 | CM34: =274.378*5 -> 1371.89 | CN34: 302.4 | CO34: =100.8*6 -> 604.8 | CP34: =46.57/1.2*0.6 -> 23.285 | CQ34: =38.808*2 -> 77.616 | CR34: 181.44 | CS34: =403.2*5 -> 2016 | CU34: =478.195*1.5 -> 717.2925 | CW34: =558.029 -> 558.029 | CX34: =59.118*1.2 -> 70.9416 | CY34: =58.212/1.5*0.5 -> 19.404 | CZ34: =38.808*1.5 -> 58.212 | DA34: =18.295*2 -> 36.59 | DB34: =604.8 -> 604.8 | DD34: =97.119*7 -> 679.833 | DE34: =97.119*3 -> 291.357 | DF34: =246.96*1.5 -> 370.44 | DG34: 604.8 | DH34: 56.398 | DI34: 160.145 | DJ34: 254.155 | DK34: =100.8*5 -> 504 | DL34: 322.56 | DM34: =100.8*7 -> 705.6 | DN34: =59.118*1.5 -> 88.677 | DO34: =302.4*1.2 -> 362.88 | DP34: =282.24*1.5 -> 423.36 | DQ34: =274.378*1.7 -> 466.4426 | DR34: =38.808*0.3 -> 11.6424 | DS34: =222.675*0.3 -> 66.8025 | DT34: =97.119*5 -> 485.595 | DU34: =SUM(CC34:DT34) -> 15181.681 | DW34: =161.28*2.4 -> 387.072 | DX34: =38.808*1.3 -> 50.4504 | DY34: =282.24*1.5 -> 423.36 | DZ34: =38.808 -> 38.808 | EA34: =161.28*5 -> 806.4 | EB34: =26.208*3 -> 78.624 | EC34: =38.808*2 -> 77.616 | ED34: =60.126*1.5 -> 90.189 | EE34: =322.56*1.8 -> 580.608 | GA34: =SUM(DW34:FZ34) -> 2533.1274 | GD34: =126*0.9 -> 113.4 | GF34: =201.6*3 -> 604.8 | GG34: =38.808*1.2 -> 46.5696 | GH34: =274.378*3 -> 823.134 | GO34: =SUM(GC34:GN34) -> 1587.9036 | GP34: =I34-GO34 -> 74391.711 | GQ34: =I34 -> 75979.615 | GR34: =C34 -> 26713.63 | GS34: =E34 -> 15181.66 | GT34: =B34 -> мука известняковая
A35: =A34+1 -> 26 | B35: Сахар | I35: 1200 | GA35: =SUM(DW35:FZ35) -> 0 | GO35: =SUM(GC35:GN35) -> 0 | GP35: =I35-GO35 -> 1200 | GQ35: =I35 -> 1200 | GR35: =C35 -> 0 | GS35: =E35 -> 0 | GT35: =B35 -> Сахар
A36: =A35+1 -> 27 | B36: Соль пищ выварочн сорт экстра | C36: ='1_квартал'!G35 -> 3144.59 | D36: 3261.64 | E36: 1604.23 | G36: =ROUND(AVERAGE(D36:F36),3) -> 2432.935 | H36: 9274.09 | I36: 8602.46 | Q36: =40.32*0.6 -> 24.192 | T36: =40.32*3.5 -> 141.12 | U36: =136.08*0.6 -> 81.648 | X36: =40.32*3 -> 120.96 | Y36: =136.08 -> 136.08 | AA36: =101.304*0.9 -> 91.1736 | AD36: =299.376*5 -> 1496.88 | AE36: =136.08*1.3 -> 176.904 | AF36: =136.08*0.6 -> 81.648 | AG36: 27.216 | AK36: 43.189 | AL36: 6.048 | AO36: 40.32 | AY36: =114.408 -> 114.408 | BA36: =101.304 -> 101.304 | BB36: =136.08*1.5 -> 204.12 | BI36: 136.08 | BM36: =136.08*0.6 -> 81.648 | BS36: =0.542*4 -> 2.168 | BV36: 86.486 | BZ36: =136.08*0.5 -> 68.04 | CA36: =SUM(K36:BZ36) -> 3261.6326 | CH36: 136.08 | CI36: =101.304*0.9 -> 91.1736 | CJ36: =136.08*1.3 -> 176.904 | CL36: =40.824/0.3*0.2 -> 27.216 | CP36: =163.296/1.2*0.6 -> 81.648 | CQ36: =136.08*2 -> 272.16 | CU36: =101.304*1.5 -> 151.956 | CW36: =114.408 -> 114.408 | CY36: =204.12/1.5*0.5 -> 68.04 | CZ36: =136.08*1.5 -> 204.12 | DA36: 135.979 | DH36: 43.243 | DP36: =40.32*1.5 -> 60.48 | DR36: =136.08*0.3 -> 40.824 | DU36: =SUM(CC36:DT36) -> 1604.2316 | DX36: =136.08*1.3 -> 176.904 | DY36: =40.32*1.5 -> 60.48 | DZ36: 136.08 | EB36: =8.671*3 -> 26.013 | EC36: =136.08*2 -> 272.16 | GA36: =SUM(DW36:FZ36) -> 671.637 | GD36: =30.24*0.9 -> 27.216 | GG36: =136.08*1.2 -> 163.296 | GO36: =SUM(GC36:GN36) -> 190.512 | GP36: =I36-GO36 -> 8411.948 | GQ36: =I36 -> 8602.46 | GR36: =C36 -> 3144.59 | GS36: =E36 -> 1604.23 | GT36: =B36 -> Соль пищ выварочн сорт экстра
I37: =SUM(I19:I36) -> 138204.47 | CA37: =SUM(K37:BZ37) -> 0
A38: =A36+1 -> 28 | B38: Гидрокарбонат натрия Е500 (сода) | C38: ='1_квартал'!G37 -> 354.313 | D38: =96.96+506.07 -> 603.03 | E38: =49.6+6.35 -> 55.95 | G38: =ROUND(AVERAGE(D38:F38),3) -> 329.49 | H38: =51.38+1487.58 -> 1538.96 | I38: =51.38+1344.22 -> 1395.6 | AA38: =8.568*0.9 -> 7.7112 | AD38: =101.213*5 -> 506.065 | AG38: 9.072 | AS38: 29.867 | AY38: =29.044 -> 29.044 | BA38: =8.568 -> 8.568 | BV38: 12.701 | CA38: =SUM(K38:BZ38) -> 603.0282 | CI38: =8.568*0.9 -> 7.7112 | CU38: =8.568*1.5 -> 12.852 | CW38: =29.044 -> 29.044 | DH38: 6.35 | DU38: =SUM(CC38:DT38) -> 55.9572 | EB38: =47.786*3 -> 143.358 | GA38: =SUM(DW38:FZ38) -> 143.358 | GD38: =10.08*0.9 -> 9.072 | GO38: =SUM(GC38:GN38) -> 9.072 | GP38: =I38-GO38 -> 1386.528 | GQ38: =I38 -> 1395.6 | GR38: =C38 -> 354.313 | GS38: =E38 -> 55.95 | GT38: =B38 -> Гидрокарбонат натрия Е500 (сода)
A39: =A38+1 -> 29 | B39: Актиген | C39: ='1_квартал'!G38 -> 735.673 | D39: =184.58+249+244.06 -> 677.64 | E39: =55.94+265.31 -> 321.25 | G39: =ROUND(AVERAGE(D39:F39),3) -> 499.445 | H39: =133.69+200 -> 333.69 | I39: =107.68+200 -> 307.68 | M39: =30.24*5 -> 151.2 | S39: =5.04*7.5 -> 37.8 | T39: =3.125*3.5 -> 10.9375 | X39: =3.125*3 -> 9.375 | AB39: =5.04*3 -> 15.12 | AD39: =21.168*5 -> 105.84 | AG39: 10.886 | AK39: 33.264 | AN39: 3.024 | AP39: =30.24*0.3 -> 9.072 | AQ39: 0.806 | AS39: 0.537 | AZ39: 48.384 | BC39: =1.21/1.2*0.3 -> 0.3025 | BD39: =0.302/0.3*0.1 -> 0.10066667 | BI39: 24.293 | BO39: =20.16*5 -> 100.8 | BR39: =4.536/0.9*0.8 -> 4.032 | BS39: =10.08*4 -> 40.32 | BU39: =70.56*0.4 -> 28.224 | BX39: 24.192 | BY39: =5.04*3.8 -> 19.152 | CA39: =SUM(K39:BZ39) -> 677.66167 | CH39: 24.293 | CN39: 30.24 | CO39: =5.04*6 -> 30.24 | CT39: =20.16*5 -> 100.8 | DC39: =48.384/3*3.5 -> 56.448 | DF39: =5.04*1.5 -> 7.56 | DK39: =5.04*5 -> 25.2 | DM39: =5.04*7 -> 35.28 | DP39: =1.613*1.5 -> 2.4195 | DS39: =29.232*0.3 -> 8.7696 | DU39: =SUM(CC39:DT39) -> 321.2501 | DY39: =1.613*1.5 -> 2.4195 | DZ39: =23.587 -> 23.587 | GA39: =SUM(DW39:FZ39) -> 26.0065 | GD39: =12.096*0.9 -> 10.8864 | GO39: =SUM(GC39:GN39) -> 10.8864 | GP39: =I39-GO39 -> 296.7936 | GQ39: =I39 -> 307.68 | GR39: =C39 -> 735.673 | GS39: =E39 -> 321.25 | GT39: =B39 -> Актиген
A40: =A39+1 -> 30 | B40: Биогром Энерджи | C40: ='1_квартал'!G39 -> 81.137 | D40: 16.4 | E40: 0 | G40: =ROUND(AVERAGE(D40:F40),3) -> 8.2 | H40: 75 | I40: 75 | AQ40: 16.4 | CA40: =SUM(K40:BZ40) -> 16.4 | DU40: =SUM(CC40:DT40) -> 0 | GA40: =SUM(DW40:FZ40) -> 0 | GO40: =SUM(GC40:GN40) -> 0 | GP40: =I40-GO40 -> 75 | GQ40: =I40 -> 75 | GR40: =C40 -> 81.137 | GS40: =E40 -> 0 | GT40: =B40 -> Биогром Энерджи
A41: =A40+1 -> 31 | B41: Биогром Холин | C41: ='1_квартал'!G40 -> 408.023 | D41: 120.87 | E41: 0 | G41: =ROUND(AVERAGE(D41:F41),3) -> 60.435 | H41: 0 | I41: 0 | Z41: 36 | AG41: 54 | AZ41: 30.87 | CA41: =SUM(K41:BZ41) -> 120.87 | DU41: =SUM(CC41:DT41) -> 0 | GA41: =SUM(DW41:FZ41) -> 0 | GO41: =SUM(GC41:GN41) -> 0 | GP41: =I41-GO41 -> 0 | GQ41: =I41 -> 0 | GR41: =C41 -> 408.023 | GS41: =E41 -> 0 | GT41: =B41 -> Биогром Холин
A42: =A41+1 -> 32 | B42: Биоплекс марганец | C42: ='1_квартал'!G41 -> 910.763 | D42: =662.843+188.127 -> 850.97 | E42: 712.48 | G42: =ROUND(AVERAGE(D42:F42),3) -> 781.725 | H42: =598.393+1000 -> 1598.393 | I42: =338.263+1000 -> 1338.263 | K42: =23.52*3 -> 70.56 | N42: =8.064*5 -> 40.32 | O42: =2.352*2.7 -> 6.3504 | P42: =23.52*2.4 -> 56.448 | Q42: =3.36*0.6 -> 2.016 | R42: 100.8 | S42: =2.352*7.5 -> 17.64 | T42: =6.72*3.5 -> 23.52 | U42: =17.674*0.6 -> 10.6044 | V42: =11.76*1.6 -> 18.816 | W42: =2.352*0.6 -> 1.4112 | X42: =6.72*3 -> 20.16 | Y42: =17.674 -> 17.674 | Z42: 2.822 | AA42: =8.4*0.9 -> 7.56 | AB42: =2.352*3 -> 7.056 | AC42: =23.52*2 -> 47.04 | AD42: =3.36*5 -> 16.8 | AE42: =17.674*1.3 -> 22.9762 | AF42: =8.837*0.6 -> 5.3022 | AG42: 6.048 | AJ42: =7.056*1.4 -> 9.8784 | AK42: 1.008 | AM42: =11.76*3 -> 35.28 | AN42: 5.04 | AO42: 3.36 | AQ42: 0.04 | AS42: 0.013 | AX42: =23.52*5 -> 117.6 | AY42: =5.544 -> 5.544 | AZ42: 14.112 | BA42: =8.4 -> 8.4 | BB42: =17.674*1.5 -> 26.511 | BC42: =3.629/1.2*0.3 -> 0.90725 | BD42: =0.403/0.3*0.1 -> 0.13433333 | BE42: 0.302 | BI42: 17.674 | BJ42: =28.654/8*1.8 -> 6.44715 | BK42: =28.654/8*1.5 -> 5.372625 | BM42: =8.837*0.6 -> 5.3022 | BP42: =28.654/8*4.7 -> 16.834225 | BR42: =4.234/0.9*0.8 -> 3.7635556 | BV42: 4.435 | BW42: =11.76*3 -> 35.28 | BX42: 8.064 | BY42: =2.352*3.8 -> 8.9376 | BZ42: =17.674*0.5 -> 8.837 | CA42: =SUM(K42:BZ42) -> 851.00174 | CC42: =23.52*2.4 -> 56.448 | CE42: =2.352*0.6 -> 1.4112 | CF42: =7.056*1.8 -> 12.7008 | CG42: =11.76*1.3 -> 15.288 | CH42: 17.674 | CI42: =8.4*0.9 -> 7.56 | CJ42: =17.674*1.3 -> 22.9762 | CK42: =23.52*5 -> 117.6 | CL42: =2.651/0.3*0.2 -> 1.7673333 | CM42: =11.76*5 -> 58.8 | CN42: 14.112 | CO42: =2.352*6 -> 14.112 | CP42: =10.604/1.2*0.6 -> 5.302 | CQ42: =17.674*2 -> 35.348 | CS42: =8.064*5 -> 40.32 | CU42: =8.4*1.5 -> 12.6 | CV42: =23.52*4 -> 94.08 | CW42: =5.544 -> 5.544 | CY42: =26.51/1.5*0.5 -> 8.8366667 | CZ42: =17.674*1.5 -> 26.511 | DA42: =8.837*2 -> 17.674 | DC42: =14.112/3*3.5 -> 16.464 | DF42: =2.52*1.5 -> 3.78 | DH42: 2.218 | DJ42: 50.4 | DK42: =2.352*5 -> 11.76 | DM42: =2.352*7 -> 16.464 | DP42: =6.72*1.5 -> 10.08 | DQ42: =7.056*1.7 -> 11.9952 | DR42: =8.837*0.3 -> 2.6511 | DU42: =SUM(CC42:DT42) -> 712.4775 | DW42: =23.52*2.4 -> 56.448 | DX42: =17.674*1.3 -> 22.9762 | DY42: =6.72*1.5 -> 10.08 | DZ42: 17.674 | EA42: =23.52*5 -> 117.6 | EC42: =17.674*2 -> 35.348 | GA42: =SUM(DW42:FZ42) -> 260.1262 | GD42: =6.72*0.9 -> 6.048 | GE42: =4.704*0.9 -> 4.2336 | GG42: =8.837*1.2 -> 10.6044 | GH42: =11.76*3 -> 35.28 | GO42: =SUM(GC42:GN42) -> 56.166 | GP42: =I42-GO42 -> 1282.097 | GQ42: =I42 -> 1338.263 | GR42: =C42 -> 910.763 | GS42: =E42 -> 712.48 | GT42: =B42 -> Биоплекс марганец
A43: =A42+1 -> 33 | B43: Биоплекс медь | C43: ='1_квартал'!G42 -> 756.803 | D43: =625.537+55.903 -> 681.44 | E43: =374.463+183.947 -> 558.41 | G43: =ROUND(AVERAGE(D43:F43),3) -> 619.925 | H43: =816.053+1000 -> 1816.053 | I43: =603.873+1000 -> 1603.873 | K43: =20.16*3 -> 60.48 | O43: =2.419*2.7 -> 6.5313 | P43: =20.16*2.4 -> 48.384 | Q43: =2.419*0.6 -> 1.4514 | R43: 100.8 | S43: =2.419*7.5 -> 18.1425 | T43: =4.838*3.5 -> 16.933 | U43: =12.751*0.6 -> 7.6506 | V43: =10.08*1.6 -> 16.128 | W43: =2.419*0.6 -> 1.4514 | X43: =4.838*3 -> 14.514 | Y43: =12.751 -> 12.751 | Z43: 2.419 | AA43: =3.528*0.9 -> 3.1752 | AB43: =2.419*3 -> 7.257 | AC43: =20.16*2 -> 40.32 | AD43: =5.04*5 -> 25.2 | AE43: =12.751*1.3 -> 16.5763 | AF43: =6.376*0.6 -> 3.8256 | AG43: 4.355 | AJ43: =6.048*1.4 -> 8.4672 | AM43: =10.08*3 -> 30.24 | AN43: 7.56 | AO43: 2.419 | AQ43: 0.048 | AS43: 0.02 | AX43: =20.16*5 -> 100.8 | AY43: =3.024 -> 3.024 | AZ43: 12.096 | BA43: =3.528 -> 3.528 | BB43: =12.751*1.5 -> 19.1265 | BC43: =5.443/1.2*0.3 -> 1.36075 | BD43: =0.242/0.3*0.1 -> 0.080666667 | BE43: 0.454 | BI43: 12.751 | BJ43: =8.064/8*1.8 -> 1.8144 | BK43: =8.064/8*1.5 -> 1.512 | BM43: =6.376*0.6 -> 3.8256 | BN43: =0.504*0.6 -> 0.3024 | BP43: =8.064/8*4.7 -> 4.7376 | BR43: =1.814/0.9*0.8 -> 1.6124444 | BV43: 6.653 | BW43: =10.08*3 -> 30.24 | BX43: 4.838 | BY43: =2.419*3.8 -> 9.1922 | BZ43: =12.751*0.5 -> 6.3755 | CA43: =SUM(K43:BZ43) -> 681.42356 | CC43: =20.16*2.4 -> 48.384 | CE43: =2.419*0.6 -> 1.4514 | CF43: =6.048*1.8 -> 10.8864 | CG43: =10.08*1.3 -> 13.104 | CH43: 12.751 | CI43: =3.528*0.9 -> 3.1752 | CJ43: =12.751*1.3 -> 16.5763 | CK43: =20.16*5 -> 100.8 | CL43: =1.913/0.3*0.2 -> 1.2753333 | CM43: =10.08*5 -> 50.4 | CN43: 6.048 | CO43: =2.419*6 -> 14.514 | CP43: =7.651/1.2*0.6 -> 3.8255 | CQ43: =12.751*2 -> 25.502 | CU43: =3.528*1.5 -> 5.292 | CV43: =20.16*4 -> 80.64 | CW43: =3.024 -> 3.024 | CY43: =19.127/1.5*0.5 -> 6.3756667 | CZ43: =12.751*1.5 -> 19.1265 | DA43: 12.751 | DC43: =12.096/3*3.5 -> 14.112 | DF43: =3.78*1.5 -> 5.67 | DH43: 3.326 | DJ43: 50.4 | DK43: =2.419*5 -> 12.095 | DL43: 0.504 | DM43: =2.419*7 -> 16.933 | DP43: =4.838*1.5 -> 7.257 | DQ43: =6.048*1.7 -> 10.2816 | DR43: =6.376*0.3 -> 1.9128 | DU43: =SUM(CC43:DT43) -> 558.3937 | DW43: =20.16*2.4 -> 48.384 | DX43: =12.751*1.3 -> 16.5763 | DY43: =4.838*1.5 -> 7.257 | DZ43: 12.751 | EA43: =20.16*5 -> 100.8 | EC43: =12.751*2 -> 25.502 | EE43: =0.504*1.8 -> 0.9072 | GA43: =SUM(DW43:FZ43) -> 212.1775 | GD43: =4.838*0.9 -> 4.3542 | GE43: =4.032*0.9 -> 3.6288 | GG43: =6.376*1.2 -> 7.6512 | GH43: =10.08*3 -> 30.24 | GO43: =SUM(GC43:GN43) -> 45.8742 | GP43: =I43-GO43 -> 1557.9988 | GQ43: =I43 -> 1603.873 | GR43: =C43 -> 756.803 | GS43: =E43 -> 558.41 | GT43: =B43 -> Биоплекс медь
A44: =A43+1 -> 34 | B44: Биоплекс цинк | C44: ='1_квартал'!G43 -> 1571.233 | D44: =811.823+594.057 -> 1405.88 | E44: =1238.18 -> 1238.18 | G44: =ROUND(AVERAGE(D44:F44),3) -> 1322.03 | H44: =916.763+250+999 -> 2165.763 | I44: =517.003+250+999 -> 1766.003 | K44: =43.68*3 -> 131.04 | N44: =14.112*5 -> 70.56 | O44: =4.704*2.7 -> 12.7008 | P44: =43.68*2.4 -> 104.832 | Q44: =2.822*0.6 -> 1.6932 | R44: 134.4 | S44: =4.704*7.5 -> 35.28 | T44: =5.376*3.5 -> 18.816 | U44: =14.515*0.6 -> 8.709 | V44: =21.84*1.6 -> 34.944 | W44: =4.704*0.6 -> 2.8224 | X44: =5.376*3 -> 16.128 | Y44: =14.515 -> 14.515 | Z44: 4.838 | AA44: =8.4*0.9 -> 7.56 | AB44: =4.704*3 -> 14.112 | AC44: =43.68*2 -> 87.36 | AD44: =5.04*5 -> 25.2 | AE44: =14.515*1.3 -> 18.8695 | AF44: =7.258*0.6 -> 4.3548 | AG44: 4.838 | AH44: =7.728*2 -> 15.456 | AI44: =7.728*8 -> 61.824 | AJ44: =13.104*1.4 -> 18.3456 | AK44: 6.048 | AM44: =21.84*3 -> 65.52 | AN44: 10.08 | AO44: 2.822 | AR44: 1.21 | AS44: 0.008 | AX44: =43.68*5 -> 218.4 | AY44: =7.056 -> 7.056 | AZ44: 24.192 | BA44: =8.4 -> 8.4 | BB44: =14.515*1.5 -> 21.7725 | BC44: =7.258/1.2*0.3 -> 1.8145 | BD44: =0.403/0.3*0.1 -> 0.13433333 | BE44: 0.605 | BF44: =1.21/0.6*0.7 -> 1.4116667 | BI44: 14.515 | BJ44: =53.76/8*1.8 -> 12.096 | BK44: =53.76/8*1.5 -> 10.08 | BL44: 1.21 | BM44: =7.258*0.6 -> 4.3548 | BN44: =3.36*0.6 -> 2.016 | BP44: =53.76/8*4.7 -> 31.584 | BR44: =4.234/0.9*0.8 -> 3.7635556 | BV44: 8.87 | BW44: =21.84*3 -> 65.52 | BX44: 8.064 | BY44: =4.704*3.8 -> 17.8752 | BZ44: =14.515*0.5 -> 7.2575 | CA44: =SUM(K44:BZ44) -> 1405.8784 | CC44: =43.68*2.4 -> 104.832 | CE44: =4.704*0.6 -> 2.8224 | CF44: =13.104*1.8 -> 23.5872 | CG44: =21.84*1.3 -> 28.392 | CH44: 14.515 | CI44: =8.4*0.9 -> 7.56 | CJ44: =14.515*1.3 -> 18.8695 | CK44: =43.68*5 -> 218.4 | CL44: =2.177/0.3*0.2 -> 1.4513333 | CM44: =21.84*5 -> 109.2 | CN44: 14.112 | CO44: =4.704*6 -> 28.224 | CP44: =8.709/1.2*0.6 -> 4.3545 | CQ44: =14.515*2 -> 29.03 | CR44: 1.21 | CS44: =12.096*5 -> 60.48 | CU44: =8.4*1.5 -> 12.6 | CV44: =43.68*4 -> 174.72 | CW44: =7.056 -> 7.056 | CY44: =21.773/1.5*0.5 -> 7.2576667 | CZ44: =14.515*1.5 -> 21.7725 | DA44: 14.515 | DB44: =30.24 -> 30.24 | DC44: =24.192/3*3.5 -> 28.224 | DD44: =6.72*7 -> 47.04 | DE44: =6.72*3 -> 20.16 | DF44: =5.04*1.5 -> 7.56 | DH44: 4.435 | DJ44: 67.2 | DK44: =4.704*5 -> 23.52 | DL44: 3.36 | DM44: =4.704*7 -> 32.928 | DO44: =2.016*1.2 -> 2.4192 | DP44: =5.376*1.5 -> 8.064 | DQ44: =13.104*1.7 -> 22.2768 | DR44: =7.258*0.3 -> 2.1774 | DT44: =6.72*5 -> 33.6 | DU44: =SUM(CC44:DT44) -> 1238.1655 | DW44: =43.68*2.4 -> 104.832 | DX44: =14.515*1.3 -> 18.8695 | DY44: =5.376*1.5 -> 8.064 | DZ44: 14.515 | EA44: =43.68*5 -> 218.4 | EC44: =14.515*2 -> 29.03 | EE44: =3.36*1.8 -> 6.048 | GA44: =SUM(DW44:FZ44) -> 399.7585 | GD44: =5.376*0.9 -> 4.8384 | GE44: =8.064*0.9 -> 7.2576 | GF44: =10.08*3 -> 30.24 | GG44: =7.258*1.2 -> 8.7096 | GH44: =21.84*3 -> 65.52 | GO44: =SUM(GC44:GN44) -> 116.5656 | GP44: =I44-GO44 -> 1649.4374 | GQ44: =I44 -> 1766.003 | GR44: =C44 -> 1571.233 | GS44: =E44 -> 1238.18 | GT44: =B44 -> Биоплекс цинк
A45: =A44+1 -> 35 | B45: Биопромис Селен Пауэр | C45: ='1_квартал'!G44 -> 0 | D45: 0 | E45: 0 | G45: =ROUND(AVERAGE(D45:F45),3) -> 0 | H45: 0 | I45: 0 | CA45: =SUM(K45:BZ45) -> 0 | DU45: =SUM(CC45:DT45) -> 0 | GA45: =SUM(DW45:FZ45) -> 0 | GO45: =SUM(GC45:GN45) -> 0 | GP45: =I45-GO45 -> 0 | GQ45: =I45 -> 0 | GR45: =C45 -> 0 | GS45: =E45 -> 0 | GT45: =B45 -> Биопромис Селен Пауэр
A46: =A45+1 -> 36 | B46: Биопромис Хром пиколинат | C46: ='1_квартал'!G45 -> 56.997 | D46: 68.81 | E46: =0.27+10.45 -> 10.72 | G46: =ROUND(AVERAGE(D46:F46),3) -> 39.765 | H46: =25+12.55 -> 37.55 | I46: =25+4.76 -> 29.76 | AR46: 3.574 | BC46: =8.247/1.2*0.3 -> 2.06175 | BD46: =1.374/0.3*0.1 -> 0.458 | BF46: =3.574/0.6*0.7 -> 4.1696667 | BJ46: =54.98/8*1.8 -> 12.3705 | BK46: =54.98/8*1.5 -> 10.30875 | BL46: 3.574 | BP46: =54.98/8*4.7 -> 32.30075 | CA46: =SUM(K46:BZ46) -> 68.817417 | CR46: 3.574 | DO46: =5.956*1.2 -> 7.1472 | DU46: =SUM(CC46:DT46) -> 10.7212 | EB46: =2.598*3 -> 7.794 | GA46: =SUM(DW46:FZ46) -> 7.794 | GO46: =SUM(GC46:GN46) -> 0 | GP46: =I46-GO46 -> 29.76 | GQ46: =I46 -> 29.76 | GR46: =C46 -> 56.997 | GS46: =E46 -> 10.72 | GT46: =B46 -> Биопромис Хром пиколинат
A47: =A46+1 -> 37 | B47: Виусид-Вет | C47: ='1_квартал'!G46 -> 98.52 | D47: 19.48 | E47: 0 | G47: =ROUND(AVERAGE(D47:F47),3) -> 9.74 | H47: 18.84 | I47: 18.84 | U47: =2.318*0.6 -> 1.3908 | Y47: =2.318 -> 2.318 | AE47: =4.536*1.3 -> 5.8968 | AS47: 6.693 | BG47: 2.016 | BZ47: =2.318*0.5 -> 1.159 | CA47: =SUM(K47:BZ47) -> 19.4736 | DU47: =SUM(CC47:DT47) -> 0 | GA47: =SUM(DW47:FZ47) -> 0 | GO47: =SUM(GC47:GN47) -> 0 | GP47: =I47-GO47 -> 18.84 | GQ47: =I47 -> 18.84 | GR47: =C47 -> 98.52 | GS47: =E47 -> 0 | GT47: =B47 -> Виусид-Вет
A48: =A47+1 -> 38 | B48: Декстроза | C48: ='1_квартал'!G47 -> 9645.257 | D48: 9143.06 | E48: =5720.17+2966.27 -> 8686.44 | G48: =ROUND(AVERAGE(D48:F48),3) -> 8914.75 | H48: =4033.73+3000 -> 7033.73 | I48: =4033.73+3000 -> 7033.73 | O48: =302.4*2.7 -> 816.48 | S48: =302.4*7.5 -> 2268 | W48: =302.4*0.6 -> 181.44 | Z48: 120.96 | AB48: =302.4*3 -> 907.2 | AG48: 54.432 | AL48: 48.384 | AQ48: 60.48 | AS48: 40.32 | AZ48: 604.8 | BC48: =60.48/1.2*0.3 -> 15.12 | BD48: =15.12/0.3*0.1 -> 5.04 | BE48: 15.12 | BJ48: =645.12/8*1.8 -> 145.152 | BK48: =645.12/8*1.5 -> 120.96 | BO48: =221.76*5 -> 1108.8 | BP48: =645.12/8*4.7 -> 379.008 | BQ48: 945 | BX48: 157.248 | BY48: =302.4*3.8 -> 1149.12 | CA48: =SUM(K48:BZ48) -> 9143.064 | CE48: =302.4*0.6 -> 181.44 | CN48: 302.4 | CO48: =302.4*6 -> 1814.4 | CT48: =221.76*5 -> 1108.8 | DC48: =604.8/3*3.5 -> 705.6 | DG48: 945 | DK48: =302.4*5 -> 1512 | DM48: =302.4*7 -> 2116.8 | DU48: =SUM(CC48:DT48) -> 8686.44 | GA48: =SUM(DW48:FZ48) -> 0 | GD48: =60.48*0.9 -> 54.432 | GE48: =201.6*0.9 -> 181.44 | GO48: =SUM(GC48:GN48) -> 235.872 | GP48: =I48-GO48 -> 6797.858 | GQ48: =I48 -> 7033.73 | GR48: =C48 -> 9645.257 | GS48: =E48 -> 8686.44 | GT48: =B48 -> Декстроза
A49: =A48+1 -> 39 | B49: Диоксид кремния Экстрасил | C49: ='1_квартал'!G48 -> 0 | D49: 7.26 | E49: 10.89 | G49: =ROUND(AVERAGE(D49:F49),3) -> 9.075 | H49: 31.82 | I49: 25.77 | BH49: =4.032*0.6 -> 2.4192 | BT49: =4.032*1.2 -> 4.8384 | CA49: =SUM(K49:BZ49) -> 7.2576 | CX49: =4.032*1.2 -> 4.8384 | DN49: =4.032*1.5 -> 6.048 | DU49: =SUM(CC49:DT49) -> 10.8864 | ED49: =4.032*1.5 -> 6.048 | GA49: =SUM(DW49:FZ49) -> 6.048 | GO49: =SUM(GC49:GN49) -> 0 | GP49: =I49-GO49 -> 25.77 | GQ49: =I49 -> 25.77 | GR49: =C49 -> 0 | GS49: =E49 -> 10.89 | GT49: =B49 -> Диоксид кремния Экстрасил
